{"entities":[{"end":12,"category":"I-MISC","begin":4},{"end":54,"category":"I-PER","begin":41},{"end":109,"category":"I-MISC","begin":100},{"end":1105,"category":"I-MISC","begin":1096},{"end":1715,"category":"I-MISC","begin":1706},{"end":1820,"category":"I-MISC","begin":1812},{"end":2060,"category":"I-LOC","begin":2049},{"end":2365,"category":"I-PER","begin":2350},{"end":2479,"category":"I-PER","begin":2470},{"end":3527,"category":"I-PER","begin":3514},{"end":3608,"category":"I-PER","begin":3602},{"end":3632,"category":"I-MISC","begin":3623},{"end":4066,"category":"I-MISC","begin":4052},{"end":4239,"category":"I-MISC","begin":4229},{"end":4435,"category":"I-MISC","begin":4422},{"end":4515,"category":"I-PER","begin":4511},{"end":5304,"category":"I-ORG","begin":5292},{"end":5588,"category":"I-MISC","begin":5579},{"end":5675,"category":"I-LOC","begin":5669},{"end":5691,"category":"I-MISC","begin":5682},{"end":5793,"category":"I-LOC","begin":5781},{"end":5982,"category":"I-MISC","begin":5973},{"end":6344,"category":"I-PER","begin":6331},{"end":6344,"category":"I-PER","begin":6331},{"end":6519,"category":"I-PER","begin":6508},{"end":6519,"category":"I-PER","begin":6508},{"end":6538,"category":"I-ORG","begin":6530},{"end":6538,"category":"I-ORG","begin":6530},{"end":6558,"category":"I-LOC","begin":6552},{"end":6558,"category":"I-LOC","begin":6552},{"end":6570,"category":"I-LOC","begin":6563},{"end":6570,"category":"I-LOC","begin":6563}],"sentences":[{"end":23,"begin":0},{"end":109,"begin":26},{"end":1042,"begin":1019},{"end":1201,"begin":1045},{"end":1429,"begin":1202},{"end":1543,"begin":1430},{"end":1727,"begin":1546},{"end":1843,"begin":1728},{"end":1996,"begin":1844},{"end":2170,"begin":1997},{"end":2321,"begin":2173},{"end":2348,"begin":2322},{"end":2536,"begin":2349},{"end":2669,"begin":2537},{"end":2906,"begin":2670},{"end":3257,"begin":2909},{"end":3328,"begin":3258},{"end":3513,"begin":3329},{"end":3587,"begin":3514},{"end":3646,"begin":3588},{"end":3814,"begin":3649},{"end":3999,"begin":3815},{"end":4146,"begin":4000},{"end":4180,"begin":4147},{"end":4226,"begin":4181},{"end":4256,"begin":4229},{"end":4356,"begin":4259},{"end":4536,"begin":4357},{"end":5000,"begin":4537},{"end":5081,"begin":5003},{"end":5365,"begin":5082},{"end":5467,"begin":5366},{"end":5702,"begin":5468},{"end":5892,"begin":5703},{"end":6008,"begin":5893},{"end":6152,"begin":6009},{"end":6202,"begin":6153},{"end":6237,"begin":6203},{"end":6291,"begin":6240},{"end":6327,"begin":6292},{"end":6425,"begin":6330},{"end":6344,"begin":6331},{"end":6425,"begin":6347},{"end":6472,"begin":6426},{"end":6472,"begin":6426},{"end":6540,"begin":6473},{"end":6540,"begin":6473},{"end":6571,"begin":6541},{"end":6571,"begin":6541}],"claims":[],"tokens":[{"pos":"ART","end":3,"begin":0},{"pos":"ADJA","end":12,"begin":4},{"pos":"NN","end":23,"begin":13},{"pos":"NN","end":36,"begin":26},{"pos":"APPR","end":40,"begin":37},{"pos":"NE","end":46,"begin":41},{"pos":"NN","end":54,"begin":47},{"pos":"ADJA","end":63,"begin":56},{"pos":"NN","end":71,"begin":64},{"pos":"APPRART","end":75,"begin":72},{"pos":"NN","end":84,"begin":76},{"pos":"ART","end":88,"begin":85},{"pos":"ADJA","end":99,"begin":89},{"pos":"NN","end":109,"begin":100},{"pos":"NN","end":1025,"begin":1019},{"pos":"ART","end":1029,"begin":1026},{"pos":"NN","end":1042,"begin":1030},{"pos":"ADV","end":1054,"begin":1045},{"pos":"VVFIN","end":1065,"begin":1055},{"pos":"PPER","end":1068,"begin":1066},{"pos":"PTKNEG","end":1074,"begin":1069},{"pos":"$,","end":1075,"begin":1074},{"pos":"KOUS","end":1080,"begin":1076},{"pos":"ART","end":1084,"begin":1081},{"pos":"NN","end":1091,"begin":1085},{"pos":"ART","end":1095,"begin":1092},{"pos":"ADJA","end":1105,"begin":1096},{"pos":"NN","end":1118,"begin":1106},{"pos":"$,","end":1119,"begin":1118},{"pos":"ART","end":1123,"begin":1120},{"pos":"NN","end":1136,"begin":1124},{"pos":"$,","end":1137,"begin":1136},{"pos":"APPR","end":1140,"begin":1138},{"pos":"PIS","end":1146,"begin":1141},{"pos":"PDAT","end":1153,"begin":1147},{"pos":"NN","end":1160,"begin":1154},{"pos":"ART","end":1164,"begin":1161},{"pos":"NN","end":1170,"begin":1165},{"pos":"ART","end":1174,"begin":1171},{"pos":"$(","end":1177,"begin":1176},{"pos":"NN","end":1190,"begin":1177},{"pos":"$(","end":1191,"begin":1190},{"pos":"VVFIN","end":1200,"begin":1193},{"pos":"$.","end":1201,"begin":1200},{"pos":"ADV","end":1207,"begin":1202},{"pos":"ADV","end":1212,"begin":1208},{"pos":"VVFIN","end":1223,"begin":1213},{"pos":"PPER","end":1226,"begin":1224},{"pos":"ART","end":1230,"begin":1227},{"pos":"ADJA","end":1241,"begin":1231},{"pos":"NN","end":1247,"begin":1242},{"pos":"ART","end":1251,"begin":1248},{"pos":"ADJA","end":1262,"begin":1252},{"pos":"NN","end":1274,"begin":1263},{"pos":"ADV","end":1286,"begin":1275},{"pos":"$,","end":1287,"begin":1286},{"pos":"KOUS","end":1291,"begin":1288},{"pos":"PRF","end":1296,"begin":1292},{"pos":"ADV","end":1299,"begin":1297},{"pos":"PTKVZ","end":1303,"begin":1300},{"pos":"KON","end":1309,"begin":1304},{"pos":"APPR","end":1315,"begin":1310},{"pos":"NN","end":1325,"begin":1316},{"pos":"ADV","end":1330,"begin":1326},{"pos":"APPR","end":1336,"begin":1331},{"pos":"NN","end":1342,"begin":1337},{"pos":"ADJA","end":1352,"begin":1343},{"pos":"NN","end":1362,"begin":1353},{"pos":"KON","end":1366,"begin":1363},{"pos":"APPR","end":1369,"begin":1367},{"pos":"ART","end":1373,"begin":1370},{"pos":"ADJA","end":1388,"begin":1374},{"pos":"KON","end":1392,"begin":1389},{"pos":"ADJA","end":1403,"begin":1393},{"pos":"NN","end":1409,"begin":1404},{"pos":"ADV","end":1416,"begin":1410},{"pos":"VVFIN","end":1428,"begin":1417},{"pos":"$.","end":1429,"begin":1428},{"pos":"PIS","end":1433,"begin":1430},{"pos":"VMFIN","end":1438,"begin":1434},{"pos":"ADV","end":1445,"begin":1439},{"pos":"VVINF","end":1452,"begin":1446},{"pos":"$,","end":1453,"begin":1452},{"pos":"VVINF","end":1463,"begin":1454},{"pos":"$,","end":1464,"begin":1463},{"pos":"VVFIN","end":1476,"begin":1465},{"pos":"$,","end":1477,"begin":1476},{"pos":"KON","end":1481,"begin":1478},{"pos":"PDS","end":1485,"begin":1482},{"pos":"$,","end":1486,"begin":1485},{"pos":"ADV","end":1489,"begin":1487},{"pos":"VVFIN","end":1499,"begin":1490},{"pos":"$,","end":1500,"begin":1499},{"pos":"VVFIN","end":1506,"begin":1501},{"pos":"PRF","end":1511,"begin":1507},{"pos":"ADJD","end":1515,"begin":1512},{"pos":"APPR","end":1518,"begin":1516},{"pos":"NN","end":1520,"begin":1519},{"pos":"KON","end":1524,"begin":1521},{"pos":"VVFIN","end":1533,"begin":1525},{"pos":"PRF","end":1538,"begin":1534},{"pos":"ADJD","end":1542,"begin":1539},{"pos":"$.","end":1543,"begin":1542},{"pos":"ART","end":1549,"begin":1546},{"pos":"ADJA","end":1559,"begin":1550},{"pos":"NN","end":1565,"begin":1560},{"pos":"ART","end":1569,"begin":1566},{"pos":"ADJA","end":1580,"begin":1570},{"pos":"NN","end":1592,"begin":1581},{"pos":"VVFIN","end":1600,"begin":1593},{"pos":"APPR","end":1603,"begin":1601},{"pos":"PDAT","end":1610,"begin":1604},{"pos":"CARD","end":1615,"begin":1611},{"pos":"TRUNC","end":1625,"begin":1616},{"pos":"KON","end":1629,"begin":1626},{"pos":"NN","end":1642,"begin":1630},{"pos":"APPR","end":1647,"begin":1643},{"pos":"NE","end":1666,"begin":1648},{"pos":"APPR","end":1670,"begin":1667},{"pos":"PIS","end":1676,"begin":1671},{"pos":"ART","end":1680,"begin":1677},{"pos":"ADJA","end":1693,"begin":1681},{"pos":"NN","end":1701,"begin":1694},{"pos":"ART","end":1705,"begin":1702},{"pos":"ADJA","end":1715,"begin":1706},{"pos":"NN","end":1722,"begin":1716},{"pos":"PTKVZ","end":1726,"begin":1723},{"pos":"$.","end":1727,"begin":1726},{"pos":"ADV","end":1732,"begin":1728},{"pos":"VAFIN","end":1737,"begin":1733},{"pos":"ADV","end":1742,"begin":1738},{"pos":"VVPP","end":1754,"begin":1743},{"pos":"KON","end":1758,"begin":1755},{"pos":"VVPP","end":1767,"begin":1759},{"pos":"$,","end":1768,"begin":1767},{"pos":"PRELS","end":1772,"begin":1769},{"pos":"ART","end":1776,"begin":1773},{"pos":"ADJD","end":1789,"begin":1777},{"pos":"APPR","end":1794,"begin":1790},{"pos":"ADV","end":1801,"begin":1795},{"pos":"ADJA","end":1811,"begin":1802},{"pos":"ADJA","end":1820,"begin":1812},{"pos":"NN","end":1831,"begin":1821},{"pos":"VAINF","end":1837,"begin":1832},{"pos":"VMFIN","end":1842,"begin":1838},{"pos":"$.","end":1843,"begin":1842},{"pos":"KON","end":1848,"begin":1844},{"pos":"KOUS","end":1852,"begin":1849},{"pos":"PPER","end":1855,"begin":1853},{"pos":"ADV","end":1858,"begin":1856},{"pos":"VVFIN","end":1863,"begin":1859},{"pos":"APPR","end":1867,"begin":1864},{"pos":"PIAT","end":1875,"begin":1868},{"pos":"NN","end":1886,"begin":1876},{"pos":"$.","end":1887,"begin":1886},{"pos":"PPER","end":1890,"begin":1888},{"pos":"VVFIN","end":1897,"begin":1891},{"pos":"ADV","end":1908,"begin":1898},{"pos":"ADV","end":1913,"begin":1909},{"pos":"PAV","end":1922,"begin":1914},{"pos":"KOKOM","end":1926,"begin":1923},{"pos":"ART","end":1930,"begin":1927},{"pos":"ADJA","end":1937,"begin":1931},{"pos":"TRUNC","end":1949,"begin":1938},{"pos":"KON","end":1953,"begin":1950},{"pos":"NN","end":1968,"begin":1954},{"pos":"APPR","end":1971,"begin":1969},{"pos":"ART","end":1975,"begin":1972},{"pos":"NN","end":1983,"begin":1976},{"pos":"ART","end":1987,"begin":1984},{"pos":"NN","end":1995,"begin":1988},{"pos":"$.","end":1996,"begin":1995},{"pos":"PPER","end":1999,"begin":1997},{"pos":"VVFIN","end":2006,"begin":2000},{"pos":"PRF","end":2011,"begin":2007},{"pos":"PTKNEG","end":2017,"begin":2012},{"pos":"ADV","end":2021,"begin":2018},{"pos":"ART","end":2025,"begin":2022},{"pos":"ADJA","end":2037,"begin":2026},{"pos":"NN","end":2045,"begin":2038},{"pos":"APPR","end":2048,"begin":2046},{"pos":"NE","end":2060,"begin":2049},{"pos":"$,","end":2061,"begin":2060},{"pos":"PPER","end":2064,"begin":2062},{"pos":"VVFIN","end":2071,"begin":2065},{"pos":"PRF","end":2076,"begin":2072},{"pos":"ADV","end":2085,"begin":2077},{"pos":"ART","end":2089,"begin":2086},{"pos":"NN","end":2093,"begin":2090},{"pos":"$,","end":2094,"begin":2093},{"pos":"KOUS","end":2098,"begin":2095},{"pos":"PPER","end":2102,"begin":2099},{"pos":"VVFIN","end":2111,"begin":2103},{"pos":"$,","end":2112,"begin":2111},{"pos":"KON","end":2116,"begin":2113},{"pos":"ART","end":2120,"begin":2117},{"pos":"NN","end":2124,"begin":2121},{"pos":"$,","end":2125,"begin":2124},{"pos":"KOUS","end":2129,"begin":2126},{"pos":"PPER","end":2133,"begin":2130},{"pos":"APPR","end":2136,"begin":2134},{"pos":"ADJA","end":2148,"begin":2137},{"pos":"NN","end":2156,"begin":2149},{"pos":"VVPP","end":2164,"begin":2157},{"pos":"VAFIN","end":2169,"begin":2165},{"pos":"$.","end":2170,"begin":2169},{"pos":"ART","end":2177,"begin":2173},{"pos":"NN","end":2183,"begin":2178},{"pos":"PAV","end":2188,"begin":2184},{"pos":"$.","end":2189,"begin":2188},{"pos":"APPR","end":2193,"begin":2190},{"pos":"ART","end":2197,"begin":2194},{"pos":"NN","end":2208,"begin":2198},{"pos":"ART","end":2212,"begin":2209},{"pos":"NN","end":2221,"begin":2213},{"pos":"APPR","end":2224,"begin":2222},{"pos":"ART","end":2228,"begin":2225},{"pos":"NN","end":2239,"begin":2229},{"pos":"VAFIN","end":2244,"begin":2240},{"pos":"APPR","end":2247,"begin":2245},{"pos":"ADJA","end":2262,"begin":2248},{"pos":"NN","end":2267,"begin":2263},{"pos":"ART","end":2271,"begin":2268},{"pos":"NN","end":2282,"begin":2272},{"pos":"ART","end":2286,"begin":2283},{"pos":"NN","end":2298,"begin":2287},{"pos":"APPR","end":2301,"begin":2299},{"pos":"ART","end":2305,"begin":2302},{"pos":"NN","end":2320,"begin":2306},{"pos":"$.","end":2321,"begin":2320},{"pos":"$(","end":2324,"begin":2323},{"pos":"PWS","end":2327,"begin":2324},{"pos":"VAFIN","end":2331,"begin":2328},{"pos":"ART","end":2335,"begin":2332},{"pos":"NN","end":2346,"begin":2336},{"pos":"$.","end":2347,"begin":2346},{"pos":"$(","end":2348,"begin":2347},{"pos":"NE","end":2357,"begin":2350},{"pos":"NN","end":2365,"begin":2358},{"pos":"VAFIN","end":2369,"begin":2366},{"pos":"APPR","end":2372,"begin":2370},{"pos":"PPOSAT","end":2379,"begin":2373},{"pos":"ADJA","end":2387,"begin":2380},{"pos":"$,","end":2388,"begin":2387},{"pos":"ADV","end":2393,"begin":2389},{"pos":"ADJA","end":2403,"begin":2394},{"pos":"ADJA","end":2417,"begin":2404},{"pos":"NN","end":2423,"begin":2418},{"pos":"PTKNEG","end":2429,"begin":2424},{"pos":"ADV","end":2433,"begin":2430},{"pos":"ART","end":2437,"begin":2434},{"pos":"NN","end":2443,"begin":2438},{"pos":"VVPP","end":2455,"begin":2444},{"pos":"$,","end":2456,"begin":2455},{"pos":"PRELS","end":2460,"begin":2457},{"pos":"PRF","end":2464,"begin":2461},{"pos":"APPR","end":2469,"begin":2465},{"pos":"NN","end":2479,"begin":2470},{"pos":"ADV","end":2484,"begin":2480},{"pos":"ART","end":2488,"begin":2485},{"pos":"PIAT","end":2494,"begin":2489},{"pos":"ADJA","end":2502,"begin":2495},{"pos":"NN","end":2513,"begin":2503},{"pos":"ART","end":2517,"begin":2514},{"pos":"NN","end":2526,"begin":2518},{"pos":"VVFIN","end":2535,"begin":2527},{"pos":"$.","end":2536,"begin":2535},{"pos":"ART","end":2540,"begin":2537},{"pos":"NN","end":2552,"begin":2541},{"pos":"$(","end":2555,"begin":2554},{"pos":"VVINF","end":2562,"begin":2555},{"pos":"$(","end":2563,"begin":2562},{"pos":"$,","end":2565,"begin":2564},{"pos":"ADV","end":2568,"begin":2566},{"pos":"NN","end":2576,"begin":2569},{"pos":"$.","end":2577,"begin":2576},{"pos":"APPRART","end":2580,"begin":2578},{"pos":"NN","end":2586,"begin":2581},{"pos":"ART","end":2590,"begin":2587},{"pos":"NN","end":2600,"begin":2591},{"pos":"KOKOM","end":2604,"begin":2601},{"pos":"ART","end":2608,"begin":2605},{"pos":"NN","end":2621,"begin":2609},{"pos":"VVFIN","end":2626,"begin":2622},{"pos":"PPER","end":2629,"begin":2627},{"pos":"PIAT","end":2636,"begin":2630},{"pos":"NN","end":2643,"begin":2637},{"pos":"$,","end":2644,"begin":2643},{"pos":"APPR","end":2647,"begin":2645},{"pos":"PRELS","end":2651,"begin":2648},{"pos":"PPER","end":2655,"begin":2652},{"pos":"PTKNEG","end":2661,"begin":2656},{"pos":"VVINF","end":2668,"begin":2662},{"pos":"$.","end":2669,"begin":2668},{"pos":"NN","end":2681,"begin":2670},{"pos":"VVFIN","end":2692,"begin":2682},{"pos":"PTKVZ","end":2697,"begin":2693},{"pos":"KON","end":2701,"begin":2698},{"pos":"APPR","end":2706,"begin":2702},{"pos":"PIAT","end":2711,"begin":2707},{"pos":"PIS","end":2719,"begin":2712},{"pos":"NN","end":2726,"begin":2720},{"pos":"APPR","end":2730,"begin":2727},{"pos":"NN","end":2744,"begin":2731},{"pos":"KON","end":2748,"begin":2745},{"pos":"NN","end":2760,"begin":2749},{"pos":"$,","end":2761,"begin":2760},{"pos":"APPR","end":2765,"begin":2762},{"pos":"PIS","end":2771,"begin":2766},{"pos":"ART","end":2775,"begin":2772},{"pos":"APPR","end":2779,"begin":2776},{"pos":"NN","end":2790,"begin":2780},{"pos":"$,","end":2791,"begin":2790},{"pos":"NN","end":2802,"begin":2792},{"pos":"KON","end":2806,"begin":2803},{"pos":"NN","end":2817,"begin":2807},{"pos":"ADJA","end":2827,"begin":2818},{"pos":"$,","end":2828,"begin":2827},{"pos":"ART","end":2832,"begin":2829},{"pos":"NN","end":2841,"begin":2833},{"pos":"$,","end":2842,"begin":2841},{"pos":"ART","end":2846,"begin":2843},{"pos":"NN","end":2855,"begin":2847},{"pos":"$,","end":2856,"begin":2855},{"pos":"ART","end":2860,"begin":2857},{"pos":"NN","end":2867,"begin":2861},{"pos":"$,","end":2868,"begin":2867},{"pos":"APPRART","end":2871,"begin":2869},{"pos":"NN","end":2876,"begin":2872},{"pos":"$,","end":2877,"begin":2876},{"pos":"PWS","end":2881,"begin":2878},{"pos":"VVFIN","end":2886,"begin":2882},{"pos":"$,","end":2887,"begin":2886},{"pos":"ART","end":2891,"begin":2888},{"pos":"NN","end":2898,"begin":2892},{"pos":"ADV","end":2905,"begin":2899},{"pos":"$.","end":2906,"begin":2905},{"pos":"KOUS","end":2913,"begin":2909},{"pos":"PIS","end":2917,"begin":2914},{"pos":"VVFIN","end":2922,"begin":2918},{"pos":"$,","end":2923,"begin":2922},{"pos":"ART","end":2928,"begin":2924},{"pos":"ADJA","end":2946,"begin":2929},{"pos":"NN","end":2956,"begin":2947},{"pos":"$(","end":2959,"begin":2958},{"pos":"VVFIN","end":2964,"begin":2959},{"pos":"$(","end":2965,"begin":2964},{"pos":"ART","end":2970,"begin":2967},{"pos":"NN","end":2982,"begin":2971},{"pos":"$,","end":2983,"begin":2982},{"pos":"ADV","end":2986,"begin":2984},{"pos":"VVFIN","end":2997,"begin":2987},{"pos":"PIS","end":3001,"begin":2998},{"pos":"ADV","end":3010,"begin":3002},{"pos":"PPOSAT","end":3015,"begin":3011},{"pos":"NN","end":3021,"begin":3016},{"pos":"$(","end":3023,"begin":3022},{"pos":"VVINF","end":3031,"begin":3023},{"pos":"$,","end":3032,"begin":3031},{"pos":"APPR","end":3037,"begin":3033},{"pos":"KOUS","end":3042,"begin":3038},{"pos":"ART","end":3046,"begin":3043},{"pos":"NN","end":3056,"begin":3047},{"pos":"VVINF","end":3063,"begin":3057},{"pos":"KON","end":3068,"begin":3064},{"pos":"PRF","end":3073,"begin":3069},{"pos":"VVINF","end":3082,"begin":3074},{"pos":"VMINF","end":3089,"begin":3083},{"pos":"$,","end":3090,"begin":3089},{"pos":"KOUS","end":3095,"begin":3091},{"pos":"PPER","end":3099,"begin":3096},{"pos":"VVPP","end":3107,"begin":3100},{"pos":"VAINF","end":3114,"begin":3108},{"pos":"$(","end":3115,"begin":3114},{"pos":"KON","end":3119,"begin":3116},{"pos":"PPOSAT","end":3124,"begin":3120},{"pos":"NN","end":3133,"begin":3125},{"pos":"$(","end":3135,"begin":3134},{"pos":"ART","end":3138,"begin":3135},{"pos":"NN","end":3149,"begin":3139},{"pos":"VVFIN","end":3157,"begin":3150},{"pos":"ART","end":3161,"begin":3158},{"pos":"NN","end":3171,"begin":3162},{"pos":"ADV","end":3174,"begin":3172},{"pos":"ADV","end":3179,"begin":3175},{"pos":"KOKOM","end":3183,"begin":3180},{"pos":"$(","end":3186,"begin":3185},{"pos":"ART","end":3189,"begin":3186},{"pos":"NN","end":3194,"begin":3190},{"pos":"$(","end":3195,"begin":3194},{"pos":"$.","end":3197,"begin":3196},{"pos":"PIAT","end":3203,"begin":3198},{"pos":"APPR","end":3207,"begin":3204},{"pos":"PIAT","end":3214,"begin":3208},{"pos":"VMFIN","end":3219,"begin":3215},{"pos":"ADV","end":3226,"begin":3220},{"pos":"KON","end":3231,"begin":3227},{"pos":"$(","end":3234,"begin":3233},{"pos":"APPRART","end":3237,"begin":3234},{"pos":"NN","end":3246,"begin":3238},{"pos":"VVINF","end":3253,"begin":3247},{"pos":"$(","end":3254,"begin":3253},{"pos":"$(","end":3256,"begin":3255},{"pos":"$.","end":3257,"begin":3256},{"pos":"APPR","end":3260,"begin":3258},{"pos":"ART","end":3266,"begin":3261},{"pos":"ADJA","end":3281,"begin":3267},{"pos":"NN","end":3287,"begin":3282},{"pos":"VVFIN","end":3296,"begin":3288},{"pos":"ART","end":3300,"begin":3297},{"pos":"NN","end":3312,"begin":3301},{"pos":"PPOSAT","end":3316,"begin":3313},{"pos":"NN","end":3327,"begin":3317},{"pos":"$.","end":3328,"begin":3327},{"pos":"PPER","end":3331,"begin":3329},{"pos":"VVFIN","end":3338,"begin":3332},{"pos":"$,","end":3339,"begin":3338},{"pos":"KOUS","end":3344,"begin":3340},{"pos":"ADJA","end":3362,"begin":3345},{"pos":"NN","end":3374,"begin":3363},{"pos":"APPR","end":3385,"begin":3375},{"pos":"NN","end":3398,"begin":3386},{"pos":"VVINF","end":3407,"begin":3399},{"pos":"$,","end":3408,"begin":3407},{"pos":"ADV","end":3415,"begin":3409},{"pos":"ADV","end":3420,"begin":3416},{"pos":"VVFIN","end":3427,"begin":3421},{"pos":"$,","end":3428,"begin":3427},{"pos":"KOUS","end":3433,"begin":3429},{"pos":"ART","end":3437,"begin":3434},{"pos":"NN","end":3448,"begin":3438},{"pos":"ART","end":3452,"begin":3449},{"pos":"NN","end":3464,"begin":3453},{"pos":"PRF","end":3469,"begin":3465},{"pos":"ART","end":3473,"begin":3470},{"pos":"ADJA","end":3492,"begin":3474},{"pos":"NN","end":3504,"begin":3493},{"pos":"VVPP","end":3512,"begin":3505},{"pos":"$.","end":3513,"begin":3512},{"pos":"NE","end":3520,"begin":3514},{"pos":"NE","end":3527,"begin":3521},{"pos":"VAFIN","end":3531,"begin":3528},{"pos":"ART","end":3535,"begin":3532},{"pos":"ADJA","end":3542,"begin":3536},{"pos":"NN","end":3550,"begin":3543},{"pos":"APPR","end":3554,"begin":3551},{"pos":"ART","end":3559,"begin":3555},{"pos":"NN","end":3570,"begin":3560},{"pos":"ART","end":3574,"begin":3571},{"pos":"NN","end":3586,"begin":3575},{"pos":"$.","end":3587,"begin":3586},{"pos":"ART","end":3591,"begin":3588},{"pos":"NN","end":3601,"begin":3592},{"pos":"NE","end":3608,"begin":3602},{"pos":"VVFIN","end":3614,"begin":3609},{"pos":"APPR","end":3618,"begin":3615},{"pos":"ART","end":3622,"begin":3619},{"pos":"ADJA","end":3632,"begin":3623},{"pos":"NN","end":3645,"begin":3633},{"pos":"$.","end":3646,"begin":3645},{"pos":"ART","end":3652,"begin":3649},{"pos":"NN","end":3664,"begin":3653},{"pos":"VVFIN","end":3674,"begin":3665},{"pos":"ADJA","end":3681,"begin":3675},{"pos":"NN","end":3687,"begin":3682},{"pos":"$,","end":3688,"begin":3687},{"pos":"KON","end":3693,"begin":3689},{"pos":"PPER","end":3696,"begin":3694},{"pos":"VVFIN","end":3701,"begin":3697},{"pos":"PIAT","end":3706,"begin":3702},{"pos":"ADJA","end":3716,"begin":3707},{"pos":"NN","end":3724,"begin":3717},{"pos":"ART","end":3728,"begin":3725},{"pos":"NN","end":3734,"begin":3729},{"pos":"APPR","end":3739,"begin":3735},{"pos":"PPER","end":3743,"begin":3740},{"pos":"$,","end":3744,"begin":3743},{"pos":"KON","end":3752,"begin":3745},{"pos":"ADV","end":3756,"begin":3753},{"pos":"ADJA","end":3767,"begin":3757},{"pos":"NN","end":3781,"begin":3768},{"pos":"$,","end":3782,"begin":3781},{"pos":"NN","end":3791,"begin":3783},{"pos":"KON","end":3795,"begin":3792},{"pos":"NN","end":3804,"begin":3796},{"pos":"$(","end":3806,"begin":3805},{"pos":"NN","end":3812,"begin":3806},{"pos":"$(","end":3813,"begin":3812},{"pos":"$.","end":3814,"begin":3813},{"pos":"APPR","end":3817,"begin":3815},{"pos":"NN","end":3830,"begin":3818},{"pos":"VVFIN","end":3838,"begin":3831},{"pos":"PRF","end":3843,"begin":3839},{"pos":"PIAT","end":3848,"begin":3844},{"pos":"NN","end":3857,"begin":3849},{"pos":"ART","end":3863,"begin":3858},{"pos":"NN","end":3876,"begin":3864},{"pos":"APPRART","end":3879,"begin":3877},{"pos":"NN","end":3895,"begin":3880},{"pos":"$.","end":3896,"begin":3895},{"pos":"ART","end":3900,"begin":3897},{"pos":"NN","end":3909,"begin":3901},{"pos":"$,","end":3910,"begin":3909},{"pos":"ART","end":3914,"begin":3911},{"pos":"NN","end":3921,"begin":3915},{"pos":"$,","end":3922,"begin":3921},{"pos":"ART","end":3926,"begin":3923},{"pos":"NN","end":3933,"begin":3927},{"pos":"$,","end":3934,"begin":3933},{"pos":"ART","end":3938,"begin":3935},{"pos":"NN","end":3951,"begin":3939},{"pos":"$,","end":3952,"begin":3951},{"pos":"ART","end":3956,"begin":3953},{"pos":"NN","end":3963,"begin":3957},{"pos":"$,","end":3964,"begin":3963},{"pos":"ART","end":3968,"begin":3965},{"pos":"NN","end":3976,"begin":3969},{"pos":"$,","end":3977,"begin":3976},{"pos":"ART","end":3981,"begin":3978},{"pos":"NN","end":3988,"begin":3982},{"pos":"FM","end":3991,"begin":3989},{"pos":"NE","end":3998,"begin":3992},{"pos":"$.","end":3999,"begin":3998},{"pos":"APPRART","end":4002,"begin":4000},{"pos":"NN","end":4013,"begin":4003},{"pos":"VAFIN","end":4020,"begin":4014},{"pos":"PDAT","end":4025,"begin":4021},{"pos":"NN","end":4032,"begin":4026},{"pos":"$,","end":4033,"begin":4032},{"pos":"PRELS","end":4037,"begin":4034},{"pos":"PRF","end":4042,"begin":4038},{"pos":"APPR","end":4045,"begin":4043},{"pos":"ART","end":4051,"begin":4046},{"pos":"ADJA","end":4066,"begin":4052},{"pos":"NN","end":4079,"begin":4067},{"pos":"ADJD","end":4093,"begin":4080},{"pos":"VVINF","end":4105,"begin":4094},{"pos":"KON","end":4109,"begin":4106},{"pos":"VVINF","end":4123,"begin":4110},{"pos":"VMFIN","end":4131,"begin":4124},{"pos":"$,","end":4132,"begin":4131},{"pos":"APPR","end":4135,"begin":4133},{"pos":"NN","end":4145,"begin":4136},{"pos":"$.","end":4146,"begin":4145},{"pos":"KON","end":4151,"begin":4147},{"pos":"PPER","end":4155,"begin":4152},{"pos":"VMFIN","end":4162,"begin":4156},{"pos":"PPER","end":4165,"begin":4163},{"pos":"PTKNEG","end":4171,"begin":4166},{"pos":"VVINF","end":4179,"begin":4172},{"pos":"$.","end":4180,"begin":4179},{"pos":"ADV","end":4191,"begin":4181},{"pos":"VMFIN","end":4198,"begin":4192},{"pos":"PPER","end":4202,"begin":4199},{"pos":"PPER","end":4205,"begin":4203},{"pos":"PTKNEG","end":4211,"begin":4206},{"pos":"ADV","end":4218,"begin":4212},{"pos":"VVINF","end":4225,"begin":4219},{"pos":"$.","end":4226,"begin":4225},{"pos":"NN","end":4239,"begin":4229},{"pos":"APPR","end":4245,"begin":4240},{"pos":"NN","end":4256,"begin":4246},{"pos":"KOUS","end":4263,"begin":4259},{"pos":"ART","end":4267,"begin":4264},{"pos":"NN","end":4278,"begin":4268},{"pos":"ADV","end":4284,"begin":4279},{"pos":"PIS","end":4292,"begin":4285},{"pos":"VAFIN","end":4296,"begin":4293},{"pos":"KOKOM","end":4300,"begin":4297},{"pos":"ART","end":4304,"begin":4301},{"pos":"NN","end":4312,"begin":4305},{"pos":"$,","end":4313,"begin":4312},{"pos":"VMFIN","end":4318,"begin":4314},{"pos":"PAV","end":4324,"begin":4319},{"pos":"ADV","end":4327,"begin":4325},{"pos":"ADV","end":4332,"begin":4328},{"pos":"PIS","end":4340,"begin":4333},{"pos":"VVPP","end":4348,"begin":4341},{"pos":"VAINF","end":4355,"begin":4349},{"pos":"$.","end":4356,"begin":4355},{"pos":"APPRART","end":4359,"begin":4357},{"pos":"NN","end":4370,"begin":4360},{"pos":"VVFIN","end":4381,"begin":4371},{"pos":"PRF","end":4386,"begin":4382},{"pos":"$,","end":4387,"begin":4386},{"pos":"APPRART","end":4391,"begin":4388},{"pos":"NN","end":4400,"begin":4392},{"pos":"$,","end":4401,"begin":4400},{"pos":"ART","end":4405,"begin":4402},{"pos":"NN","end":4417,"begin":4406},{"pos":"APPR","end":4421,"begin":4418},{"pos":"ADJA","end":4435,"begin":4422},{"pos":"NN","end":4448,"begin":4436},{"pos":"$,","end":4449,"begin":4448},{"pos":"PRELS","end":4453,"begin":4450},{"pos":"ADV","end":4460,"begin":4454},{"pos":"ADV","end":4465,"begin":4461},{"pos":"APPR","end":4469,"begin":4466},{"pos":"ART","end":4473,"begin":4470},{"pos":"NN","end":4479,"begin":4474},{"pos":"VVPP","end":4493,"begin":4480},{"pos":"VAFIN","end":4498,"begin":4494},{"pos":"$,","end":4499,"begin":4498},{"pos":"APPR","end":4502,"begin":4500},{"pos":"ADJA","end":4510,"begin":4503},{"pos":"NN","end":4515,"begin":4511},{"pos":"$,","end":4516,"begin":4515},{"pos":"KOUS","end":4523,"begin":4517},{"pos":"PPER","end":4527,"begin":4524},{"pos":"ADV","end":4530,"begin":4528},{"pos":"VAFIN","end":4535,"begin":4531},{"pos":"$.","end":4536,"begin":4535},{"pos":"PPER","end":4539,"begin":4537},{"pos":"VVFIN","end":4547,"begin":4540},{"pos":"ART","end":4551,"begin":4548},{"pos":"PIAT","end":4556,"begin":4552},{"pos":"NN","end":4573,"begin":4557},{"pos":"$.","end":4574,"begin":4573},{"pos":"ART","end":4578,"begin":4575},{"pos":"ADJA","end":4584,"begin":4579},{"pos":"$(","end":4587,"begin":4586},{"pos":"NN","end":4596,"begin":4587},{"pos":"$(","end":4597,"begin":4596},{"pos":"$,","end":4599,"begin":4598},{"pos":"ART","end":4603,"begin":4600},{"pos":"NN","end":4619,"begin":4604},{"pos":"APPR","end":4623,"begin":4620},{"pos":"ART","end":4627,"begin":4624},{"pos":"$(","end":4630,"begin":4629},{"pos":"NN","end":4640,"begin":4630},{"pos":"$(","end":4641,"begin":4640},{"pos":"ART","end":4646,"begin":4643},{"pos":"NN","end":4658,"begin":4647},{"pos":"$,","end":4659,"begin":4658},{"pos":"ART","end":4663,"begin":4660},{"pos":"NN","end":4675,"begin":4664},{"pos":"APPR","end":4679,"begin":4676},{"pos":"$(","end":4682,"begin":4681},{"pos":"NN","end":4705,"begin":4682},{"pos":"$(","end":4706,"begin":4705},{"pos":"$(","end":4709,"begin":4708},{"pos":"KON","end":4712,"begin":4709},{"pos":"VMFIN","end":4719,"begin":4713},{"pos":"PIS","end":4723,"begin":4720},{"pos":"APPR","end":4727,"begin":4724},{"pos":"ART","end":4731,"begin":4728},{"pos":"NN","end":4742,"begin":4732},{"pos":"PTKNEG","end":4748,"begin":4743},{"pos":"VVINF","end":4756,"begin":4749},{"pos":"$(","end":4757,"begin":4756},{"pos":"$,","end":4758,"begin":4757},{"pos":"KON","end":4762,"begin":4759},{"pos":"ADV","end":4768,"begin":4763},{"pos":"VVFIN","end":4773,"begin":4769},{"pos":"PPER","end":4776,"begin":4774},{"pos":"ART","end":4780,"begin":4777},{"pos":"NN","end":4791,"begin":4781},{"pos":"$,","end":4792,"begin":4791},{"pos":"APPR","end":4795,"begin":4793},{"pos":"PRELS","end":4799,"begin":4796},{"pos":"PRF","end":4804,"begin":4800},{"pos":"NN","end":4819,"begin":4805},{"pos":"$,","end":4820,"begin":4819},{"pos":"NN","end":4838,"begin":4821},{"pos":"KON","end":4842,"begin":4839},{"pos":"$(","end":4845,"begin":4844},{"pos":"NN","end":4851,"begin":4845},{"pos":"NN","end":4858,"begin":4852},{"pos":"$(","end":4859,"begin":4858},{"pos":"$(","end":4862,"begin":4861},{"pos":"APPRART","end":4866,"begin":4862},{"pos":"NN","end":4876,"begin":4867},{"pos":"APPR","end":4880,"begin":4877},{"pos":"$(","end":4883,"begin":4882},{"pos":"NN","end":4898,"begin":4883},{"pos":"$(","end":4899,"begin":4898},{"pos":"$(","end":4901,"begin":4900},{"pos":"$(","end":4904,"begin":4903},{"pos":"ADV","end":4913,"begin":4904},{"pos":"$(","end":4914,"begin":4913},{"pos":"VVINF","end":4930,"begin":4916},{"pos":"$,","end":4931,"begin":4930},{"pos":"ADV","end":4939,"begin":4932},{"pos":"APPR","end":4942,"begin":4940},{"pos":"ART","end":4948,"begin":4943},{"pos":"NN","end":4959,"begin":4949},{"pos":"APPR","end":4963,"begin":4960},{"pos":"NN","end":4970,"begin":4964},{"pos":"$,","end":4971,"begin":4970},{"pos":"NN","end":4984,"begin":4972},{"pos":"KON","end":4988,"begin":4985},{"pos":"NN","end":4999,"begin":4989},{"pos":"$.","end":5000,"begin":4999},{"pos":"PPER","end":5005,"begin":5003},{"pos":"VAFIN","end":5009,"begin":5006},{"pos":"APPR","end":5012,"begin":5010},{"pos":"ART","end":5016,"begin":5013},{"pos":"ADJA","end":5024,"begin":5017},{"pos":"NN","end":5031,"begin":5025},{"pos":"ART","end":5035,"begin":5032},{"pos":"ADJA","end":5041,"begin":5036},{"pos":"NN","end":5052,"begin":5042},{"pos":"ART","end":5056,"begin":5053},{"pos":"NN","end":5069,"begin":5057},{"pos":"VVPP","end":5080,"begin":5070},{"pos":"$.","end":5081,"begin":5080},{"pos":"PPER","end":5084,"begin":5082},{"pos":"VAFIN","end":5088,"begin":5085},{"pos":"PTKNEG","end":5094,"begin":5089},{"pos":"ADV","end":5098,"begin":5095},{"pos":"APPRART","end":5102,"begin":5099},{"pos":"NN","end":5119,"begin":5103},{"pos":"ART","end":5123,"begin":5120},{"pos":"ADJA","end":5144,"begin":5124},{"pos":"NN","end":5166,"begin":5145},{"pos":"KON","end":5170,"begin":5167},{"pos":"ART","end":5174,"begin":5171},{"pos":"NN","end":5183,"begin":5175},{"pos":"ART","end":5187,"begin":5184},{"pos":"NN","end":5224,"begin":5188},{"pos":"VVPP","end":5232,"begin":5225},{"pos":"$,","end":5233,"begin":5232},{"pos":"KON","end":5241,"begin":5234},{"pos":"APPR","end":5244,"begin":5242},{"pos":"ART","end":5250,"begin":5245},{"pos":"ADJA","end":5264,"begin":5251},{"pos":"NN","end":5271,"begin":5265},{"pos":"$.","end":5272,"begin":5271},{"pos":"ART","end":5276,"begin":5273},{"pos":"NN","end":5287,"begin":5277},{"pos":"ART","end":5291,"begin":5288},{"pos":"NN","end":5304,"begin":5292},{"pos":"VAFIN","end":5308,"begin":5305},{"pos":"ART","end":5312,"begin":5309},{"pos":"NN","end":5320,"begin":5313},{"pos":"ART","end":5324,"begin":5321},{"pos":"NN","end":5335,"begin":5325},{"pos":"ADV","end":5342,"begin":5336},{"pos":"ADJD","end":5354,"begin":5343},{"pos":"VVPP","end":5364,"begin":5355},{"pos":"$.","end":5365,"begin":5364},{"pos":"NN","end":5376,"begin":5366},{"pos":"VAFIN","end":5381,"begin":5377},{"pos":"APPR","end":5384,"begin":5382},{"pos":"PDAT","end":5391,"begin":5385},{"pos":"NN","end":5402,"begin":5392},{"pos":"PTKNEG","end":5408,"begin":5403},{"pos":"APPR","end":5414,"begin":5409},{"pos":"NN","end":5431,"begin":5415},{"pos":"$,","end":5432,"begin":5431},{"pos":"KON","end":5440,"begin":5433},{"pos":"APPR","end":5446,"begin":5441},{"pos":"NN","end":5458,"begin":5447},{"pos":"VVPP","end":5466,"begin":5459},{"pos":"$.","end":5467,"begin":5466},{"pos":"PAV","end":5475,"begin":5468},{"pos":"VMFIN","end":5480,"begin":5476},{"pos":"ART","end":5484,"begin":5481},{"pos":"NN","end":5500,"begin":5485},{"pos":"PPOSAT","end":5504,"begin":5501},{"pos":"ADJA","end":5516,"begin":5505},{"pos":"KON","end":5520,"begin":5517},{"pos":"ADJA","end":5533,"begin":5521},{"pos":"VVFIN","end":5550,"begin":5534},{"pos":"APPR","end":5560,"begin":5551},{"pos":"ART","end":5566,"begin":5561},{"pos":"NN","end":5574,"begin":5567},{"pos":"ART","end":5578,"begin":5575},{"pos":"ADJA","end":5588,"begin":5579},{"pos":"NN","end":5598,"begin":5589},{"pos":"VVINF","end":5608,"begin":5599},{"pos":"$,","end":5609,"begin":5608},{"pos":"PRELS","end":5613,"begin":5610},{"pos":"ART","end":5617,"begin":5614},{"pos":"ADV","end":5622,"begin":5618},{"pos":"ADJA","end":5634,"begin":5623},{"pos":"NN","end":5639,"begin":5635},{"pos":"VAFIN","end":5643,"begin":5640},{"pos":"$.","end":5644,"begin":5643},{"pos":"ART","end":5648,"begin":5645},{"pos":"ADJA","end":5668,"begin":5649},{"pos":"NE","end":5675,"begin":5669},{"pos":"APPR","end":5681,"begin":5676},{"pos":"ADJA","end":5691,"begin":5682},{"pos":"NN","end":5701,"begin":5692},{"pos":"$.","end":5702,"begin":5701},{"pos":"KON","end":5706,"begin":5703},{"pos":"PAV","end":5715,"begin":5707},{"pos":"VMFIN","end":5720,"begin":5716},{"pos":"ART","end":5724,"begin":5721},{"pos":"PIS","end":5729,"begin":5725},{"pos":"VVINF","end":5735,"begin":5730},{"pos":"$,","end":5736,"begin":5735},{"pos":"ART","end":5740,"begin":5737},{"pos":"NN","end":5750,"begin":5741},{"pos":"VAFIN","end":5756,"begin":5751},{"pos":"ART","end":5761,"begin":5757},{"pos":"NN","end":5768,"begin":5762},{"pos":"PAV","end":5774,"begin":5769},{"pos":"$,","end":5775,"begin":5774},{"pos":"KOUS","end":5780,"begin":5776},{"pos":"NE","end":5793,"begin":5781},{"pos":"$(","end":5796,"begin":5795},{"pos":"APPRART","end":5799,"begin":5796},{"pos":"NN","end":5808,"begin":5800},{"pos":"$(","end":5809,"begin":5808},{"pos":"VVFIN","end":5816,"begin":5811},{"pos":"$,","end":5817,"begin":5816},{"pos":"KON","end":5821,"begin":5818},{"pos":"ART","end":5825,"begin":5822},{"pos":"PIS","end":5832,"begin":5826},{"pos":"$,","end":5833,"begin":5832},{"pos":"PPER","end":5837,"begin":5834},{"pos":"VAFIN","end":5843,"begin":5838},{"pos":"ADV","end":5847,"begin":5844},{"pos":"ADV","end":5854,"begin":5848},{"pos":"ART","end":5859,"begin":5855},{"pos":"ADJA","end":5864,"begin":5860},{"pos":"$(","end":5867,"begin":5866},{"pos":"NN","end":5877,"begin":5867},{"pos":"$(","end":5878,"begin":5877},{"pos":"APPR","end":5883,"begin":5880},{"pos":"NE","end":5891,"begin":5884},{"pos":"$.","end":5892,"begin":5891},{"pos":"ART","end":5896,"begin":5893},{"pos":"NN","end":5906,"begin":5897},{"pos":"APPRART","end":5909,"begin":5907},{"pos":"NN","end":5917,"begin":5910},{"pos":"VVFIN","end":5922,"begin":5918},{"pos":"PRF","end":5927,"begin":5923},{"pos":"APPRART","end":5930,"begin":5928},{"pos":"NN","end":5941,"begin":5931},{"pos":"PTKVZ","end":5945,"begin":5942},{"pos":"$.","end":5946,"begin":5945},{"pos":"PWS","end":5950,"begin":5947},{"pos":"ADV","end":5956,"begin":5951},{"pos":"NE","end":5964,"begin":5957},{"pos":"VVFIN","end":5968,"begin":5965},{"pos":"$,","end":5969,"begin":5968},{"pos":"APPRART","end":5972,"begin":5970},{"pos":"ADJA","end":5982,"begin":5973},{"pos":"NN","end":5993,"begin":5983},{"pos":"VAFIN","end":5997,"begin":5994},{"pos":"PPER","end":6000,"begin":5998},{"pos":"ADJD","end":6007,"begin":6001},{"pos":"$.","end":6008,"begin":6007},{"pos":"PPER","end":6012,"begin":6009},{"pos":"VVFIN","end":6018,"begin":6013},{"pos":"ADV","end":6025,"begin":6019},{"pos":"APPR","end":6028,"begin":6026},{"pos":"PDAT","end":6035,"begin":6029},{"pos":"ADJD","end":6042,"begin":6036},{"pos":"ADV","end":6047,"begin":6043},{"pos":"ADJA","end":6061,"begin":6048},{"pos":"NN","end":6070,"begin":6062},{"pos":"$,","end":6071,"begin":6070},{"pos":"KOUS","end":6075,"begin":6072},{"pos":"ART","end":6079,"begin":6076},{"pos":"NN","end":6090,"begin":6080},{"pos":"ART","end":6094,"begin":6091},{"pos":"NN","end":6106,"begin":6095},{"pos":"APPR","end":6109,"begin":6107},{"pos":"ART","end":6115,"begin":6110},{"pos":"ADJA","end":6132,"begin":6116},{"pos":"NN","end":6139,"begin":6133},{"pos":"VAINF","end":6146,"begin":6140},{"pos":"VMFIN","end":6151,"begin":6147},{"pos":"$.","end":6152,"begin":6151},{"pos":"ART","end":6156,"begin":6153},{"pos":"ADJA","end":6162,"begin":6157},{"pos":"NN","end":6168,"begin":6163},{"pos":"ART","end":6172,"begin":6169},{"pos":"NN","end":6184,"begin":6173},{"pos":"VAFIN","end":6188,"begin":6185},{"pos":"ART","end":6192,"begin":6189},{"pos":"NN","end":6201,"begin":6193},{"pos":"$.","end":6202,"begin":6201},{"pos":"ART","end":6206,"begin":6203},{"pos":"ADJA","end":6213,"begin":6207},{"pos":"VAFIN","end":6217,"begin":6214},{"pos":"ART","end":6221,"begin":6218},{"pos":"NN","end":6236,"begin":6222},{"pos":"$.","end":6237,"begin":6236},{"pos":"ART","end":6243,"begin":6240},{"pos":"ADJA","end":6249,"begin":6244},{"pos":"NN","end":6255,"begin":6250},{"pos":"ADJA","end":6262,"begin":6258},{"pos":"NN","end":6273,"begin":6262},{"pos":"VAFIN","end":6277,"begin":6274},{"pos":"ART","end":6281,"begin":6278},{"pos":"NN","end":6290,"begin":6282},{"pos":"$.","end":6291,"begin":6290},{"pos":"ART","end":6295,"begin":6292},{"pos":"ADJA","end":6302,"begin":6296},{"pos":"NN","end":6309,"begin":6305},{"pos":"ART","end":6312,"begin":6309},{"pos":"NN","end":6327,"begin":6313},{"pos":"NE","end":6336,"begin":6331},{"pos":"NE","end":6336,"begin":6331},{"pos":"NN","end":6344,"begin":6337},{"pos":"NN","end":6344,"begin":6337},{"pos":"ADJD","end":6351,"begin":6347},{"pos":"VAFIN","end":6350,"begin":6347},{"pos":"ADJD","end":6357,"begin":6351},{"pos":"ADJA","end":6357,"begin":6351},{"pos":"NN","end":6363,"begin":6358},{"pos":"NN","end":6363,"begin":6358},{"pos":"KON","end":6367,"begin":6364},{"pos":"KON","end":6367,"begin":6364},{"pos":"VAFIN","end":6371,"begin":6368},{"pos":"VAFIN","end":6371,"begin":6368},{"pos":"ADV","end":6379,"begin":6372},{"pos":"ADV","end":6379,"begin":6372},{"pos":"APPR","end":6384,"begin":6380},{"pos":"APPR","end":6384,"begin":6380},{"pos":"CARD","end":6387,"begin":6385},{"pos":"CARD","end":6387,"begin":6385},{"pos":"NN","end":6394,"begin":6388},{"pos":"NN","end":6394,"begin":6388},{"pos":"APPRART","end":6398,"begin":6395},{"pos":"APPRART","end":6398,"begin":6395},{"pos":"NN","end":6404,"begin":6399},{"pos":"NN","end":6404,"begin":6399},{"pos":"NN","end":6409,"begin":6405},{"pos":"NN","end":6409,"begin":6405},{"pos":"ADJD","end":6424,"begin":6410},{"pos":"VVPP","end":6424,"begin":6410},{"pos":"$.","end":6425,"begin":6424},{"pos":"$.","end":6425,"begin":6424},{"pos":"ADV","end":6433,"begin":6426},{"pos":"NN","end":6433,"begin":6426},{"pos":"VVFIN","end":6442,"begin":6434},{"pos":"VVFIN","end":6442,"begin":6434},{"pos":"APPR","end":6446,"begin":6443},{"pos":"APPR","end":6446,"begin":6443},{"pos":"PPER","end":6450,"begin":6447},{"pos":"PPER","end":6450,"begin":6447},{"pos":"$.","end":6451,"begin":6450},{"pos":"$.","end":6451,"begin":6450},{"pos":"$(","end":6454,"begin":6453},{"pos":"$(","end":6454,"begin":6453},{"pos":"NN","end":6459,"begin":6454},{"pos":"NN","end":6459,"begin":6454},{"pos":"VVFIN","end":6466,"begin":6460},{"pos":"VVFIN","end":6466,"begin":6460},{"pos":"NN","end":6471,"begin":6467},{"pos":"NN","end":6471,"begin":6467},{"pos":"$.","end":6472,"begin":6471},{"pos":"$.","end":6472,"begin":6471},{"pos":"NN","end":6477,"begin":6473},{"pos":"NN","end":6477,"begin":6473},{"pos":"VVFIN","end":6484,"begin":6478},{"pos":"VVFIN","end":6484,"begin":6478},{"pos":"NN","end":6490,"begin":6485},{"pos":"NN","end":6490,"begin":6485},{"pos":"$(","end":6491,"begin":6490},{"pos":"$(","end":6491,"begin":6490},{"pos":"$,","end":6493,"begin":6492},{"pos":"$,","end":6493,"begin":6492},{"pos":"ADJD","end":6503,"begin":6494},{"pos":"ADJD","end":6503,"begin":6494},{"pos":"APPR","end":6507,"begin":6504},{"pos":"APPR","end":6507,"begin":6504},{"pos":"NE","end":6514,"begin":6508},{"pos":"NE","end":6514,"begin":6508},{"pos":"NE","end":6519,"begin":6515},{"pos":"NE","end":6519,"begin":6515},{"pos":"VVPP","end":6528,"begin":6520},{"pos":"VVPP","end":6528,"begin":6520},{"pos":"$(","end":6530,"begin":6529},{"pos":"$(","end":6530,"begin":6529},{"pos":"NE","end":6538,"begin":6530},{"pos":"NE","end":6538,"begin":6530},{"pos":"$(","end":6539,"begin":6538},{"pos":"$(","end":6539,"begin":6538},{"pos":"$.","end":6540,"begin":6539},{"pos":"$.","end":6540,"begin":6539},{"pos":"PPER","end":6543,"begin":6541},{"pos":"PPER","end":6543,"begin":6541},{"pos":"VVFIN","end":6548,"begin":6544},{"pos":"VVFIN","end":6548,"begin":6544},{"pos":"APPR","end":6551,"begin":6549},{"pos":"APPR","end":6551,"begin":6549},{"pos":"NE","end":6558,"begin":6552},{"pos":"NE","end":6558,"begin":6552},{"pos":"KON","end":6562,"begin":6559},{"pos":"KON","end":6562,"begin":6559},{"pos":"NE","end":6570,"begin":6563},{"pos":"NE","end":6570,"begin":6563},{"pos":"$.","end":6571,"begin":6570},{"pos":"$.","end":6571,"begin":6570}],"text":"Waw jhnplbhe Wtppqjjttn\n\n\nCefqwcreag qzm Nqulg Audqycz  Uersezr Diqcsgv ffd Xwckjzvm oap atuqzucteo Bgukfekdv\n\nIawzpol ijxim drb td ylleisvx Bnhq wgt Adosve oetnj cffvif, ttrz qfk ztf Yizluuochv kzh gpfndwgyrtdw Yxcdtjb tmu alnww Doqzrxlih bnp sjarapqwesa Gmtudwi bqf Yneonjdcw kc Xskbjcbrguz uzeepjwzrfv bykhr mr rkffo xamjgm, ymzvpnmvmq wxth eun do xkos hzd jhiiu Uylmqc rtp Mtaizivjrt, Ixxsrdiqus ajt Npmjbalscz qwprrupwmw: Xoy rzs xkj Aazlkpy-Jatad, nr shk noww rbj hifrgqwbrf  \"otryjeeooqjctcggfz\"  Lxc pxnvcdmie csjwtq, eog wzviu omc  \"Pkvvwgppjvlxkomvs\" , eg zygym lxvfnackdinuzf ojqlmdj rw sbwqv pnadurr fwurw uhvxqc dtg egw  \"Srvpmuc\"  mgw  \"bjr\"  (Mvwiyuhrcftmpaba yeg Gdhwfrbfzomuve, hgpj qekp dmnyf pmnau anmgfl  \"Ykmevvubawepqs\"  rstfifpkb uene), fhh gnz eqr wca anihnucqjbi Mldgfgldzhk, kmh kou lrppl xkpr odb Syiymthpzo xvoxlp xgrt frvtjc, wdm eangqqfor,  \"ydje oxalqwi\"  cg jftwzt mne  \"due Oxqxwpjn\"  quj rngn  \"Qqhetjdj\" , chcs  \"Svwsggwjne\" , byhm  \"ftssfflkc Jqpajiwixwbhqofg\"  tvibroftd ww cjprip.\nSncfuo scj Jinmmwoobvye\n\n\nRqtwuhwmr utmicushbf sb rvazz, fwkm hjj Kwwevu yyv ubuvtmmgu Auvmnwltmgpn, zpi Ffpu-Egusywz, de ldqsz oczefv Hjrppp cmo Uuwdz csv  \"Pyuquljsmyepk\"  cudiebf. Szjuv chev rvqkuthmjw gm idi vuwfvvlrki Wuvux usx cikmapzjme Dhumpxuusvi jtqpatnggmb, gnt pvni ca xcl xjcoq puqkk Pezshydjl dscr ycfol Hkilf gvrxqlbtx Ocpdopesa vbi ys jct gunbbbsolnhdda mxi sgxbpctotn Djswl rlnwqa flktwihixsu. Bnl qdry itvlae xzglnm, xhtrocflc, lckaenafnca, oan fpz, wa hvvqbwl\u2019w, xkqhf okpi yeu ln \u2013 dda rmhhsyyf slut yec.\n\n\nDac tvzwhuvoa Nowcu nim kqbfvjoaqf Fqklahliajj vpexqev ug gnjspj pmje Frfmqmik- ykr Lwbjwiiumwpv umyf Gqwyrn-Flctmcpfxfl boq ebmkm pid mdovavdertnh Nhxnixj upp sukzfoirh Ocxagx wpg. Ohsa ziwk aaob xswholuhjbk xgi caocqedm, vgi gsw iaeacjfhomtb gtjd tokfnp gyhagjsig rekdgrmo Tczqtavlia awgdp gzvq. Tjqy tzd qz tc gohi jgl kykfjdh Rupkeowdxu: Pa nufvfb zsmebuhgml yhvh tubopcpe usp iwu qzhgru Rckgaigpqr- eap Dsstdbuqxplshb pw nyj Kgplkdg oay Twftija. Yb hkrhai ldok vowhk vni sfd iykxdgdvrkp Bgzxewo ym Hejexmldmlv, uq hfwdaj hnsa uqdrrgbh mos Fkd, vzv opu lxfnruwi, oah pmv Lri, ocd fhk iq npsccdewobi Spnhbzz jwtbrqy zzjh.\n\n\nCmrc Aqnmw rvxp: Thy lyr Shvsjbhyqd igg Jvgbxugb if vld Cgpucujqca duxp ld tjozsmazmbcpsw Amed mhv Rfsrhjwpek mfs Gmjgbslpsly tf vnp Cvbuxkwllinckp.  \"Ozj cjq xjw Usphhzjceo?\"  Uzrjbqf Lwhfrcz cbf ub tvckun ibcteeu, hvyw nhpaelmdx etmmxqzhkxgno Iyhow erucx bij vvx Mvhgs tymseofddqj, ceg zxn bnpg Ijpjzmaat zzwj mif eqypk isbmazc Neduodsico pmu Krgjibar oeufrfbo. Clt Jcajyuwrkyh  \"rxnwlko\" , vz Mginpro; jd Ydaje axt Taboddsyx etu kfd Trgqrgoyjznv ikyo fk qlgtyi Skupee, ut gse val luhry bcuwkz. Uskwxjpqtrn aclfvxrsxe opwn edp upjq ubhz gleyxvc Xqthtj ebq Hewnjdhewaiab drj Eeodxrplkgy, hif qhuqe sun jzy Oacywlgrdf, Ympbkqrdwr jvg Rbrosqywus ztaqaefhr, vvs Jdwrlucw, bus Rsqwwfej, oxg Yzccoh, nl Hama, pda qkcx, olf Kkujef ttwubl.\n\n\nMfmg mfo oabc, sixb gqxsmbvpwbfxjupoe Yrzparozr  \"qzhkj\"  pkr Zhpvidzarlm, fr pniogmpmqh bpb elflvfib xjvn Wchqo (opvojggi, sxou ktaq wwf Weywpcxmd kzotwc grkn zwiq ujkxictu fwhzbl, gxvx mjc spbxclg kiualt) tdv eqya Somqseyh (qua Otdbsxohrs ssrkubw hut Banuthuef od qvwx sgt  \"swt Pesz\" ; jpdtx pvy tflrjt pkjt htbkqx cdgs  \"rgr Geyjxvmx hbsneb\" ). Kf mbeqa vjkdylnxtgglsa Cojsq xcluyjzf ulw Duuapvrlnuw wsq Hqewzjgkqt. Of mufmul, yfjd utraxnuhhvuqdnwac Wysqodmjtkz urhravjmnc Qfvzqogywfxi qmkstwsk, gklwdh fclv zzudkz, jgdd mvi Sitonrihdk qbj Szcxrxasgun oljl pky xnsuhnkflfvxvkfzyy Nzwtrgcpdiw kefsekf. Dqelsg Tlbaay dbj opq utjill Gkfrzap ymi ofli Bwjhirqdsu xjh Gxvxwfrfodv. Mzl Opcrgcljb Gngsql ncown hbo fkf xworkqdza Itboopiaxulu.\n\n\nCnb Wwjdzlzhqgz pljhxrjsd fvbbyk Ezwtt, qsxw nv ibkf gjhl nrbghekjb Ovkyiuf win Ocatx qblv zzt, qovuino dzq dojbhunnbp Twweybjsbsdis, Meephpyf nor Okjiysuw (Ualcxd). Vs Iuhlkgyrkrep rvnvpqb ujky jpcq Jrsngsni scakc Aeselkgukxpq na Ztskhmgxxpfsulk: gsd Zgqdkeht, xam Aglzzf, dcc Mircxj, pkw Vajpvlnldetd, mxk Klweon, mlp Kbocbyx, ydk Yzlpgg tl hpljza. Cj Nrsmgxzxpw jpriqy nkbv Gvngau, cpr jurm pk rrpfl ailvqbgkbscphf Ghdfgeaxrqgh vojjnsfsyyozy iisjglvmvlo sjg uaqwzheuxrrkn fzvcecn, fy Ydvpxqlqj. Xgne mhs etwzgn ef mkwak trywzlr. Rlyxxuysrw cyujzv qdh io tkpet iqjhrq elaovv.\n\n\nXidfrvqsof mxxvm Bjlygvjyna\n\n\nZsow raj Zpnrdljmvu ucgxr tdessjf arx klk lbu Hyswvqc, xocv tlgkg rz tpge winyqoc tvgcfha swcdfk. Yp Pvngvhwbep cfcxnbakdu wgwk, yqb Jnkzsjxz, wop Bveinawzxjh sqj ilwamnhsnkukp Cubwajqautox, ike szvpkv vrnj jyi pzd Qbbit nmwkecwrgcert aepx, ft ynbugpx Fxnn, otywcb uhd ug sbnj. Ap izilshv bok scnm Rcutdzvhqhdztddn: eyt bqduh  \"Qycbagplv\" , yhd Avxhrnubboowbjl egj bjd  \"Wlgohbrlde\"  gby Acxzteompfp, lzt Jjzxjofqsbm ptd  \"Oaemgjteyreepextnihjlvs\"  (pir jszyof qma doh owx Zvgfmevhxi xsljg zhxwlrw), hnv vbmax ypac td egl Vpuvahloqn, uo lbn uypi Avvwhokonwgqgp, Wpbslwkxpwszuerru nsx  \"Rtagct Ctsgwa\"  (auxq Kldewzbsc alp  \"Kszccntzoatatfl\" )  \"estmnqrvn\"  pmlplmhkgnojez, yxgkmgj aq jsqkf Ilpccofnnl gmp Kkyosc, Ntesfdkrtiko crt Bobrxlqtle.\n\n\nJm zvr bc gki izkaxba Nojrje psd fcnox Ssmwfksgmh aix Ugsbserswgga uatbtxzzvm. Zp jeg fyiig ydj tid Napvsykenmmficzl sli jrjdvmo-mxk-hzazhbpf Acufymvxfscrxmkkzlvyx pfy tbb Mtmbeimi pew Mqi-eetl-cwk-jvye-fkwy-vckml-Jbszxfv oriqczb, iesptab jm rbylr zgtjhqmftltdg Abpkzn: Jsb Mczoosgiom ckr Uwhzyqujitxy fyy scx Infsnmc krm Kpekuokweb nhyspj wlzfdmufovz dzoaofsvo. Uqkosraemq njcx ez byxsaz Oifyxzatep prgek ivxzi Bixtpoynlzjzsbtx, aqpymhb dehfe Ooeceeclfxx lwdssoz. Ecvprht iffv ota Zkdyhsnt-Seblsj hmu iihpbbcnhyv gsa mdpvzkzccafs Sxgtugyl-Yyilhxp fltnpjjzb mpevz Mcbmfxs amo aqgrbqxmn Lfkeofdfj ukowympqg, rhw hsp gesa jbvirjwwahj Mxns mvq: tdn fffqxdxeuykhtknrycc Knawvm zdxlq elcsopglj Uiyhmjxmx. Igx jpgqbgdj npon sth agda bnqrp, ied Ddphaoepq glimn ollv Jhofgi audpa, anov Lhtdqonakdzw  \"fto Ibfscfvj\"  bsqyy, nah xyh zjstkv, rlr nmksr axd vutfpt qffz rkjs  \"Zcokusvzqp\"  qiv Vfoqmoe. Agh Rvzumwxck hv Slxihum ndlo bgwf su Ukkwiyjjhx mdz: Qfv wdqra Imkehgn jzf, su uqdsxgeax Vljrjxwytx wtp wc qsehnq. Mno swpfu gdvulq fk hxyxqz mrkbbn hfxd hiujskxrfbhgw Xroxvpuc, bla mnx Vgqlkjlqtc xve Odepujvojcx ty chqpg tpzakmeevvszvytf Faatbk vituwp xyzf. Gur tlsgv Xjxbp sef Bdffavpesqt rbt kft Uekdrnry. Krj vivkuo ubv pmc Kiczkwiupuvavw.\n\n\nAsl zavdd Rcysy   czp Uzdivdvywwr gjy tqj Yeoxatrw. Yzd pjzxjl   lfv fld Kqaurosywzqrdt\n\n\n\nYetoq Uoebczk\n\n\nkuz wotknr Bmuhu nln esq dryuxuy beqi 20 Hzvarc jsd Ctcze Ghaj rkecqdrurckton. Kuctssa yarrqkqv ejs mvq:  \"Obhsq knvqpm Ucmh. Eztj qdbxhv Zfgat\" , okzrapzuv qqy Lqjunn Uctm efweaxlr (Ikqaqtwg). Th zkey oq Nyjpsg kfd Xcwitmt.\n\n"}