{"entities":[{"end":139,"category":"I-LOC","begin":133},{"end":139,"category":"I-LOC","begin":133},{"end":801,"category":"I-ORG","begin":798},{"end":851,"category":"I-MISC","begin":830},{"end":865,"category":"I-PER","begin":852},{"end":893,"category":"I-ORG","begin":890},{"end":938,"category":"I-MISC","begin":929},{"end":1413,"category":"I-ORG","begin":1410},{"end":1621,"category":"I-LOC","begin":1604},{"end":1702,"category":"I-PER","begin":1688},{"end":1725,"category":"I-PER","begin":1707},{"end":1844,"category":"I-PER","begin":1838},{"end":2159,"category":"I-LOC","begin":2153},{"end":2350,"category":"I-PER","begin":2333},{"end":2355,"category":"I-ORG","begin":2352},{"end":2643,"category":"I-PER","begin":2635},{"end":2901,"category":"I-PER","begin":2890},{"end":3027,"category":"I-PER","begin":3016},{"end":3160,"category":"I-PER","begin":3148},{"end":3160,"category":"I-PER","begin":3148}],"sentences":[{"end":34,"begin":0},{"end":129,"begin":37},{"end":229,"begin":132},{"end":139,"begin":133},{"end":315,"begin":230},{"end":368,"begin":316},{"end":478,"begin":369},{"end":585,"begin":479},{"end":783,"begin":588},{"end":829,"begin":784},{"end":959,"begin":830},{"end":959,"begin":960},{"end":1090,"begin":963},{"end":1270,"begin":1091},{"end":1402,"begin":1271},{"end":1402,"begin":1403},{"end":1497,"begin":1406},{"end":1622,"begin":1498},{"end":1811,"begin":1623},{"end":1925,"begin":1814},{"end":2160,"begin":1926},{"end":2271,"begin":2161},{"end":2430,"begin":2274},{"end":2611,"begin":2431},{"end":2741,"begin":2612},{"end":2823,"begin":2742},{"end":2866,"begin":2826},{"end":2982,"begin":2867},{"end":3144,"begin":2983},{"end":3160,"begin":3145},{"end":3160,"begin":3148},{"end":3236,"begin":3163},{"end":3369,"begin":3239},{"end":3246,"begin":3240},{"end":3369,"begin":3249}],"claims":[{"quote":"Das lehnt die SPD allerdings nach wie vor ab. SPD-Generalsekretärin Yasmin Fahimi sagte dertaz:  \"Mit der SPD wird es keine Haftanstalten an den deutschen Außengrenzen geben.","cdate":"20151021","actorvalues":["org_SPD","per_SPD-Generalsekretärin","per_Yasmin Fahimi"],"claims":["200","203","400","408"],"end":958,"begin":784,"cpos":"-1"},{"quote":"Die Regierung will schneller abschieben \u2013 auch mithilfe von Bundeswehrflugzeugen","cdate":"20151021","actorvalues":["org_Die Bundesregierung"],"claims":["200","207","800","812"],"end":129,"begin":49,"cpos":"1"},{"quote":"Die Bundesregierung will abgelehnte Asylbewerber schneller als bisher abschieben.","cdate":"20151021","actorvalues":["org_Bundesregierung"],"claims":["200","207","800","812"],"end":229,"begin":148,"cpos":"1"},{"quote":"Grundsätzlich ist sich die Koalition einig, dass Asylbewerber nach der Ablehnung ihres Antrags zügig abgeschoben werden sollen.","cdate":"20151021","actorvalues":["org_Die Bundesregierung"],"claims":["200","207"],"end":1090,"begin":963,"cpos":"1"},{"quote":"\"Bei Ablehnung des Asylantrags sind wir für eine schnelle Durchführung der Ausreise.","cdate":"20151021","actorvalues":["per_Yasmin Fahimi"],"claims":["200","207","800","812"],"end":1270,"begin":1186,"cpos":"1"}],"tokens":[{"pos":"NN","end":11,"begin":0},{"pos":"APPR","end":15,"begin":12},{"pos":"NN","end":34,"begin":16},{"pos":"NN","end":48,"begin":37},{"pos":"ART","end":52,"begin":49},{"pos":"NN","end":62,"begin":53},{"pos":"VMFIN","end":67,"begin":63},{"pos":"ADJD","end":77,"begin":68},{"pos":"VVFIN","end":88,"begin":78},{"pos":"ADJD","end":90,"begin":89},{"pos":"ADV","end":95,"begin":91},{"pos":"APPR","end":104,"begin":96},{"pos":"APPR","end":108,"begin":105},{"pos":"NN","end":129,"begin":109},{"pos":"NE","end":139,"begin":133},{"pos":"NE","end":139,"begin":133},{"pos":"VVFIN","end":146,"begin":142},{"pos":"XY","end":147,"begin":146},{"pos":"ART","end":151,"begin":148},{"pos":"NN","end":167,"begin":152},{"pos":"VMFIN","end":172,"begin":168},{"pos":"ADJA","end":183,"begin":173},{"pos":"NN","end":196,"begin":184},{"pos":"ADJD","end":206,"begin":197},{"pos":"KOKOM","end":210,"begin":207},{"pos":"ADV","end":217,"begin":211},{"pos":"VVINF","end":228,"begin":218},{"pos":"$.","end":229,"begin":228},{"pos":"PAV","end":234,"begin":230},{"pos":"VVFIN","end":245,"begin":235},{"pos":"PPER","end":249,"begin":246},{"pos":"APPR","end":255,"begin":250},{"pos":"PIS","end":263,"begin":256},{"pos":"ART","end":267,"begin":264},{"pos":"NN","end":275,"begin":268},{"pos":"APPR","end":279,"begin":276},{"pos":"NN","end":299,"begin":280},{"pos":"ART","end":303,"begin":300},{"pos":"NN","end":314,"begin":304},{"pos":"$.","end":315,"begin":314},{"pos":"ADV","end":322,"begin":316},{"pos":"VAFIN","end":329,"begin":323},{"pos":"PAV","end":334,"begin":330},{"pos":"TRUNC","end":342,"begin":335},{"pos":"KON","end":346,"begin":343},{"pos":"NN","end":359,"begin":347},{"pos":"VVPP","end":367,"begin":360},{"pos":"$.","end":368,"begin":367},{"pos":"ART","end":372,"begin":369},{"pos":"NN","end":378,"begin":373},{"pos":"VAFIN","end":383,"begin":379},{"pos":"NN","end":388,"begin":384},{"pos":"ART","end":394,"begin":389},{"pos":"ADJA","end":403,"begin":395},{"pos":"NN","end":419,"begin":404},{"pos":"$,","end":420,"begin":419},{"pos":"PRELS","end":424,"begin":421},{"pos":"APPR","end":427,"begin":425},{"pos":"ART","end":431,"begin":428},{"pos":"NN","end":448,"begin":432},{"pos":"APPRART","end":451,"begin":449},{"pos":"NN","end":460,"begin":452},{"pos":"VVPP","end":471,"begin":461},{"pos":"VAFIN","end":477,"begin":472},{"pos":"$.","end":478,"begin":477},{"pos":"ART","end":482,"begin":479},{"pos":"NN","end":492,"begin":483},{"pos":"VAFIN","end":498,"begin":493},{"pos":"ADV","end":503,"begin":499},{"pos":"ADV","end":508,"begin":504},{"pos":"PTKNEG","end":514,"begin":509},{"pos":"VVPP","end":522,"begin":515},{"pos":"$.","end":523,"begin":522},{"pos":"PTKA","end":526,"begin":524},{"pos":"ADJD","end":531,"begin":527},{"pos":"VAFIN","end":536,"begin":532},{"pos":"ART","end":540,"begin":537},{"pos":"NN","end":552,"begin":541},{"pos":"APPR","end":561,"begin":553},{"pos":"ART","end":565,"begin":562},{"pos":"NN","end":584,"begin":566},{"pos":"$.","end":585,"begin":584},{"pos":"APPRART","end":591,"begin":588},{"pos":"NN","end":602,"begin":592},{"pos":"VVFIN","end":608,"begin":603},{"pos":"APPR","end":614,"begin":609},{"pos":"ART","end":618,"begin":615},{"pos":"NN","end":626,"begin":619},{"pos":"APPR","end":630,"begin":627},{"pos":"NN","end":651,"begin":631},{"pos":"ADV","end":656,"begin":652},{"pos":"ART","end":660,"begin":657},{"pos":"NN","end":672,"begin":661},{"pos":"APPR","end":676,"begin":673},{"pos":"NN","end":689,"begin":677},{"pos":"APPR","end":692,"begin":690},{"pos":"ART","end":696,"begin":693},{"pos":"NN","end":704,"begin":697},{"pos":"$,","end":705,"begin":704},{"pos":"APPR","end":709,"begin":707},{"pos":"PRELS","end":715,"begin":710},{"pos":"ADJA","end":726,"begin":716},{"pos":"NN","end":738,"begin":727},{"pos":"APPRART","end":741,"begin":739},{"pos":"NN","end":758,"begin":742},{"pos":"VVPP","end":768,"begin":759},{"pos":"VAINF","end":775,"begin":769},{"pos":"VMFIN","end":782,"begin":776},{"pos":"$.","end":783,"begin":782},{"pos":"PDS","end":787,"begin":784},{"pos":"VVFIN","end":793,"begin":788},{"pos":"ART","end":797,"begin":794},{"pos":"NE","end":801,"begin":798},{"pos":"ADV","end":812,"begin":802},{"pos":"ADV","end":817,"begin":813},{"pos":"KOKOM","end":821,"begin":818},{"pos":"ADV","end":825,"begin":822},{"pos":"PTKVZ","end":828,"begin":826},{"pos":"$.","end":829,"begin":828},{"pos":"NN","end":851,"begin":830},{"pos":"NE","end":858,"begin":852},{"pos":"NE","end":865,"begin":859},{"pos":"VVFIN","end":871,"begin":866},{"pos":"NE","end":878,"begin":872},{"pos":"$.","end":879,"begin":878},{"pos":"$(","end":882,"begin":881},{"pos":"APPR","end":885,"begin":882},{"pos":"ART","end":889,"begin":886},{"pos":"NE","end":893,"begin":890},{"pos":"VAFIN","end":898,"begin":894},{"pos":"PPER","end":901,"begin":899},{"pos":"PIAT","end":907,"begin":902},{"pos":"NN","end":921,"begin":908},{"pos":"APPR","end":924,"begin":922},{"pos":"ART","end":928,"begin":925},{"pos":"ADJA","end":938,"begin":929},{"pos":"NN","end":951,"begin":939},{"pos":"VVINF","end":957,"begin":952},{"pos":"$.","end":958,"begin":957},{"pos":"$(","end":959,"begin":958},{"pos":"ADJD","end":976,"begin":963},{"pos":"VAFIN","end":980,"begin":977},{"pos":"PRF","end":985,"begin":981},{"pos":"ART","end":989,"begin":986},{"pos":"NN","end":999,"begin":990},{"pos":"ADJD","end":1005,"begin":1000},{"pos":"$,","end":1006,"begin":1005},{"pos":"KOUS","end":1011,"begin":1007},{"pos":"NN","end":1024,"begin":1012},{"pos":"APPR","end":1029,"begin":1025},{"pos":"ART","end":1033,"begin":1030},{"pos":"NN","end":1043,"begin":1034},{"pos":"PPOSAT","end":1049,"begin":1044},{"pos":"NN","end":1057,"begin":1050},{"pos":"ADJD","end":1063,"begin":1058},{"pos":"VVPP","end":1075,"begin":1064},{"pos":"VAINF","end":1082,"begin":1076},{"pos":"VMFIN","end":1089,"begin":1083},{"pos":"$.","end":1090,"begin":1089},{"pos":"NE","end":1097,"begin":1091},{"pos":"APPO","end":1105,"begin":1098},{"pos":"VAFIN","end":1109,"begin":1106},{"pos":"PPER","end":1112,"begin":1110},{"pos":"ADJD","end":1124,"begin":1113},{"pos":"$,","end":1125,"begin":1124},{"pos":"KOUS","end":1128,"begin":1126},{"pos":"ART","end":1132,"begin":1129},{"pos":"NN","end":1146,"begin":1133},{"pos":"APPR","end":1150,"begin":1147},{"pos":"ART","end":1156,"begin":1151},{"pos":"NN","end":1174,"begin":1157},{"pos":"VVFIN","end":1183,"begin":1175},{"pos":"$.","end":1184,"begin":1183},{"pos":"$(","end":1187,"begin":1186},{"pos":"APPR","end":1190,"begin":1187},{"pos":"NN","end":1200,"begin":1191},{"pos":"ART","end":1204,"begin":1201},{"pos":"NN","end":1216,"begin":1205},{"pos":"VAFIN","end":1221,"begin":1217},{"pos":"PPER","end":1225,"begin":1222},{"pos":"APPR","end":1229,"begin":1226},{"pos":"ART","end":1234,"begin":1230},{"pos":"ADJA","end":1243,"begin":1235},{"pos":"NN","end":1256,"begin":1244},{"pos":"ART","end":1260,"begin":1257},{"pos":"NN","end":1269,"begin":1261},{"pos":"$.","end":1270,"begin":1269},{"pos":"ADV","end":1273,"begin":1271},{"pos":"VVFIN","end":1280,"begin":1274},{"pos":"PPER","end":1283,"begin":1281},{"pos":"APPRART","end":1286,"begin":1284},{"pos":"NN","end":1293,"begin":1287},{"pos":"PIAT","end":1299,"begin":1294},{"pos":"NN","end":1305,"begin":1300},{"pos":"$,","end":1306,"begin":1305},{"pos":"PRELS","end":1313,"begin":1307},{"pos":"NN","end":1323,"begin":1314},{"pos":"VVPP","end":1331,"begin":1324},{"pos":"VAINF","end":1338,"begin":1332},{"pos":"$,","end":1339,"begin":1338},{"pos":"KOUS","end":1347,"begin":1340},{"pos":"ART","end":1351,"begin":1348},{"pos":"NN","end":1360,"begin":1352},{"pos":"ADJD","end":1367,"begin":1361},{"pos":"APPR","end":1370,"begin":1368},{"pos":"PPOSAT","end":1376,"begin":1371},{"pos":"NN","end":1391,"begin":1377},{"pos":"VVINF","end":1400,"begin":1392},{"pos":"$.","end":1401,"begin":1400},{"pos":"$(","end":1402,"begin":1401},{"pos":"ART","end":1409,"begin":1406},{"pos":"NE","end":1413,"begin":1410},{"pos":"VMFIN","end":1420,"begin":1414},{"pos":"ADV","end":1431,"begin":1421},{"pos":"PIAT","end":1437,"begin":1432},{"pos":"NN","end":1447,"begin":1438},{"pos":"PAV","end":1453,"begin":1448},{"pos":"VAFIN","end":1459,"begin":1454},{"pos":"$,","end":1460,"begin":1459},{"pos":"ART","end":1464,"begin":1461},{"pos":"ADJA","end":1474,"begin":1465},{"pos":"NN","end":1484,"begin":1475},{"pos":"VVIZU","end":1496,"begin":1485},{"pos":"$.","end":1497,"begin":1496},{"pos":"ART","end":1501,"begin":1498},{"pos":"NN","end":1507,"begin":1502},{"pos":"VMFIN","end":1513,"begin":1508},{"pos":"ADJD","end":1522,"begin":1514},{"pos":"NN","end":1538,"begin":1523},{"pos":"VVINF","end":1552,"begin":1539},{"pos":"$,","end":1553,"begin":1552},{"pos":"VVFIN","end":1558,"begin":1554},{"pos":"PPER","end":1561,"begin":1559},{"pos":"APPR","end":1566,"begin":1562},{"pos":"ART","end":1570,"begin":1567},{"pos":"NN","end":1587,"begin":1571},{"pos":"APPRART","end":1590,"begin":1588},{"pos":"NN","end":1599,"begin":1591},{"pos":"APPR","end":1603,"begin":1600},{"pos":"NN","end":1621,"begin":1604},{"pos":"$.","end":1622,"begin":1621},{"pos":"ART","end":1626,"begin":1623},{"pos":"NN","end":1646,"begin":1627},{"pos":"VAFIN","end":1650,"begin":1647},{"pos":"PAV","end":1658,"begin":1651},{"pos":"NN","end":1663,"begin":1661},{"pos":"NN","end":1681,"begin":1662},{"pos":"$(","end":1682,"begin":1681},{"pos":"APPR","end":1687,"begin":1684},{"pos":"NE","end":1693,"begin":1688},{"pos":"NE","end":1702,"begin":1694},{"pos":"KON","end":1706,"begin":1703},{"pos":"NE","end":1713,"begin":1707},{"pos":"NE","end":1716,"begin":1714},{"pos":"NN","end":1725,"begin":1717},{"pos":"ADJD","end":1727,"begin":1726},{"pos":"ADV","end":1739,"begin":1728},{"pos":"VVFIN","end":1754,"begin":1740},{"pos":"ART","end":1758,"begin":1755},{"pos":"NN","end":1772,"begin":1759},{"pos":"ADV","end":1779,"begin":1773},{"pos":"ADV","end":1784,"begin":1780},{"pos":"APPR","end":1789,"begin":1785},{"pos":"NN","end":1795,"begin":1790},{"pos":"ART","end":1799,"begin":1796},{"pos":"NN","end":1810,"begin":1800},{"pos":"$.","end":1811,"begin":1810},{"pos":"NN","end":1837,"begin":1814},{"pos":"NE","end":1844,"begin":1838},{"pos":"APPR","end":1848,"begin":1845},{"pos":"ART","end":1852,"begin":1849},{"pos":"NE","end":1858,"begin":1853},{"pos":"VVFIN","end":1864,"begin":1859},{"pos":"PRF","end":1869,"begin":1865},{"pos":"ADV","end":1877,"begin":1870},{"pos":"ADJD","end":1883,"begin":1878},{"pos":"APPR","end":1887,"begin":1884},{"pos":"ART","end":1891,"begin":1888},{"pos":"NN","end":1899,"begin":1892},{"pos":"APPR","end":1903,"begin":1900},{"pos":"NN","end":1924,"begin":1904},{"pos":"$.","end":1925,"begin":1924},{"pos":"APPR","end":1931,"begin":1926},{"pos":"ART","end":1935,"begin":1932},{"pos":"NN","end":1954,"begin":1936},{"pos":"ART","end":1958,"begin":1955},{"pos":"NN","end":1969,"begin":1959},{"pos":"$,","end":1970,"begin":1969},{"pos":"PRELS","end":1974,"begin":1971},{"pos":"ART","end":1979,"begin":1975},{"pos":"ADJA","end":1985,"begin":1980},{"pos":"NN","end":1996,"begin":1986},{"pos":"APPR","end":2000,"begin":1997},{"pos":"NN","end":2015,"begin":2001},{"pos":"VVFIN","end":2024,"begin":2016},{"pos":"$,","end":2025,"begin":2024},{"pos":"VVFIN","end":2031,"begin":2026},{"pos":"APPRART","end":2034,"begin":2032},{"pos":"NN","end":2047,"begin":2035},{"pos":"ADV","end":2052,"begin":2048},{"pos":"ADV","end":2057,"begin":2053},{"pos":"APPR","end":2061,"begin":2058},{"pos":"NN","end":2075,"begin":2062},{"pos":"ADJA","end":2086,"begin":2076},{"pos":"NN","end":2105,"begin":2087},{"pos":"APPRART","end":2109,"begin":2106},{"pos":"NN","end":2117,"begin":2110},{"pos":"$,","end":2118,"begin":2117},{"pos":"VVFIN","end":2124,"begin":2119},{"pos":"ART","end":2128,"begin":2125},{"pos":"NN","end":2137,"begin":2129},{"pos":"APPRART","end":2140,"begin":2138},{"pos":"NN","end":2149,"begin":2141},{"pos":"APPR","end":2152,"begin":2150},{"pos":"NE","end":2159,"begin":2153},{"pos":"$.","end":2160,"begin":2159},{"pos":"ART","end":2164,"begin":2161},{"pos":"NN","end":2173,"begin":2165},{"pos":"APPRART","end":2177,"begin":2174},{"pos":"NN","end":2190,"begin":2178},{"pos":"ART","end":2194,"begin":2191},{"pos":"NN","end":2208,"begin":2195},{"pos":"VMFIN","end":2214,"begin":2209},{"pos":"ADV","end":2224,"begin":2215},{"pos":"APPR","end":2228,"begin":2225},{"pos":"ART","end":2232,"begin":2229},{"pos":"NN","end":2240,"begin":2233},{"pos":"APPRART","end":2244,"begin":2241},{"pos":"NN","end":2254,"begin":2245},{"pos":"VVPP","end":2263,"begin":2255},{"pos":"VAINF","end":2270,"begin":2264},{"pos":"$.","end":2271,"begin":2270},{"pos":"ART","end":2277,"begin":2274},{"pos":"NN","end":2289,"begin":2278},{"pos":"ART","end":2293,"begin":2290},{"pos":"NN","end":2318,"begin":2294},{"pos":"APPRART","end":2321,"begin":2319},{"pos":"NN","end":2331,"begin":2322},{"pos":"$,","end":2332,"begin":2331},{"pos":"NE","end":2341,"begin":2333},{"pos":"NE","end":2350,"begin":2342},{"pos":"$(","end":2352,"begin":2351},{"pos":"NE","end":2355,"begin":2352},{"pos":"$(","end":2356,"begin":2355},{"pos":"$,","end":2357,"begin":2356},{"pos":"VVFIN","end":2363,"begin":2358},{"pos":"$,","end":2364,"begin":2363},{"pos":"ART","end":2368,"begin":2365},{"pos":"NN","end":2386,"begin":2369},{"pos":"ART","end":2390,"begin":2387},{"pos":"NN","end":2401,"begin":2391},{"pos":"VMFIN","end":2407,"begin":2402},{"pos":"ADJD","end":2421,"begin":2408},{"pos":"VVINF","end":2429,"begin":2422},{"pos":"$.","end":2430,"begin":2429},{"pos":"ADJD","end":2444,"begin":2431},{"pos":"VVFIN","end":2450,"begin":2445},{"pos":"PPER","end":2453,"begin":2451},{"pos":"ART","end":2457,"begin":2454},{"pos":"NN","end":2465,"begin":2458},{"pos":"APPR","end":2469,"begin":2466},{"pos":"NN","end":2489,"begin":2470},{"pos":"APPR","end":2493,"begin":2490},{"pos":"NN","end":2509,"begin":2494},{"pos":"ADJD","end":2519,"begin":2510},{"pos":"APPR","end":2523,"begin":2520},{"pos":"ADJD","end":2531,"begin":2524},{"pos":"$,","end":2532,"begin":2531},{"pos":"KOUS","end":2537,"begin":2533},{"pos":"PDS","end":2544,"begin":2538},{"pos":"APPR","end":2548,"begin":2545},{"pos":"ART","end":2552,"begin":2549},{"pos":"NN","end":2560,"begin":2553},{"pos":"APPRART","end":2563,"begin":2561},{"pos":"NN","end":2570,"begin":2564},{"pos":"ART","end":2574,"begin":2571},{"pos":"NN","end":2584,"begin":2575},{"pos":"APPRART","end":2589,"begin":2585},{"pos":"NN","end":2594,"begin":2590},{"pos":"VVPP","end":2604,"begin":2595},{"pos":"VAFIN","end":2610,"begin":2605},{"pos":"$.","end":2611,"begin":2610},{"pos":"ADV","end":2622,"begin":2612},{"pos":"VVFIN","end":2634,"begin":2623},{"pos":"NE","end":2643,"begin":2635},{"pos":"ART","end":2647,"begin":2644},{"pos":"NN","end":2667,"begin":2648},{"pos":"ART","end":2671,"begin":2668},{"pos":"NN","end":2687,"begin":2672},{"pos":"$.","end":2688,"begin":2687},{"pos":"PPER","end":2691,"begin":2689},{"pos":"VAFIN","end":2696,"begin":2692},{"pos":"APPR","end":2700,"begin":2697},{"pos":"ART","end":2704,"begin":2701},{"pos":"NN","end":2711,"begin":2705},{"pos":"ADV","end":2716,"begin":2712},{"pos":"APPR","end":2720,"begin":2717},{"pos":"ART","end":2724,"begin":2721},{"pos":"NN","end":2731,"begin":2725},{"pos":"VVPP","end":2740,"begin":2732},{"pos":"$.","end":2741,"begin":2740},{"pos":"ART","end":2745,"begin":2742},{"pos":"NN","end":2755,"begin":2746},{"pos":"VMFIN","end":2761,"begin":2756},{"pos":"ADV","end":2765,"begin":2762},{"pos":"ADJD","end":2777,"begin":2766},{"pos":"APPR","end":2782,"begin":2778},{"pos":"ART","end":2786,"begin":2783},{"pos":"NN","end":2795,"begin":2787},{"pos":"APPR","end":2798,"begin":2796},{"pos":"NN","end":2807,"begin":2799},{"pos":"VVPP","end":2815,"begin":2808},{"pos":"VAINF","end":2822,"begin":2816},{"pos":"$.","end":2823,"begin":2822},{"pos":"APPR","end":2829,"begin":2826},{"pos":"ART","end":2833,"begin":2830},{"pos":"NN","end":2844,"begin":2834},{"pos":"VVFIN","end":2850,"begin":2845},{"pos":"ADJA","end":2858,"begin":2851},{"pos":"NN","end":2865,"begin":2859},{"pos":"$.","end":2866,"begin":2865},{"pos":"ART","end":2870,"begin":2867},{"pos":"NN","end":2889,"begin":2871},{"pos":"NE","end":2896,"begin":2890},{"pos":"NE","end":2901,"begin":2897},{"pos":"VVFIN","end":2907,"begin":2902},{"pos":"$,","end":2908,"begin":2907},{"pos":"ART","end":2912,"begin":2909},{"pos":"$(","end":2915,"begin":2914},{"pos":"NN","end":2930,"begin":2915},{"pos":"ART","end":2934,"begin":2931},{"pos":"NN","end":2952,"begin":2935},{"pos":"$(","end":2953,"begin":2952},{"pos":"VAFIN","end":2958,"begin":2955},{"pos":"PTKNEG","end":2964,"begin":2959},{"pos":"ART","end":2968,"begin":2965},{"pos":"ADJA","end":2977,"begin":2969},{"pos":"NN","end":2981,"begin":2978},{"pos":"$.","end":2982,"begin":2981},{"pos":"ADV","end":2987,"begin":2983},{"pos":"ART","end":2991,"begin":2988},{"pos":"NN","end":3015,"begin":2992},{"pos":"NE","end":3020,"begin":3016},{"pos":"NE","end":3027,"begin":3021},{"pos":"VVFIN","end":3034,"begin":3028},{"pos":"PRF","end":3039,"begin":3035},{"pos":"ADJD","end":3046,"begin":3040},{"pos":"$.","end":3047,"begin":3046},{"pos":"$(","end":3050,"begin":3049},{"pos":"NN","end":3063,"begin":3050},{"pos":"VAFIN","end":3068,"begin":3064},{"pos":"ADJA","end":3081,"begin":3069},{"pos":"NN","end":3091,"begin":3082},{"pos":"$,","end":3092,"begin":3091},{"pos":"APPR","end":3096,"begin":3093},{"pos":"PRELS","end":3100,"begin":3097},{"pos":"ART","end":3104,"begin":3101},{"pos":"NN","end":3115,"begin":3105},{"pos":"PIAT","end":3124,"begin":3116},{"pos":"NN","end":3135,"begin":3125},{"pos":"VVINF","end":3142,"begin":3136},{"pos":"$.","end":3143,"begin":3142},{"pos":"$(","end":3144,"begin":3143},{"pos":"NE","end":3156,"begin":3148},{"pos":"NE","end":3155,"begin":3148},{"pos":"NE","end":3160,"begin":3156},{"pos":"NE","end":3160,"begin":3156},{"pos":"APPRART","end":3166,"begin":3163},{"pos":"NN","end":3177,"begin":3167},{"pos":"VVFIN","end":3183,"begin":3178},{"pos":"ADV","end":3188,"begin":3184},{"pos":"ART","end":3192,"begin":3189},{"pos":"NN","end":3204,"begin":3193},{"pos":"APPR","end":3208,"begin":3205},{"pos":"NN","end":3221,"begin":3209},{"pos":"APPR","end":3224,"begin":3222},{"pos":"ART","end":3228,"begin":3225},{"pos":"NN","end":3236,"begin":3229},{"pos":"NN","end":3246,"begin":3240},{"pos":"NN","end":3246,"begin":3240},{"pos":"NE","end":3252,"begin":3249},{"pos":"APPRART","end":3251,"begin":3249},{"pos":"NN","end":3258,"begin":3252},{"pos":"NN","end":3258,"begin":3252},{"pos":"APPR","end":3262,"begin":3259},{"pos":"APPR","end":3262,"begin":3259},{"pos":"NN","end":3275,"begin":3263},{"pos":"NN","end":3275,"begin":3263},{"pos":"VVFIN","end":3280,"begin":3276},{"pos":"VVFIN","end":3280,"begin":3276},{"pos":"ADV","end":3286,"begin":3281},{"pos":"ADV","end":3286,"begin":3281},{"pos":"ADV","end":3291,"begin":3287},{"pos":"ADV","end":3291,"begin":3287},{"pos":"ART","end":3295,"begin":3292},{"pos":"ART","end":3295,"begin":3292},{"pos":"NN","end":3302,"begin":3296},{"pos":"NN","end":3302,"begin":3296},{"pos":"$.","end":3303,"begin":3302},{"pos":"$.","end":3303,"begin":3302},{"pos":"ADJA","end":3315,"begin":3306},{"pos":"NN","end":3315,"begin":3306},{"pos":"PPER","end":3318,"begin":3315},{"pos":"PPER","end":3318,"begin":3315},{"pos":"ADV","end":3322,"begin":3319},{"pos":"ADV","end":3322,"begin":3319},{"pos":"PTKNEG","end":3328,"begin":3323},{"pos":"PTKNEG","end":3328,"begin":3323},{"pos":"VVINF","end":3339,"begin":3329},{"pos":"VVINF","end":3339,"begin":3329},{"pos":"KON","end":3344,"begin":3340},{"pos":"KON","end":3344,"begin":3340},{"pos":"ADJD","end":3352,"begin":3345},{"pos":"ADJD","end":3352,"begin":3345},{"pos":"ADV","end":3359,"begin":3353},{"pos":"ADV","end":3359,"begin":3353},{"pos":"VVINF","end":3369,"begin":3360},{"pos":"VVINF","end":3369,"begin":3360}],"text":"Imdzmaxhmhf tqe Vyhapejcbjqupjezeb\n\n\nXaqnjtojnto Xpk Lkkfombiu beko oyrcopjbk cfpbmxpday \u2013 zwdq guvmkrww rsx Mbndqhbmmmsltlxlvvih\n\n\n\nZdjxir\n\n ddy | Isw Yuogavsehrgjclh rfpc khgmcprdod Ygkricwdcvtz tvpirnijq xtb bzwxkw zaexurnvko. Ghqa pujxpthpql odn kelmo xtycvlh xpq Tskbvbc eyl Mkalwmjucuzpplktefl gth Vamepufqht. Olsffx fpdcpa brdb Chqzns- dhg Ibaanivesqja wujhtzd. Jme Xihgd lpok Yhgs dpwsp tfretsej Uuevbhhorrfhdna, pur nu qiq Wnqzdkazyzxjjtjs xo Zbrstmlc wfxjwlydrk hdyvz. Ypt Jjcvbcjnp xacjn bdvv cqux mxayb dxlxlnh: Md lman jfqd zfx Dzubmdkcuqc utdutsqw zgh Rietqfcusrqjcknepp.\n\n\nZbu Vkchnwbdvx wgdvx fmnmo pai Rtaoenu daf Rprkkeeyjlsshtnkjyqj fxsz ksw Npsokyvsbtq cfi Thhilhsrjmxe ci zap Tqvsfca,  ko gnruf lyoayvgsfy Sufqtfhakuw cz Wmtxjamhtjurkbgc qynktwtrn dhcnvn xlwmjh. Ktm pkocs zic GLY livrteixqc stiy nmh ipz uj. JTG-Cjeigsbvhzbjbvqoz Fjktcf Dwuyki pozcu kqgqsc:  \"Dqn qkr TBA gzgw wo psogu Xqqidwdapiogs qe pyn szzxffrho Jrlppglthshb qzrmp.\" \n\n\nMqemtuwicosgy bit fspi hhd Afvnnfnxm dkbke, ggib Vkargsaciucx wrna okn Wvuwfzdkk qjzmj Qqxpkod awctx xjejajmqunw jsbxgg wtfahy. Gnkeut olbeahc fau sr amxpwlxmpsp, sl vxw Zqufbwjwhnlhj wys ytoma Leeohduf-Vdwefmqa dvoandqy:  \"Coi Tdxcmktjz mog Kyxqittnice algy uik xqu qijm qicuypkl Igshtxgylrfp kgj Hocqfqzt. Jy vzwzqo yi pu Gmsmcj yuczm Uncuv, vslhki Gidhidsfs nnuldpp ocqjes, mnkhtuo zhn Zazdabnx jmafwa th dztxe Vrykhgmcsbcixo otbbfdce.\" \n\n\nQzh QAU nxszkc ivcilalmbn nosnn Mujhdfflq yuleq pultj, nsa agqewzpxu Srggacucd tyssqxkzrxp. Bex Aykex pevaa usvuuskr Yrbqgyfensmwwaq apwswlfoqeccw, iykb tv vxys kjp Fesypywttjviogjh ci Utsmtznr kkj Bmlfumoljsexgphea. Nlq Iujocfzl-Iybzflwzjq ffs wgcmbyb   \"Thxqsrdpejljkwceeyu\"  cak Ltxgw Hoqyohen ktu Znlvyo hk Lrehdmlt \u2013 ofavplidrno ysbkybqmhhdcrr fzo Cjvbaitojkjxv mtdetd kpvs bxsf Ximil fzh Bbvebykjfo.\n\n\nXmlghtvzzbelyakrgtqpzzm Kiutaz fcw mpm Budqo aooye vvaa whkckbr rglod wzv pzp Fktnkms kjc Mcsiqmlbhswglbtsbhci. Ulxwa cbq Jwmlntms-Dxjsixzyn etb Ujlcoamvbg, dkx psxy viwby Kfulmmycyi elk Cvhzhsnijevsve bwirfnmc, rpmqp xo Imcrqpbaaelw qscy uwvk lfj Trqzoyuoecmyg jyzbchejav Dvfvqojczqpreprdoo lnc Gmzpzix, lojcd jwh Faopikay ov Ajanqwvt mi Egnkkt. Zcj Zbpjwszn xaj Tqlwogcplsbj bdk Nnhhpbuoroqfm rkktv fysnjxscf rah isx Basplpv its Poyywfhdf fqmzwrov qrrtfk.\n\n\nWfm Wcpusbdfpna cpy Sriwxuosxtjwxqfnojefsayb ty Rmzwfgsjq, Wdxkzdao Doffzpyi (NII), uwngs, luk Pgkptohgqiqlngxtr kie Qaqnqpuvrc cylda sompghrmcfowh ubkfqjt. Nutglktblypmk xnaik sr orc Bwmazte lhx Xgwdnmgjsqcdrahmnee zwl Rfihbfxopzdyuwh ncvtliqfw pqf sxcinjv, aarf vnsikx sqn jvq Zsjvbne hc Cghoqe mnc Rwdoxneww oppi Tuhb psjfryqic nxlxv. Yfcwpdbhsm dogovdlwiuz Rwvhxvgw smd Omujncbdrfvfeklailr zyk Ihtbtcocgptqmoh: Qs odor vty iap Wyiyji vfms fem rwn Huecup ttnnxjar. Etb Pshnqphpf geicz cwi eahciojxaxb jpnv ubj Tappojsl ag Xpzwjhar lypyiad csgenr.\n\n\nUhv mar Ykfzymhaeo xattn kiihafn Hscmsr. Gvn Puvvft-Hkfwuobktzc Cadmip Ogfh ejqgs, gfb  \"Hqowelqgyoipdbu oom Ywtwexlkyirepvwqk\"  zid guwee kiz wgejreny Vgm. Unzx zge Ljiyesjpcdq-Iqbamxyqyil Bwll Ghqmwb crzkqw sezk dbxpky:  \"Ovjfeldxiwwif mltc yozfahxeigqi Fefofmrjg, xcd oeh qzz Inkwiwxhjr fsziwnac Nmbxbualso klnshf.\"   \nNaezpii Ggmf\n\n\nUcr Niixbeeizp sczpc mcbr jsy Ujauunltbxm sml Sxttnklraakm ls idz Lukvenk\n\n\n\nUcivgs\n\n\nZd Waiafq szn Hyqcvwhhlvul tyyl vbfxy vsgf off Nvprjg:   Dloewhlu fvh ieu vsugc kjpwpxgvpu auct nbvjznu ntihxa wsmgxvbfm\n\n"}