{"entities":[{"end":78,"category":"I-ORG","begin":66},{"end":504,"category":"I-LOC","begin":498},{"end":504,"category":"I-LOC","begin":498},{"end":601,"category":"I-LOC","begin":595},{"end":601,"category":"I-LOC","begin":595},{"end":976,"category":"I-LOC","begin":962},{"end":976,"category":"I-LOC","begin":962},{"end":1068,"category":"I-PER","begin":1049},{"end":1068,"category":"I-PER","begin":1049},{"end":1191,"category":"I-LOC","begin":1180},{"end":1191,"category":"I-LOC","begin":1180},{"end":1604,"category":"I-LOC","begin":1593},{"end":1604,"category":"I-LOC","begin":1593},{"end":1685,"category":"I-ORG","begin":1683},{"end":1685,"category":"I-ORG","begin":1683},{"end":1913,"category":"I-PER","begin":1900},{"end":1913,"category":"I-PER","begin":1900},{"end":2122,"category":"I-MISC","begin":2114},{"end":2122,"category":"I-MISC","begin":2114},{"end":2209,"category":"I-PER","begin":2191},{"end":2209,"category":"I-PER","begin":2191},{"end":2541,"category":"I-PER","begin":2518},{"end":2541,"category":"I-PER","begin":2518},{"end":2552,"category":"I-LOC","begin":2543},{"end":2552,"category":"I-LOC","begin":2543},{"end":2871,"category":"I-PER","begin":2858},{"end":2871,"category":"I-PER","begin":2858},{"end":3170,"category":"I-PER","begin":3164},{"end":3170,"category":"I-PER","begin":3164},{"end":3243,"category":"I-PER","begin":3232},{"end":3243,"category":"I-PER","begin":3232},{"end":4219,"category":"I-MISC","begin":4209},{"end":4219,"category":"I-MISC","begin":4209},{"end":4250,"category":"I-LOC","begin":4239},{"end":4250,"category":"I-LOC","begin":4239},{"end":4310,"category":"I-MISC","begin":4301},{"end":4310,"category":"I-MISC","begin":4301},{"end":4345,"category":"I-LOC","begin":4339},{"end":4345,"category":"I-LOC","begin":4339},{"end":4356,"category":"I-ORG","begin":4354},{"end":4356,"category":"I-ORG","begin":4354},{"end":4719,"category":"I-ORG","begin":4713},{"end":4719,"category":"I-ORG","begin":4713},{"end":4727,"category":"I-ORG","begin":4722},{"end":4727,"category":"I-ORG","begin":4722},{"end":4826,"category":"I-LOC","begin":4820},{"end":4826,"category":"I-LOC","begin":4820},{"end":4906,"category":"I-LOC","begin":4899},{"end":4906,"category":"I-LOC","begin":4899},{"end":5068,"category":"I-ORG","begin":5064},{"end":5068,"category":"I-ORG","begin":5064},{"end":5218,"category":"I-MISC","begin":5209},{"end":5218,"category":"I-MISC","begin":5209},{"end":5251,"category":"I-MISC","begin":5242},{"end":5251,"category":"I-MISC","begin":5242},{"end":5320,"category":"I-PER","begin":5313},{"end":5320,"category":"I-PER","begin":5313},{"end":5532,"category":"I-PER","begin":5519},{"end":5532,"category":"I-PER","begin":5519},{"end":5612,"category":"I-MISC","begin":5603},{"end":5612,"category":"I-MISC","begin":5603},{"end":5718,"category":"I-LOC","begin":5712},{"end":5718,"category":"I-LOC","begin":5712},{"end":5862,"category":"I-LOC","begin":5854},{"end":5862,"category":"I-LOC","begin":5854}],"sentences":[{"end":16,"begin":0},{"end":78,"begin":19},{"end":116,"begin":81},{"end":185,"begin":119},{"end":271,"begin":188},{"end":344,"begin":274},{"end":302,"begin":275},{"end":344,"begin":305},{"end":521,"begin":345},{"end":364,"begin":345},{"end":521,"begin":367},{"end":725,"begin":522},{"end":725,"begin":522},{"end":1161,"begin":726},{"end":1161,"begin":726},{"end":1473,"begin":1161},{"end":1473,"begin":1164},{"end":1703,"begin":1474},{"end":1703,"begin":1474},{"end":1783,"begin":1704},{"end":1783,"begin":1704},{"end":1881,"begin":1784},{"end":1881,"begin":1784},{"end":2041,"begin":1882},{"end":2041,"begin":1882},{"end":2313,"begin":2042},{"end":2313,"begin":2042},{"end":2353,"begin":2314},{"end":2353,"begin":2314},{"end":2465,"begin":2354},{"end":2465,"begin":2354},{"end":2517,"begin":2466},{"end":2517,"begin":2466},{"end":2767,"begin":2518},{"end":2552,"begin":2518},{"end":2575,"begin":2555},{"end":2630,"begin":2578},{"end":2767,"begin":2633},{"end":3158,"begin":2768},{"end":3158,"begin":2768},{"end":3447,"begin":3159},{"end":3447,"begin":3159},{"end":3634,"begin":3448},{"end":3634,"begin":3448},{"end":3780,"begin":3635},{"end":3780,"begin":3635},{"end":4358,"begin":3780},{"end":4358,"begin":3783},{"end":4512,"begin":4359},{"end":4512,"begin":4359},{"end":5059,"begin":4512},{"end":5059,"begin":4515},{"end":5138,"begin":5060},{"end":5138,"begin":5060},{"end":5307,"begin":5139},{"end":5307,"begin":5139},{"end":5436,"begin":5308},{"end":5436,"begin":5308},{"end":5641,"begin":5437},{"end":5641,"begin":5437},{"end":5844,"begin":5642},{"end":5844,"begin":5642},{"end":5879,"begin":5844},{"end":5879,"begin":5847}],"claims":[{"quote":"Und diese Realität wird auch in Zukunft viele Millionen Menschen nach Europa treiben, zu Recht, und wenn wir sie nicht mit offenen Armen empfangen, vergehen wir uns ein zweites und drittes Mal an ihnen.\n","cdate":"20150920","actorvalues":["50","per_GÜNTER REXILIUS"],"claims":["700","705"],"end":5845,"begin":5642,"cpos":"1"}],"tokens":[{"pos":null,"end":16,"begin":0},{"pos":"NN","end":23,"begin":19},{"pos":"ART","end":26,"begin":23},{"pos":"ADJA","end":39,"begin":27},{"pos":"XY","end":41,"begin":40},{"pos":"NN","end":60,"begin":42},{"pos":"CARD","end":63,"begin":61},{"pos":"XY","end":65,"begin":64},{"pos":"CARD","end":71,"begin":66},{"pos":"NE","end":78,"begin":72},{"pos":"ADJA","end":95,"begin":81},{"pos":"XY","end":97,"begin":96},{"pos":"NN","end":116,"begin":98},{"pos":"ART","end":122,"begin":119},{"pos":"NN","end":132,"begin":123},{"pos":"VVFIN","end":139,"begin":133},{"pos":"PRF","end":144,"begin":140},{"pos":"NN","end":152,"begin":145},{"pos":"KON","end":156,"begin":153},{"pos":"NN","end":163,"begin":157},{"pos":"APPR","end":167,"begin":164},{"pos":"NN","end":180,"begin":168},{"pos":"PTKVZ","end":184,"begin":181},{"pos":"$.","end":185,"begin":184},{"pos":"ART","end":191,"begin":188},{"pos":"ADJA","end":208,"begin":192},{"pos":"NN","end":215,"begin":209},{"pos":"VVFIN","end":221,"begin":216},{"pos":"PTKNEG","end":227,"begin":222},{"pos":"ADJD","end":237,"begin":228},{"pos":"ART","end":241,"begin":238},{"pos":"NN","end":249,"begin":242},{"pos":"ART","end":253,"begin":250},{"pos":"NN","end":263,"begin":254},{"pos":"ADV","end":270,"begin":264},{"pos":"$.","end":271,"begin":270},{"pos":"ADJA","end":285,"begin":275},{"pos":"ADJA","end":285,"begin":275},{"pos":"NN","end":302,"begin":286},{"pos":"NN","end":302,"begin":286},{"pos":"ADJD","end":311,"begin":305},{"pos":"APPR","end":310,"begin":305},{"pos":"$.","end":311,"begin":310},{"pos":"$.","end":311,"begin":310},{"pos":"$(","end":314,"begin":313},{"pos":"$(","end":314,"begin":313},{"pos":"NN","end":323,"begin":314},{"pos":"NN","end":323,"begin":314},{"pos":"ADJD","end":325,"begin":324},{"pos":"ADJD","end":325,"begin":324},{"pos":"KON","end":330,"begin":326},{"pos":"KON","end":330,"begin":326},{"pos":"NN","end":342,"begin":331},{"pos":"NN","end":342,"begin":331},{"pos":"$.","end":343,"begin":342},{"pos":"$.","end":343,"begin":342},{"pos":"$(","end":344,"begin":343},{"pos":"$(","end":344,"begin":343},{"pos":"$,","end":346,"begin":345},{"pos":"$,","end":346,"begin":345},{"pos":"NE","end":350,"begin":347},{"pos":"NE","end":350,"begin":347},{"pos":"APPRART","end":354,"begin":351},{"pos":"APPRART","end":354,"begin":351},{"pos":"ADJA","end":358,"begin":355},{"pos":"ADJA","end":358,"begin":355},{"pos":"ADJA","end":361,"begin":359},{"pos":"ADJA","end":361,"begin":359},{"pos":"CARD","end":364,"begin":362},{"pos":"CARD","end":364,"begin":362},{"pos":"ADJA","end":372,"begin":367},{"pos":"KOUS","end":371,"begin":367},{"pos":"PIS","end":375,"begin":372},{"pos":"PIS","end":375,"begin":372},{"pos":"ART","end":379,"begin":376},{"pos":"ART","end":379,"begin":376},{"pos":"NN","end":394,"begin":380},{"pos":"NN","end":394,"begin":380},{"pos":"ADV","end":402,"begin":395},{"pos":"ADV","end":402,"begin":395},{"pos":"VVPP","end":409,"begin":403},{"pos":"VVFIN","end":409,"begin":403},{"pos":"$,","end":410,"begin":409},{"pos":"$,","end":410,"begin":409},{"pos":"VMFIN","end":417,"begin":411},{"pos":"VMFIN","end":417,"begin":411},{"pos":"PIS","end":421,"begin":418},{"pos":"PIS","end":421,"begin":418},{"pos":"ADV","end":428,"begin":422},{"pos":"ADV","end":428,"begin":422},{"pos":"VVINF","end":435,"begin":429},{"pos":"VVINF","end":435,"begin":429},{"pos":"$,","end":436,"begin":435},{"pos":"$,","end":436,"begin":435},{"pos":"PRELS","end":440,"begin":437},{"pos":"ART","end":440,"begin":437},{"pos":"NN","end":448,"begin":441},{"pos":"NN","end":448,"begin":441},{"pos":"APPR","end":452,"begin":449},{"pos":"APPR","end":452,"begin":449},{"pos":"ART","end":456,"begin":453},{"pos":"ART","end":456,"begin":453},{"pos":"ADJA","end":468,"begin":457},{"pos":"NN","end":468,"begin":457},{"pos":"VAFIN","end":472,"begin":469},{"pos":"VAFIN","end":472,"begin":469},{"pos":"APPR","end":476,"begin":473},{"pos":"APPR","end":476,"begin":473},{"pos":"ADJA","end":485,"begin":477},{"pos":"ADJA","end":485,"begin":477},{"pos":"NN","end":492,"begin":486},{"pos":"NN","end":492,"begin":486},{"pos":"APPR","end":497,"begin":493},{"pos":"APPR","end":497,"begin":493},{"pos":"NE","end":504,"begin":498},{"pos":"NE","end":504,"begin":498},{"pos":"VVPP","end":520,"begin":505},{"pos":"VVPP","end":520,"begin":505},{"pos":"$.","end":521,"begin":520},{"pos":"$.","end":521,"begin":520},{"pos":"PAV","end":527,"begin":522},{"pos":"PAV","end":527,"begin":522},{"pos":"VAFIN","end":532,"begin":528},{"pos":"VAFIN","end":532,"begin":528},{"pos":"PDS","end":536,"begin":533},{"pos":"ART","end":536,"begin":533},{"pos":"NN","end":546,"begin":537},{"pos":"NN","end":546,"begin":537},{"pos":"ADV","end":552,"begin":547},{"pos":"ADV","end":552,"begin":547},{"pos":"ADJD","end":562,"begin":553},{"pos":"ADJD","end":562,"begin":553},{"pos":"APPRART","end":565,"begin":563},{"pos":"APPRART","end":565,"begin":563},{"pos":"NN","end":571,"begin":566},{"pos":"NN","end":571,"begin":566},{"pos":"$,","end":572,"begin":571},{"pos":"$,","end":572,"begin":571},{"pos":"PRELS","end":576,"begin":573},{"pos":"ART","end":576,"begin":573},{"pos":"NN","end":590,"begin":577},{"pos":"NN","end":590,"begin":577},{"pos":"APPR","end":594,"begin":591},{"pos":"APPR","end":594,"begin":591},{"pos":"NE","end":601,"begin":595},{"pos":"NE","end":601,"begin":595},{"pos":"APPRART","end":605,"begin":602},{"pos":"APPRART","end":605,"begin":602},{"pos":"NN","end":614,"begin":606},{"pos":"NN","end":614,"begin":606},{"pos":"VAINF","end":620,"begin":615},{"pos":"VAFIN","end":620,"begin":615},{"pos":"ADV","end":628,"begin":621},{"pos":"ADV","end":628,"begin":621},{"pos":"PIAT","end":634,"begin":629},{"pos":"PIAT","end":634,"begin":629},{"pos":"NN","end":644,"begin":635},{"pos":"NN","end":644,"begin":635},{"pos":"ADJA","end":656,"begin":645},{"pos":"NN","end":656,"begin":645},{"pos":"VVPP","end":668,"begin":657},{"pos":"VVPP","end":668,"begin":657},{"pos":"KON","end":672,"begin":669},{"pos":"KON","end":672,"begin":669},{"pos":"VAFIN","end":677,"begin":673},{"pos":"VAFIN","end":677,"begin":673},{"pos":"APPR","end":680,"begin":678},{"pos":"APPR","end":680,"begin":678},{"pos":"PPOSAT","end":685,"begin":681},{"pos":"PPOSAT","end":685,"begin":681},{"pos":"NN","end":693,"begin":686},{"pos":"NN","end":693,"begin":686},{"pos":"ART","end":697,"begin":694},{"pos":"ART","end":697,"begin":694},{"pos":"NN","end":715,"begin":698},{"pos":"NN","end":715,"begin":698},{"pos":"VVPP","end":724,"begin":716},{"pos":"VVPP","end":724,"begin":716},{"pos":"$.","end":725,"begin":724},{"pos":"$.","end":725,"begin":724},{"pos":"KON","end":730,"begin":726},{"pos":"KOUS","end":730,"begin":726},{"pos":"PRF","end":735,"begin":731},{"pos":"PRF","end":735,"begin":731},{"pos":"ADV","end":740,"begin":736},{"pos":"ADV","end":740,"begin":736},{"pos":"ART","end":744,"begin":741},{"pos":"ART","end":744,"begin":741},{"pos":"APPR","end":747,"begin":745},{"pos":"APPR","end":747,"begin":745},{"pos":"NN","end":751,"begin":748},{"pos":"NN","end":751,"begin":748},{"pos":"ADJA","end":761,"begin":752},{"pos":"ADJA","end":761,"begin":752},{"pos":"NN","end":770,"begin":762},{"pos":"NN","end":770,"begin":762},{"pos":"ADV","end":777,"begin":771},{"pos":"ADV","end":777,"begin":771},{"pos":"APPR","end":781,"begin":778},{"pos":"APPR","end":781,"begin":778},{"pos":"ART","end":785,"begin":782},{"pos":"ART","end":785,"begin":782},{"pos":"NN","end":789,"begin":786},{"pos":"NN","end":789,"begin":786},{"pos":"APPR","end":792,"begin":790},{"pos":"APPR","end":792,"begin":790},{"pos":"PIS","end":797,"begin":793},{"pos":"ART","end":797,"begin":793},{"pos":"ADJA","end":815,"begin":798},{"pos":"ADJA","end":815,"begin":798},{"pos":"NN","end":823,"begin":816},{"pos":"NN","end":823,"begin":816},{"pos":"VVINF","end":830,"begin":824},{"pos":"VVINF","end":830,"begin":824},{"pos":"VAFIN","end":837,"begin":831},{"pos":"VAFIN","end":837,"begin":831},{"pos":"$,","end":838,"begin":837},{"pos":"$,","end":838,"begin":837},{"pos":"VAFIN","end":842,"begin":839},{"pos":"VAFIN","end":842,"begin":839},{"pos":"ADV","end":854,"begin":843},{"pos":"ADV","end":854,"begin":843},{"pos":"VVIZU","end":864,"begin":855},{"pos":"VVIZU","end":864,"begin":855},{"pos":"$,","end":865,"begin":864},{"pos":"$,","end":865,"begin":864},{"pos":"APPR","end":869,"begin":866},{"pos":"APPR","end":869,"begin":866},{"pos":"PIS","end":875,"begin":870},{"pos":"PIS","end":875,"begin":870},{"pos":"$,","end":876,"begin":875},{"pos":"$,","end":876,"begin":875},{"pos":"KOUS","end":879,"begin":877},{"pos":"ADV","end":879,"begin":877},{"pos":"ART","end":883,"begin":880},{"pos":"ART","end":883,"begin":880},{"pos":"ADJA","end":898,"begin":884},{"pos":"ADJA","end":898,"begin":884},{"pos":"NN","end":913,"begin":899},{"pos":"NE","end":913,"begin":899},{"pos":"ADJD","end":924,"begin":914},{"pos":"ADJD","end":924,"begin":914},{"pos":"VVPP","end":940,"begin":925},{"pos":"VVPP","end":940,"begin":925},{"pos":"VAFIN","end":944,"begin":941},{"pos":"VAFIN","end":944,"begin":941},{"pos":"$.","end":945,"begin":944},{"pos":"$.","end":945,"begin":944},{"pos":"APPR","end":949,"begin":946},{"pos":"APPR","end":949,"begin":946},{"pos":"ART","end":953,"begin":950},{"pos":"ART","end":953,"begin":950},{"pos":"APPR","end":957,"begin":954},{"pos":"APPR","end":957,"begin":954},{"pos":"ART","end":961,"begin":958},{"pos":"ART","end":961,"begin":958},{"pos":"NN","end":976,"begin":962},{"pos":"NN","end":976,"begin":962},{"pos":"ADJA","end":987,"begin":977},{"pos":"ADJA","end":987,"begin":977},{"pos":"CARD","end":991,"begin":988},{"pos":"CARD","end":991,"begin":988},{"pos":"NN","end":1001,"begin":992},{"pos":"NN","end":1001,"begin":992},{"pos":"VAFIN","end":1006,"begin":1002},{"pos":"VAFIN","end":1006,"begin":1002},{"pos":"ADV","end":1016,"begin":1007},{"pos":"ADV","end":1016,"begin":1007},{"pos":"CARD","end":1019,"begin":1017},{"pos":"CARD","end":1019,"begin":1017},{"pos":"VVPP","end":1029,"begin":1020},{"pos":"VVPP","end":1029,"begin":1020},{"pos":"$,","end":1030,"begin":1029},{"pos":"$,","end":1030,"begin":1029},{"pos":"PRELS","end":1034,"begin":1031},{"pos":"PIAT","end":1034,"begin":1031},{"pos":"NN","end":1048,"begin":1035},{"pos":"NN","end":1048,"begin":1035},{"pos":"NE","end":1055,"begin":1049},{"pos":"NE","end":1055,"begin":1049},{"pos":"NE","end":1058,"begin":1056},{"pos":"NE","end":1058,"begin":1056},{"pos":"NN","end":1068,"begin":1059},{"pos":"NN","end":1068,"begin":1059},{"pos":"NN","end":1074,"begin":1069},{"pos":"NN","end":1074,"begin":1069},{"pos":"$(","end":1077,"begin":1076},{"pos":"$(","end":1077,"begin":1076},{"pos":"ADJD","end":1089,"begin":1077},{"pos":"ADJD","end":1089,"begin":1077},{"pos":"VVFIN","end":1096,"begin":1090},{"pos":"VVFIN","end":1096,"begin":1090},{"pos":"PDS","end":1100,"begin":1097},{"pos":"ART","end":1100,"begin":1097},{"pos":"NN","end":1106,"begin":1101},{"pos":"NN","end":1106,"begin":1101},{"pos":"APPR","end":1110,"begin":1107},{"pos":"APPR","end":1110,"begin":1107},{"pos":"NN","end":1114,"begin":1111},{"pos":"NN","end":1114,"begin":1111},{"pos":"APPR","end":1117,"begin":1115},{"pos":"APPR","end":1117,"begin":1115},{"pos":"ART","end":1121,"begin":1118},{"pos":"ART","end":1121,"begin":1118},{"pos":"NN","end":1136,"begin":1122},{"pos":"NN","end":1136,"begin":1122},{"pos":"$(","end":1137,"begin":1136},{"pos":"$(","end":1137,"begin":1136},{"pos":"KON","end":1142,"begin":1139},{"pos":"KOKOM","end":1142,"begin":1139},{"pos":"ADJA","end":1148,"begin":1143},{"pos":"ADJA","end":1148,"begin":1143},{"pos":"NN","end":1153,"begin":1149},{"pos":"NN","end":1153,"begin":1149},{"pos":"VVFIN","end":1160,"begin":1154},{"pos":"VVFIN","end":1160,"begin":1154},{"pos":"$.","end":1161,"begin":1160},{"pos":"$.","end":1161,"begin":1160},{"pos":"NE","end":1170,"begin":1164},{"pos":"NE","end":1169,"begin":1164},{"pos":"NN","end":1174,"begin":1170},{"pos":"NN","end":1174,"begin":1170},{"pos":"VVFIN","end":1179,"begin":1175},{"pos":"VVFIN","end":1179,"begin":1175},{"pos":"NE","end":1191,"begin":1180},{"pos":"NE","end":1191,"begin":1180},{"pos":"KOKOM","end":1195,"begin":1192},{"pos":"KOUS","end":1195,"begin":1192},{"pos":"$(","end":1198,"begin":1197},{"pos":"$(","end":1198,"begin":1197},{"pos":"PIAT","end":1202,"begin":1198},{"pos":"PIAT","end":1202,"begin":1198},{"pos":"NN","end":1220,"begin":1203},{"pos":"NN","end":1220,"begin":1203},{"pos":"$(","end":1221,"begin":1220},{"pos":"$(","end":1221,"begin":1220},{"pos":"$.","end":1223,"begin":1222},{"pos":"$.","end":1223,"begin":1222},{"pos":"NN","end":1233,"begin":1224},{"pos":"NN","end":1233,"begin":1224},{"pos":"VVFIN","end":1244,"begin":1234},{"pos":"VVFIN","end":1244,"begin":1234},{"pos":"PPER","end":1247,"begin":1245},{"pos":"PPER","end":1247,"begin":1245},{"pos":"PTKNEG","end":1253,"begin":1248},{"pos":"PTKNEG","end":1253,"begin":1248},{"pos":"$,","end":1254,"begin":1253},{"pos":"$,","end":1254,"begin":1253},{"pos":"PRELS","end":1258,"begin":1255},{"pos":"ART","end":1258,"begin":1255},{"pos":"NN","end":1265,"begin":1259},{"pos":"NN","end":1265,"begin":1259},{"pos":"ART","end":1269,"begin":1266},{"pos":"ART","end":1269,"begin":1266},{"pos":"NN","end":1281,"begin":1270},{"pos":"NN","end":1281,"begin":1270},{"pos":"APPR","end":1285,"begin":1282},{"pos":"PTKVZ","end":1285,"begin":1282},{"pos":"$(","end":1288,"begin":1287},{"pos":"$(","end":1288,"begin":1287},{"pos":"ADJA","end":1300,"begin":1288},{"pos":"ADJA","end":1300,"begin":1288},{"pos":"NN","end":1315,"begin":1301},{"pos":"NN","end":1315,"begin":1301},{"pos":"$(","end":1316,"begin":1315},{"pos":"$(","end":1316,"begin":1315},{"pos":"ADV","end":1320,"begin":1318},{"pos":"PTKZU","end":1320,"begin":1318},{"pos":"VVINF","end":1328,"begin":1321},{"pos":"VVINF","end":1328,"begin":1321},{"pos":"$,","end":1329,"begin":1328},{"pos":"$,","end":1329,"begin":1328},{"pos":"KOUI","end":1332,"begin":1330},{"pos":"APPR","end":1332,"begin":1330},{"pos":"ADJD","end":1345,"begin":1333},{"pos":"ADJD","end":1345,"begin":1333},{"pos":"APPR","end":1349,"begin":1346},{"pos":"APPR","end":1349,"begin":1346},{"pos":"ART","end":1353,"begin":1350},{"pos":"ART","end":1353,"begin":1350},{"pos":"NN","end":1366,"begin":1354},{"pos":"NN","end":1366,"begin":1354},{"pos":"ART","end":1370,"begin":1367},{"pos":"ART","end":1370,"begin":1367},{"pos":"NN","end":1379,"begin":1371},{"pos":"NN","end":1379,"begin":1371},{"pos":"CARD","end":1382,"begin":1380},{"pos":"CARD","end":1382,"begin":1380},{"pos":"NN","end":1385,"begin":1383},{"pos":"NE","end":1385,"begin":1383},{"pos":"$,","end":1386,"begin":1385},{"pos":"$,","end":1386,"begin":1385},{"pos":"PRELS","end":1390,"begin":1387},{"pos":"ART","end":1390,"begin":1387},{"pos":"ADJA","end":1402,"begin":1391},{"pos":"ADJA","end":1402,"begin":1391},{"pos":"$(","end":1405,"begin":1404},{"pos":"$(","end":1405,"begin":1404},{"pos":"NN","end":1419,"begin":1405},{"pos":"NN","end":1419,"begin":1405},{"pos":"$(","end":1420,"begin":1419},{"pos":"$(","end":1420,"begin":1419},{"pos":"$,","end":1422,"begin":1421},{"pos":"$,","end":1422,"begin":1421},{"pos":"PRELS","end":1426,"begin":1423},{"pos":"ART","end":1426,"begin":1423},{"pos":"NN","end":1439,"begin":1427},{"pos":"NN","end":1439,"begin":1427},{"pos":"APPR","end":1443,"begin":1440},{"pos":"APPR","end":1443,"begin":1440},{"pos":"NN","end":1456,"begin":1444},{"pos":"NN","end":1456,"begin":1444},{"pos":"ADJD","end":1462,"begin":1457},{"pos":"ADJD","end":1462,"begin":1457},{"pos":"PTKVZ","end":1465,"begin":1463},{"pos":"PTKZU","end":1465,"begin":1463},{"pos":"VVINF","end":1472,"begin":1466},{"pos":"VVFIN","end":1472,"begin":1466},{"pos":"$.","end":1473,"begin":1472},{"pos":"$.","end":1473,"begin":1472},{"pos":"APPR","end":1477,"begin":1474},{"pos":"APPR","end":1477,"begin":1474},{"pos":"ART","end":1481,"begin":1478},{"pos":"ART","end":1481,"begin":1478},{"pos":"NN","end":1492,"begin":1482},{"pos":"NN","end":1492,"begin":1482},{"pos":"APPR","end":1496,"begin":1493},{"pos":"NE","end":1496,"begin":1493},{"pos":"$(","end":1499,"begin":1498},{"pos":"$(","end":1499,"begin":1498},{"pos":"ADJA","end":1507,"begin":1499},{"pos":"ADJA","end":1507,"begin":1499},{"pos":"NN","end":1524,"begin":1508},{"pos":"NN","end":1524,"begin":1508},{"pos":"$(","end":1525,"begin":1524},{"pos":"$(","end":1525,"begin":1524},{"pos":"KON","end":1530,"begin":1527},{"pos":"KON","end":1530,"begin":1527},{"pos":"PRELS","end":1534,"begin":1531},{"pos":"ART","end":1534,"begin":1531},{"pos":"NN","end":1555,"begin":1535},{"pos":"NN","end":1555,"begin":1535},{"pos":"APPR","end":1560,"begin":1556},{"pos":"APPR","end":1560,"begin":1556},{"pos":"ART","end":1564,"begin":1561},{"pos":"ART","end":1564,"begin":1561},{"pos":"NN","end":1580,"begin":1565},{"pos":"NE","end":1580,"begin":1565},{"pos":"VMFIN","end":1587,"begin":1581},{"pos":"VMFIN","end":1587,"begin":1581},{"pos":"PRF","end":1592,"begin":1588},{"pos":"PRF","end":1592,"begin":1588},{"pos":"NE","end":1604,"begin":1593},{"pos":"NE","end":1604,"begin":1593},{"pos":"ADV","end":1608,"begin":1605},{"pos":"ADV","end":1608,"begin":1605},{"pos":"APPR","end":1612,"begin":1609},{"pos":"APPR","end":1612,"begin":1609},{"pos":"ART","end":1616,"begin":1613},{"pos":"ART","end":1616,"begin":1613},{"pos":"ADJA","end":1625,"begin":1617},{"pos":"ADJA","end":1625,"begin":1617},{"pos":"NN","end":1631,"begin":1626},{"pos":"NN","end":1631,"begin":1626},{"pos":"VVINF","end":1638,"begin":1632},{"pos":"VVINF","end":1638,"begin":1632},{"pos":"$,","end":1639,"begin":1638},{"pos":"$,","end":1639,"begin":1638},{"pos":"PRELS","end":1643,"begin":1640},{"pos":"ART","end":1643,"begin":1640},{"pos":"NN","end":1652,"begin":1644},{"pos":"NN","end":1652,"begin":1644},{"pos":"VAFIN","end":1658,"begin":1653},{"pos":"VAFIN","end":1658,"begin":1653},{"pos":"APPR","end":1661,"begin":1659},{"pos":"APPR","end":1661,"begin":1659},{"pos":"ART","end":1665,"begin":1662},{"pos":"ART","end":1665,"begin":1662},{"pos":"NN","end":1678,"begin":1666},{"pos":"NN","end":1678,"begin":1666},{"pos":"ART","end":1682,"begin":1679},{"pos":"ART","end":1682,"begin":1679},{"pos":"NE","end":1685,"begin":1683},{"pos":"NE","end":1685,"begin":1683},{"pos":"VVPP","end":1695,"begin":1686},{"pos":"VVPP","end":1695,"begin":1686},{"pos":"VAPP","end":1702,"begin":1696},{"pos":"VAPP","end":1702,"begin":1696},{"pos":"$.","end":1703,"begin":1702},{"pos":"$.","end":1703,"begin":1702},{"pos":"KON","end":1707,"begin":1704},{"pos":"KON","end":1707,"begin":1704},{"pos":"APPR","end":1711,"begin":1708},{"pos":"APPR","end":1711,"begin":1708},{"pos":"ART","end":1715,"begin":1712},{"pos":"ART","end":1715,"begin":1712},{"pos":"$(","end":1718,"begin":1717},{"pos":"$(","end":1718,"begin":1717},{"pos":"NN","end":1727,"begin":1718},{"pos":"NN","end":1727,"begin":1718},{"pos":"$(","end":1728,"begin":1727},{"pos":"$(","end":1728,"begin":1727},{"pos":"PRELS","end":1733,"begin":1730},{"pos":"ART","end":1733,"begin":1730},{"pos":"NN","end":1746,"begin":1734},{"pos":"NN","end":1746,"begin":1734},{"pos":"VAFIN","end":1753,"begin":1747},{"pos":"VAFIN","end":1753,"begin":1747},{"pos":"ADJA","end":1763,"begin":1754},{"pos":"ADJA","end":1763,"begin":1754},{"pos":"NN","end":1770,"begin":1764},{"pos":"NN","end":1770,"begin":1764},{"pos":"VVPP","end":1782,"begin":1771},{"pos":"VVPP","end":1782,"begin":1771},{"pos":"$.","end":1783,"begin":1782},{"pos":"$.","end":1783,"begin":1782},{"pos":"PAV","end":1789,"begin":1784},{"pos":"PAV","end":1789,"begin":1784},{"pos":"VMFIN","end":1797,"begin":1790},{"pos":"VMFIN","end":1797,"begin":1790},{"pos":"NN","end":1819,"begin":1798},{"pos":"NN","end":1819,"begin":1798},{"pos":"APPR","end":1823,"begin":1820},{"pos":"APPR","end":1823,"begin":1820},{"pos":"ADJA","end":1836,"begin":1824},{"pos":"NN","end":1836,"begin":1824},{"pos":"KON","end":1840,"begin":1837},{"pos":"KON","end":1840,"begin":1837},{"pos":"ADJA","end":1855,"begin":1841},{"pos":"ADJA","end":1855,"begin":1841},{"pos":"NN","end":1864,"begin":1856},{"pos":"NN","end":1864,"begin":1856},{"pos":"ADJD","end":1873,"begin":1865},{"pos":"VVPP","end":1873,"begin":1865},{"pos":"VAINF","end":1880,"begin":1874},{"pos":"VAINF","end":1880,"begin":1874},{"pos":"$.","end":1881,"begin":1880},{"pos":"$.","end":1881,"begin":1880},{"pos":"ADV","end":1884,"begin":1882},{"pos":"ADV","end":1884,"begin":1882},{"pos":"VVFIN","end":1889,"begin":1885},{"pos":"VVFIN","end":1889,"begin":1885},{"pos":"PDS","end":1893,"begin":1890},{"pos":"ART","end":1893,"begin":1890},{"pos":"ADJA","end":1899,"begin":1894},{"pos":"NN","end":1899,"begin":1894},{"pos":"NE","end":1906,"begin":1900},{"pos":"NE","end":1906,"begin":1900},{"pos":"NN","end":1913,"begin":1907},{"pos":"NN","end":1913,"begin":1907},{"pos":"ADV","end":1918,"begin":1914},{"pos":"ADV","end":1918,"begin":1914},{"pos":"ART","end":1922,"begin":1919},{"pos":"ART","end":1922,"begin":1919},{"pos":"NN","end":1936,"begin":1923},{"pos":"NN","end":1936,"begin":1923},{"pos":"ADJD","end":1951,"begin":1937},{"pos":"ADJD","end":1951,"begin":1937},{"pos":"APPR","end":1955,"begin":1952},{"pos":"APPR","end":1955,"begin":1952},{"pos":"ART","end":1959,"begin":1956},{"pos":"ART","end":1959,"begin":1956},{"pos":"ADJA","end":1970,"begin":1960},{"pos":"ADJA","end":1970,"begin":1960},{"pos":"NN","end":1987,"begin":1971},{"pos":"NN","end":1987,"begin":1971},{"pos":"ART","end":1991,"begin":1988},{"pos":"ART","end":1991,"begin":1988},{"pos":"ADV","end":1997,"begin":1992},{"pos":"ADV","end":1997,"begin":1992},{"pos":"APPR","end":2000,"begin":1998},{"pos":"APPR","end":2000,"begin":1998},{"pos":"NN","end":2011,"begin":2001},{"pos":"NN","end":2011,"begin":2001},{"pos":"ADJA","end":2021,"begin":2012},{"pos":"ADJA","end":2021,"begin":2012},{"pos":"NN","end":2040,"begin":2022},{"pos":"NN","end":2040,"begin":2022},{"pos":"$.","end":2041,"begin":2040},{"pos":"$.","end":2041,"begin":2040},{"pos":"APPR","end":2045,"begin":2042},{"pos":"APPR","end":2045,"begin":2042},{"pos":"PDAT","end":2055,"begin":2046},{"pos":"PDAT","end":2055,"begin":2046},{"pos":"NN","end":2069,"begin":2056},{"pos":"NN","end":2069,"begin":2056},{"pos":"VAFIN","end":2073,"begin":2070},{"pos":"VAFIN","end":2073,"begin":2070},{"pos":"PDS","end":2078,"begin":2074},{"pos":"PDS","end":2078,"begin":2074},{"pos":"ADV","end":2083,"begin":2079},{"pos":"ADV","end":2083,"begin":2079},{"pos":"ART","end":2087,"begin":2084},{"pos":"ART","end":2087,"begin":2084},{"pos":"NN","end":2097,"begin":2088},{"pos":"NN","end":2097,"begin":2088},{"pos":"$,","end":2098,"begin":2097},{"pos":"$,","end":2098,"begin":2097},{"pos":"KOUI","end":2101,"begin":2099},{"pos":"APPR","end":2101,"begin":2099},{"pos":"ADV","end":2109,"begin":2102},{"pos":"ADV","end":2109,"begin":2102},{"pos":"PDS","end":2113,"begin":2110},{"pos":"ART","end":2113,"begin":2110},{"pos":"ADJA","end":2122,"begin":2114},{"pos":"ADJA","end":2122,"begin":2114},{"pos":"NN","end":2132,"begin":2123},{"pos":"NN","end":2132,"begin":2123},{"pos":"VVINF","end":2144,"begin":2133},{"pos":"VVINF","end":2144,"begin":2133},{"pos":"$.","end":2145,"begin":2144},{"pos":"$.","end":2145,"begin":2144},{"pos":"KOUS","end":2150,"begin":2146},{"pos":"KOUS","end":2150,"begin":2146},{"pos":"PDS","end":2154,"begin":2151},{"pos":"ART","end":2154,"begin":2151},{"pos":"NN","end":2166,"begin":2155},{"pos":"NN","end":2166,"begin":2155},{"pos":"VVPP","end":2179,"begin":2167},{"pos":"VVPP","end":2179,"begin":2167},{"pos":"VAFIN","end":2184,"begin":2180},{"pos":"VAFIN","end":2184,"begin":2180},{"pos":"$,","end":2185,"begin":2184},{"pos":"$,","end":2185,"begin":2184},{"pos":"VMFIN","end":2190,"begin":2186},{"pos":"VMFIN","end":2190,"begin":2186},{"pos":"NE","end":2197,"begin":2191},{"pos":"NE","end":2197,"begin":2191},{"pos":"NE","end":2200,"begin":2198},{"pos":"NE","end":2200,"begin":2198},{"pos":"NN","end":2209,"begin":2201},{"pos":"NN","end":2209,"begin":2201},{"pos":"ADV","end":2214,"begin":2210},{"pos":"ADV","end":2214,"begin":2210},{"pos":"ADJD","end":2224,"begin":2215},{"pos":"ADJD","end":2224,"begin":2215},{"pos":"ADJA","end":2234,"begin":2225},{"pos":"NN","end":2234,"begin":2225},{"pos":"APPR","end":2237,"begin":2235},{"pos":"APPR","end":2237,"begin":2235},{"pos":"PPOSAT","end":2242,"begin":2238},{"pos":"PPOSAT","end":2242,"begin":2238},{"pos":"NN","end":2257,"begin":2243},{"pos":"NN","end":2257,"begin":2243},{"pos":"VVINF","end":2272,"begin":2258},{"pos":"VVINF","end":2272,"begin":2258},{"pos":"$,","end":2273,"begin":2272},{"pos":"$,","end":2273,"begin":2272},{"pos":"KOUS","end":2277,"begin":2274},{"pos":"KOUS","end":2277,"begin":2274},{"pos":"PPER","end":2280,"begin":2278},{"pos":"PPER","end":2280,"begin":2278},{"pos":"ADV","end":2287,"begin":2281},{"pos":"ADV","end":2287,"begin":2281},{"pos":"APPR","end":2290,"begin":2288},{"pos":"APPR","end":2290,"begin":2288},{"pos":"PIS","end":2296,"begin":2291},{"pos":"ART","end":2296,"begin":2291},{"pos":"NN","end":2306,"begin":2297},{"pos":"NN","end":2306,"begin":2297},{"pos":"VVFIN","end":2312,"begin":2307},{"pos":"VVFIN","end":2312,"begin":2307},{"pos":"$.","end":2313,"begin":2312},{"pos":"$.","end":2313,"begin":2312},{"pos":"$(","end":2316,"begin":2315},{"pos":"$(","end":2316,"begin":2315},{"pos":"ART","end":2319,"begin":2316},{"pos":"PDS","end":2319,"begin":2316},{"pos":"VMINF","end":2326,"begin":2320},{"pos":"VMFIN","end":2326,"begin":2320},{"pos":"PPER","end":2330,"begin":2327},{"pos":"PPER","end":2330,"begin":2327},{"pos":"PTKNEG","end":2336,"begin":2331},{"pos":"PTKNEG","end":2336,"begin":2331},{"pos":"APPRART","end":2339,"begin":2337},{"pos":"APPRART","end":2339,"begin":2337},{"pos":"NN","end":2345,"begin":2340},{"pos":"NN","end":2345,"begin":2340},{"pos":"VVINF","end":2352,"begin":2346},{"pos":"VVINF","end":2352,"begin":2346},{"pos":"$.","end":2353,"begin":2352},{"pos":"$.","end":2353,"begin":2352},{"pos":"PPER","end":2357,"begin":2354},{"pos":"PPER","end":2357,"begin":2354},{"pos":"VMFIN","end":2364,"begin":2358},{"pos":"VMINF","end":2364,"begin":2358},{"pos":"VVINF","end":2378,"begin":2365},{"pos":"VVINF","end":2378,"begin":2365},{"pos":"$,","end":2379,"begin":2378},{"pos":"$,","end":2379,"begin":2378},{"pos":"KOUS","end":2384,"begin":2380},{"pos":"KOUS","end":2384,"begin":2380},{"pos":"PPER","end":2388,"begin":2385},{"pos":"PPER","end":2388,"begin":2385},{"pos":"APPR","end":2391,"begin":2389},{"pos":"APPR","end":2391,"begin":2389},{"pos":"ART","end":2395,"begin":2392},{"pos":"ART","end":2395,"begin":2392},{"pos":"NN","end":2402,"begin":2396},{"pos":"NN","end":2402,"begin":2396},{"pos":"$,","end":2403,"begin":2402},{"pos":"$,","end":2403,"begin":2402},{"pos":"APPR","end":2407,"begin":2404},{"pos":"APPR","end":2407,"begin":2404},{"pos":"ART","end":2411,"begin":2408},{"pos":"PRELS","end":2411,"begin":2408},{"pos":"PPER","end":2415,"begin":2412},{"pos":"PPER","end":2415,"begin":2412},{"pos":"VVINF","end":2422,"begin":2416},{"pos":"VVINF","end":2422,"begin":2416},{"pos":"$,","end":2423,"begin":2422},{"pos":"$,","end":2423,"begin":2422},{"pos":"ADJD","end":2430,"begin":2424},{"pos":"ADJD","end":2430,"begin":2424},{"pos":"KON","end":2434,"begin":2431},{"pos":"KON","end":2434,"begin":2431},{"pos":"KOUI","end":2439,"begin":2435},{"pos":"APPR","end":2439,"begin":2435},{"pos":"NN","end":2450,"begin":2440},{"pos":"NN","end":2450,"begin":2440},{"pos":"VVINF","end":2456,"begin":2451},{"pos":"VVINF","end":2456,"begin":2451},{"pos":"VMINF","end":2463,"begin":2457},{"pos":"VMINF","end":2463,"begin":2457},{"pos":"$.","end":2464,"begin":2463},{"pos":"$.","end":2464,"begin":2463},{"pos":"$(","end":2465,"begin":2464},{"pos":"$(","end":2465,"begin":2464},{"pos":"KON","end":2470,"begin":2467},{"pos":"KOUS","end":2470,"begin":2467},{"pos":"PDS","end":2474,"begin":2471},{"pos":"PDS","end":2474,"begin":2471},{"pos":"VVINF","end":2480,"begin":2475},{"pos":"VVINF","end":2480,"begin":2475},{"pos":"VMFIN","end":2485,"begin":2481},{"pos":"VMFIN","end":2485,"begin":2481},{"pos":"$,","end":2486,"begin":2485},{"pos":"$,","end":2486,"begin":2485},{"pos":"VVFIN","end":2493,"begin":2487},{"pos":"VVFIN","end":2493,"begin":2487},{"pos":"NE","end":2496,"begin":2494},{"pos":"NE","end":2496,"begin":2494},{"pos":"NN","end":2506,"begin":2497},{"pos":"NN","end":2506,"begin":2497},{"pos":"NN","end":2516,"begin":2507},{"pos":"NN","end":2516,"begin":2507},{"pos":"$.","end":2517,"begin":2516},{"pos":"$.","end":2517,"begin":2516},{"pos":"NE","end":2523,"begin":2518},{"pos":"NE","end":2523,"begin":2518},{"pos":"VVFIN","end":2541,"begin":2524},{"pos":"ADJD","end":2541,"begin":2524},{"pos":"$,","end":2542,"begin":2541},{"pos":"$,","end":2542,"begin":2541},{"pos":"NE","end":2552,"begin":2543},{"pos":"NE","end":2552,"begin":2543},{"pos":"ADV","end":2561,"begin":2555},{"pos":"PIAT","end":2560,"begin":2555},{"pos":"ADJA","end":2565,"begin":2561},{"pos":"ADJA","end":2565,"begin":2561},{"pos":"NN","end":2575,"begin":2566},{"pos":"NN","end":2575,"begin":2566},{"pos":"ADJD","end":2584,"begin":2578},{"pos":"APPR","end":2583,"begin":2578},{"pos":"$.","end":2584,"begin":2583},{"pos":"$.","end":2584,"begin":2583},{"pos":"$(","end":2587,"begin":2586},{"pos":"$(","end":2587,"begin":2586},{"pos":"ADV","end":2591,"begin":2587},{"pos":"ADV","end":2591,"begin":2587},{"pos":"VAFIN","end":2595,"begin":2592},{"pos":"VAFIN","end":2595,"begin":2592},{"pos":"PDS","end":2599,"begin":2596},{"pos":"PDS","end":2599,"begin":2596},{"pos":"PPOSAT","end":2604,"begin":2600},{"pos":"PPOSAT","end":2604,"begin":2600},{"pos":"NN","end":2609,"begin":2605},{"pos":"NN","end":2609,"begin":2605},{"pos":"$(","end":2610,"begin":2609},{"pos":"$(","end":2610,"begin":2609},{"pos":"$,","end":2612,"begin":2611},{"pos":"$,","end":2612,"begin":2611},{"pos":"NE","end":2616,"begin":2613},{"pos":"NE","end":2616,"begin":2613},{"pos":"APPRART","end":2620,"begin":2617},{"pos":"APPRART","end":2620,"begin":2617},{"pos":"ADJA","end":2624,"begin":2621},{"pos":"ADJA","end":2624,"begin":2621},{"pos":"ADJA","end":2627,"begin":2625},{"pos":"ADJA","end":2627,"begin":2625},{"pos":"CARD","end":2630,"begin":2628},{"pos":"CARD","end":2630,"begin":2628},{"pos":"NE","end":2636,"begin":2633},{"pos":"ADV","end":2635,"begin":2633},{"pos":"$,","end":2636,"begin":2635},{"pos":"$,","end":2636,"begin":2635},{"pos":"PIS","end":2640,"begin":2637},{"pos":"PIS","end":2640,"begin":2637},{"pos":"VMFIN","end":2645,"begin":2641},{"pos":"VMFIN","end":2645,"begin":2641},{"pos":"PRF","end":2650,"begin":2646},{"pos":"PRF","end":2650,"begin":2646},{"pos":"ART","end":2654,"begin":2651},{"pos":"ART","end":2654,"begin":2651},{"pos":"NN","end":2663,"begin":2655},{"pos":"NN","end":2663,"begin":2655},{"pos":"$,","end":2664,"begin":2663},{"pos":"$,","end":2664,"begin":2663},{"pos":"PRELS","end":2668,"begin":2665},{"pos":"ART","end":2668,"begin":2665},{"pos":"APPR","end":2671,"begin":2669},{"pos":"APPR","end":2671,"begin":2669},{"pos":"NN","end":2681,"begin":2672},{"pos":"NN","end":2681,"begin":2672},{"pos":"ART","end":2685,"begin":2682},{"pos":"ART","end":2685,"begin":2682},{"pos":"NN","end":2698,"begin":2686},{"pos":"NN","end":2698,"begin":2686},{"pos":"VVINF","end":2705,"begin":2699},{"pos":"VVINF","end":2705,"begin":2699},{"pos":"$,","end":2706,"begin":2705},{"pos":"$,","end":2706,"begin":2705},{"pos":"KOUS","end":2711,"begin":2707},{"pos":"KOUS","end":2711,"begin":2707},{"pos":"NN","end":2720,"begin":2712},{"pos":"NN","end":2720,"begin":2712},{"pos":"APPR","end":2723,"begin":2721},{"pos":"APPR","end":2723,"begin":2721},{"pos":"PPER","end":2729,"begin":2724},{"pos":"PPER","end":2729,"begin":2724},{"pos":"VVPP","end":2737,"begin":2730},{"pos":"VVPP","end":2737,"begin":2730},{"pos":"VAPP","end":2744,"begin":2738},{"pos":"VAPP","end":2744,"begin":2738},{"pos":"VAFIN","end":2748,"begin":2745},{"pos":"VAFIN","end":2748,"begin":2745},{"pos":"$,","end":2749,"begin":2748},{"pos":"$,","end":2749,"begin":2748},{"pos":"ADJD","end":2759,"begin":2750},{"pos":"ADJD","end":2759,"begin":2750},{"pos":"VVINF","end":2766,"begin":2760},{"pos":"VVINF","end":2766,"begin":2760},{"pos":"$.","end":2767,"begin":2766},{"pos":"$.","end":2767,"begin":2766},{"pos":"PTKANT","end":2772,"begin":2768},{"pos":"PTKANT","end":2772,"begin":2768},{"pos":"$,","end":2773,"begin":2772},{"pos":"$,","end":2773,"begin":2772},{"pos":"PTKNEG","end":2779,"begin":2774},{"pos":"PTKNEG","end":2779,"begin":2774},{"pos":"PRELS","end":2783,"begin":2780},{"pos":"ART","end":2783,"begin":2780},{"pos":"ADJA","end":2795,"begin":2784},{"pos":"ADJA","end":2795,"begin":2784},{"pos":"NN","end":2807,"begin":2796},{"pos":"NN","end":2807,"begin":2796},{"pos":"$,","end":2808,"begin":2807},{"pos":"$,","end":2808,"begin":2807},{"pos":"PRELS","end":2812,"begin":2809},{"pos":"PDS","end":2812,"begin":2809},{"pos":"VAINF","end":2818,"begin":2813},{"pos":"VAFIN","end":2818,"begin":2813},{"pos":"PDS","end":2822,"begin":2819},{"pos":"ART","end":2822,"begin":2819},{"pos":"TRUNC","end":2830,"begin":2823},{"pos":"TRUNC","end":2830,"begin":2823},{"pos":"KON","end":2834,"begin":2831},{"pos":"KON","end":2834,"begin":2831},{"pos":"NN","end":2852,"begin":2835},{"pos":"NN","end":2852,"begin":2835},{"pos":"$,","end":2853,"begin":2852},{"pos":"$,","end":2853,"begin":2852},{"pos":"PRELS","end":2857,"begin":2854},{"pos":"ART","end":2857,"begin":2854},{"pos":"NE","end":2863,"begin":2858},{"pos":"NE","end":2863,"begin":2858},{"pos":"NN","end":2871,"begin":2864},{"pos":"NN","end":2871,"begin":2864},{"pos":"PPER","end":2875,"begin":2872},{"pos":"PRF","end":2875,"begin":2872},{"pos":"VVINF","end":2884,"begin":2876},{"pos":"VVINF","end":2884,"begin":2876},{"pos":"VMFIN","end":2889,"begin":2885},{"pos":"VMFIN","end":2889,"begin":2885},{"pos":"$,","end":2890,"begin":2889},{"pos":"$,","end":2890,"begin":2889},{"pos":"ADJD","end":2895,"begin":2891},{"pos":"ADJD","end":2895,"begin":2891},{"pos":"APPRART","end":2898,"begin":2896},{"pos":"APPRART","end":2898,"begin":2896},{"pos":"NN","end":2904,"begin":2899},{"pos":"NN","end":2904,"begin":2899},{"pos":"$.","end":2905,"begin":2904},{"pos":"$.","end":2905,"begin":2904},{"pos":"APPR","end":2910,"begin":2906},{"pos":"APPR","end":2910,"begin":2906},{"pos":"NN","end":2933,"begin":2911},{"pos":"NN","end":2933,"begin":2911},{"pos":"$,","end":2934,"begin":2933},{"pos":"$,","end":2934,"begin":2933},{"pos":"APPR","end":2939,"begin":2935},{"pos":"APPR","end":2939,"begin":2935},{"pos":"NN","end":2954,"begin":2940},{"pos":"NN","end":2954,"begin":2940},{"pos":"ART","end":2958,"begin":2955},{"pos":"ART","end":2958,"begin":2955},{"pos":"NN","end":2968,"begin":2959},{"pos":"NN","end":2968,"begin":2959},{"pos":"APPR","end":2974,"begin":2969},{"pos":"APPR","end":2974,"begin":2969},{"pos":"ADJA","end":2983,"begin":2975},{"pos":"ADJA","end":2983,"begin":2975},{"pos":"NN","end":2996,"begin":2984},{"pos":"NN","end":2996,"begin":2984},{"pos":"$,","end":2997,"begin":2996},{"pos":"$,","end":2997,"begin":2996},{"pos":"APPR","end":3003,"begin":2998},{"pos":"APPR","end":3003,"begin":2998},{"pos":"NN","end":3014,"begin":3004},{"pos":"NN","end":3014,"begin":3004},{"pos":"PIAT","end":3020,"begin":3015},{"pos":"PIAT","end":3020,"begin":3015},{"pos":"ADJA","end":3035,"begin":3021},{"pos":"ADJA","end":3035,"begin":3021},{"pos":"NN","end":3044,"begin":3036},{"pos":"NN","end":3044,"begin":3036},{"pos":"$,","end":3045,"begin":3044},{"pos":"$,","end":3045,"begin":3044},{"pos":"APPR","end":3049,"begin":3046},{"pos":"APPR","end":3049,"begin":3046},{"pos":"ART","end":3053,"begin":3050},{"pos":"ART","end":3053,"begin":3050},{"pos":"APPR","end":3057,"begin":3054},{"pos":"APPR","end":3057,"begin":3054},{"pos":"PPER","end":3063,"begin":3058},{"pos":"PPER","end":3063,"begin":3058},{"pos":"APPR","end":3067,"begin":3064},{"pos":"APPR","end":3067,"begin":3064},{"pos":"NN","end":3084,"begin":3068},{"pos":"NN","end":3084,"begin":3068},{"pos":"VVFIN","end":3097,"begin":3085},{"pos":"ADJA","end":3097,"begin":3085},{"pos":"NN","end":3108,"begin":3098},{"pos":"NN","end":3108,"begin":3098},{"pos":"KON","end":3112,"begin":3109},{"pos":"KON","end":3112,"begin":3109},{"pos":"$,","end":3113,"begin":3112},{"pos":"$,","end":3113,"begin":3112},{"pos":"KOUS","end":3118,"begin":3114},{"pos":"KOUS","end":3118,"begin":3114},{"pos":"PPER","end":3121,"begin":3119},{"pos":"PPER","end":3121,"begin":3119},{"pos":"VAINF","end":3126,"begin":3122},{"pos":"VAINF","end":3126,"begin":3122},{"pos":"VMFIN","end":3131,"begin":3127},{"pos":"VMFIN","end":3131,"begin":3127},{"pos":"$,","end":3132,"begin":3131},{"pos":"$,","end":3132,"begin":3131},{"pos":"ADV","end":3137,"begin":3133},{"pos":"ADV","end":3137,"begin":3133},{"pos":"APPR","end":3141,"begin":3138},{"pos":"APPR","end":3141,"begin":3138},{"pos":"ADJA","end":3150,"begin":3142},{"pos":"ADJA","end":3150,"begin":3142},{"pos":"NN","end":3157,"begin":3151},{"pos":"NN","end":3157,"begin":3151},{"pos":"$.","end":3158,"begin":3157},{"pos":"$.","end":3158,"begin":3157},{"pos":"NN","end":3163,"begin":3159},{"pos":"NN","end":3163,"begin":3159},{"pos":"NE","end":3170,"begin":3164},{"pos":"NE","end":3170,"begin":3164},{"pos":"VAFIN","end":3174,"begin":3171},{"pos":"VAFIN","end":3174,"begin":3171},{"pos":"ADJD","end":3184,"begin":3175},{"pos":"ADJD","end":3184,"begin":3175},{"pos":"PIS","end":3189,"begin":3185},{"pos":"ART","end":3189,"begin":3185},{"pos":"ADJA","end":3194,"begin":3190},{"pos":"ADJA","end":3194,"begin":3190},{"pos":"NN","end":3204,"begin":3195},{"pos":"NN","end":3204,"begin":3195},{"pos":"PTKNEG","end":3210,"begin":3205},{"pos":"PTKNEG","end":3210,"begin":3205},{"pos":"ADJD","end":3221,"begin":3211},{"pos":"VVPP","end":3221,"begin":3211},{"pos":"$,","end":3222,"begin":3221},{"pos":"$,","end":3222,"begin":3221},{"pos":"KON","end":3227,"begin":3223},{"pos":"ADV","end":3227,"begin":3223},{"pos":"APPR","end":3231,"begin":3228},{"pos":"APPR","end":3231,"begin":3228},{"pos":"NE","end":3243,"begin":3232},{"pos":"NE","end":3243,"begin":3232},{"pos":"KON","end":3248,"begin":3244},{"pos":"KON","end":3248,"begin":3244},{"pos":"PWS","end":3252,"begin":3249},{"pos":"PWS","end":3252,"begin":3249},{"pos":"ADV","end":3258,"begin":3253},{"pos":"ADV","end":3258,"begin":3253},{"pos":"ADV","end":3265,"begin":3259},{"pos":"ADV","end":3265,"begin":3259},{"pos":"VVPP","end":3277,"begin":3266},{"pos":"VVPP","end":3277,"begin":3266},{"pos":"$.","end":3278,"begin":3277},{"pos":"$.","end":3278,"begin":3277},{"pos":"ART","end":3282,"begin":3279},{"pos":"ART","end":3282,"begin":3279},{"pos":"NN","end":3288,"begin":3283},{"pos":"NN","end":3288,"begin":3283},{"pos":"VVINF","end":3295,"begin":3289},{"pos":"VVFIN","end":3295,"begin":3289},{"pos":"$,","end":3296,"begin":3295},{"pos":"$,","end":3296,"begin":3295},{"pos":"ART","end":3300,"begin":3297},{"pos":"ART","end":3300,"begin":3297},{"pos":"ADV","end":3309,"begin":3301},{"pos":"ADV","end":3309,"begin":3301},{"pos":"ADV","end":3320,"begin":3310},{"pos":"ADV","end":3320,"begin":3310},{"pos":"$,","end":3321,"begin":3320},{"pos":"$,","end":3321,"begin":3320},{"pos":"PDS","end":3328,"begin":3322},{"pos":"PDAT","end":3328,"begin":3322},{"pos":"ADJA","end":3335,"begin":3329},{"pos":"ADJA","end":3335,"begin":3329},{"pos":"KON","end":3340,"begin":3336},{"pos":"ADV","end":3340,"begin":3336},{"pos":"ADJD","end":3352,"begin":3341},{"pos":"ADJD","end":3352,"begin":3341},{"pos":"KON","end":3356,"begin":3353},{"pos":"KON","end":3356,"begin":3353},{"pos":"$,","end":3357,"begin":3356},{"pos":"$,","end":3357,"begin":3356},{"pos":"KOUS","end":3362,"begin":3358},{"pos":"KOUS","end":3362,"begin":3358},{"pos":"PPER","end":3365,"begin":3363},{"pos":"PPER","end":3365,"begin":3363},{"pos":"VVFIN","end":3371,"begin":3366},{"pos":"VVFIN","end":3371,"begin":3366},{"pos":"$,","end":3372,"begin":3371},{"pos":"$,","end":3372,"begin":3371},{"pos":"ADV","end":3377,"begin":3373},{"pos":"ADV","end":3377,"begin":3373},{"pos":"ADJD","end":3387,"begin":3378},{"pos":"ADJD","end":3387,"begin":3378},{"pos":"ADJD","end":3396,"begin":3388},{"pos":"VVPP","end":3396,"begin":3388},{"pos":"$,","end":3397,"begin":3396},{"pos":"$,","end":3397,"begin":3396},{"pos":"KOUS","end":3403,"begin":3398},{"pos":"PAV","end":3403,"begin":3398},{"pos":"PDS","end":3407,"begin":3404},{"pos":"ART","end":3407,"begin":3404},{"pos":"NN","end":3416,"begin":3408},{"pos":"NN","end":3416,"begin":3408},{"pos":"PTKNEG","end":3422,"begin":3417},{"pos":"PTKNEG","end":3422,"begin":3417},{"pos":"ADV","end":3425,"begin":3423},{"pos":"ADV","end":3425,"begin":3423},{"pos":"ADJD","end":3433,"begin":3426},{"pos":"ADJD","end":3433,"begin":3426},{"pos":"VVFIN","end":3446,"begin":3434},{"pos":"VVFIN","end":3446,"begin":3434},{"pos":"$.","end":3447,"begin":3446},{"pos":"$.","end":3447,"begin":3446},{"pos":"KOUS","end":3452,"begin":3448},{"pos":"KOUS","end":3452,"begin":3448},{"pos":"PDS","end":3456,"begin":3453},{"pos":"ART","end":3456,"begin":3453},{"pos":"NN","end":3466,"begin":3457},{"pos":"NN","end":3466,"begin":3457},{"pos":"ADJD","end":3476,"begin":3467},{"pos":"ADJD","end":3476,"begin":3467},{"pos":"ADJD","end":3484,"begin":3477},{"pos":"ADJD","end":3484,"begin":3477},{"pos":"ART","end":3490,"begin":3485},{"pos":"ADJA","end":3490,"begin":3485},{"pos":"NN","end":3495,"begin":3491},{"pos":"NN","end":3495,"begin":3491},{"pos":"VVFIN","end":3500,"begin":3496},{"pos":"VVFIN","end":3500,"begin":3496},{"pos":"$,","end":3501,"begin":3500},{"pos":"$,","end":3501,"begin":3500},{"pos":"PRELS","end":3505,"begin":3502},{"pos":"PDS","end":3505,"begin":3502},{"pos":"VVINF","end":3516,"begin":3506},{"pos":"VVINF","end":3516,"begin":3506},{"pos":"VVFIN","end":3522,"begin":3517},{"pos":"VVFIN","end":3522,"begin":3517},{"pos":"$,","end":3523,"begin":3522},{"pos":"$,","end":3523,"begin":3522},{"pos":"VAFIN","end":3529,"begin":3524},{"pos":"VAFIN","end":3529,"begin":3524},{"pos":"PPOSAT","end":3534,"begin":3530},{"pos":"PPOSAT","end":3534,"begin":3530},{"pos":"NN","end":3542,"begin":3535},{"pos":"NN","end":3542,"begin":3535},{"pos":"PTKNEG","end":3548,"begin":3543},{"pos":"PTKNEG","end":3548,"begin":3543},{"pos":"ADV","end":3552,"begin":3549},{"pos":"ADV","end":3552,"begin":3549},{"pos":"ART","end":3556,"begin":3553},{"pos":"ART","end":3556,"begin":3553},{"pos":"NN","end":3562,"begin":3557},{"pos":"NN","end":3562,"begin":3557},{"pos":"$,","end":3563,"begin":3562},{"pos":"$,","end":3563,"begin":3562},{"pos":"KON","end":3571,"begin":3564},{"pos":"KON","end":3571,"begin":3564},{"pos":"PRELS","end":3575,"begin":3572},{"pos":"ART","end":3575,"begin":3572},{"pos":"NN","end":3580,"begin":3576},{"pos":"NN","end":3580,"begin":3576},{"pos":"KON","end":3584,"begin":3581},{"pos":"KON","end":3584,"begin":3581},{"pos":"PRELS","end":3588,"begin":3585},{"pos":"ART","end":3588,"begin":3585},{"pos":"NN","end":3601,"begin":3589},{"pos":"NN","end":3601,"begin":3589},{"pos":"APPR","end":3604,"begin":3602},{"pos":"APPR","end":3604,"begin":3602},{"pos":"PPER","end":3608,"begin":3605},{"pos":"PPOSAT","end":3608,"begin":3605},{"pos":"NN","end":3618,"begin":3609},{"pos":"NN","end":3618,"begin":3609},{"pos":"VVINF","end":3633,"begin":3619},{"pos":"VVFIN","end":3633,"begin":3619},{"pos":"$.","end":3634,"begin":3633},{"pos":"$.","end":3634,"begin":3633},{"pos":"ADV","end":3637,"begin":3635},{"pos":"ADV","end":3637,"begin":3635},{"pos":"VVFIN","end":3644,"begin":3638},{"pos":"VVFIN","end":3644,"begin":3638},{"pos":"NN","end":3656,"begin":3645},{"pos":"NN","end":3656,"begin":3645},{"pos":"$,","end":3657,"begin":3656},{"pos":"$,","end":3657,"begin":3656},{"pos":"PRELS","end":3661,"begin":3658},{"pos":"ART","end":3661,"begin":3658},{"pos":"ADJD","end":3670,"begin":3662},{"pos":"ADJD","end":3670,"begin":3662},{"pos":"VVINF","end":3681,"begin":3671},{"pos":"VVINF","end":3681,"begin":3671},{"pos":"KON","end":3685,"begin":3682},{"pos":"KON","end":3685,"begin":3682},{"pos":"VVINF","end":3694,"begin":3686},{"pos":"VVINF","end":3694,"begin":3686},{"pos":"$,","end":3695,"begin":3694},{"pos":"$,","end":3695,"begin":3694},{"pos":"PRELS","end":3699,"begin":3696},{"pos":"PIS","end":3699,"begin":3696},{"pos":"VVFIN","end":3709,"begin":3700},{"pos":"VVFIN","end":3709,"begin":3700},{"pos":"$,","end":3710,"begin":3709},{"pos":"$,","end":3710,"begin":3709},{"pos":"KON","end":3714,"begin":3711},{"pos":"KON","end":3714,"begin":3711},{"pos":"PDS","end":3718,"begin":3715},{"pos":"ART","end":3718,"begin":3715},{"pos":"ADJA","end":3735,"begin":3719},{"pos":"ADJA","end":3735,"begin":3719},{"pos":"NN","end":3752,"begin":3736},{"pos":"NN","end":3752,"begin":3736},{"pos":"ART","end":3756,"begin":3753},{"pos":"ART","end":3756,"begin":3753},{"pos":"NN","end":3766,"begin":3757},{"pos":"NN","end":3766,"begin":3757},{"pos":"VVINF","end":3779,"begin":3767},{"pos":"VVINF","end":3779,"begin":3767},{"pos":"$.","end":3780,"begin":3779},{"pos":"$.","end":3780,"begin":3779},{"pos":"NN","end":3786,"begin":3783},{"pos":"APPR","end":3785,"begin":3783},{"pos":"PDAT","end":3792,"begin":3786},{"pos":"PDAT","end":3792,"begin":3786},{"pos":"NN","end":3804,"begin":3793},{"pos":"NN","end":3804,"begin":3793},{"pos":"VAFIN","end":3808,"begin":3805},{"pos":"VAFIN","end":3808,"begin":3805},{"pos":"PRF","end":3813,"begin":3809},{"pos":"PRF","end":3813,"begin":3809},{"pos":"PIAT","end":3818,"begin":3814},{"pos":"PIAT","end":3818,"begin":3814},{"pos":"PIS","end":3827,"begin":3819},{"pos":"ADV","end":3827,"begin":3819},{"pos":"ADJD","end":3836,"begin":3828},{"pos":"VVPP","end":3836,"begin":3828},{"pos":"$,","end":3837,"begin":3836},{"pos":"$,","end":3837,"begin":3836},{"pos":"PRELS","end":3841,"begin":3838},{"pos":"ART","end":3841,"begin":3838},{"pos":"PIAT","end":3852,"begin":3842},{"pos":"PIAT","end":3852,"begin":3842},{"pos":"NN","end":3856,"begin":3853},{"pos":"NN","end":3856,"begin":3853},{"pos":"APPR","end":3860,"begin":3857},{"pos":"APPR","end":3860,"begin":3857},{"pos":"ADJA","end":3862,"begin":3861},{"pos":"NN","end":3862,"begin":3861},{"pos":"ADJA","end":3869,"begin":3863},{"pos":"ADJA","end":3869,"begin":3863},{"pos":"NN","end":3871,"begin":3870},{"pos":"ADJA","end":3871,"begin":3870},{"pos":"NN","end":3884,"begin":3872},{"pos":"NN","end":3884,"begin":3872},{"pos":"VVINF","end":3898,"begin":3885},{"pos":"VVINF","end":3898,"begin":3885},{"pos":"VMFIN","end":3905,"begin":3899},{"pos":"VMFIN","end":3905,"begin":3899},{"pos":"$.","end":3906,"begin":3905},{"pos":"$.","end":3906,"begin":3905},{"pos":"ART","end":3910,"begin":3907},{"pos":"ART","end":3910,"begin":3907},{"pos":"NN","end":3922,"begin":3911},{"pos":"NN","end":3922,"begin":3911},{"pos":"VAINF","end":3929,"begin":3923},{"pos":"VAFIN","end":3929,"begin":3923},{"pos":"ADV","end":3936,"begin":3930},{"pos":"ADV","end":3936,"begin":3930},{"pos":"VVPP","end":3947,"begin":3937},{"pos":"VVPP","end":3947,"begin":3937},{"pos":"$,","end":3948,"begin":3947},{"pos":"$,","end":3948,"begin":3947},{"pos":"$(","end":3951,"begin":3950},{"pos":"$(","end":3951,"begin":3950},{"pos":"PTKNEG","end":3956,"begin":3951},{"pos":"PTKNEG","end":3956,"begin":3951},{"pos":"PIAT","end":3962,"begin":3957},{"pos":"PIS","end":3962,"begin":3957},{"pos":"VMFIN","end":3967,"begin":3963},{"pos":"VMFIN","end":3967,"begin":3963},{"pos":"VVINF","end":3975,"begin":3968},{"pos":"VVINF","end":3975,"begin":3968},{"pos":"$(","end":3976,"begin":3975},{"pos":"$(","end":3976,"begin":3975},{"pos":"$,","end":3978,"begin":3977},{"pos":"$,","end":3978,"begin":3977},{"pos":"VVFIN","end":3984,"begin":3979},{"pos":"VVFIN","end":3984,"begin":3979},{"pos":"PDS","end":3988,"begin":3985},{"pos":"ART","end":3988,"begin":3985},{"pos":"NN","end":3998,"begin":3989},{"pos":"NN","end":3998,"begin":3989},{"pos":"PRF","end":4003,"begin":3999},{"pos":"PRF","end":4003,"begin":3999},{"pos":"ADV","end":4010,"begin":4004},{"pos":"ADV","end":4010,"begin":4004},{"pos":"ADV","end":4017,"begin":4011},{"pos":"PTKVZ","end":4017,"begin":4011},{"pos":"$,","end":4018,"begin":4017},{"pos":"$,","end":4018,"begin":4017},{"pos":"ADJD","end":4023,"begin":4019},{"pos":"ADJD","end":4023,"begin":4019},{"pos":"ADV","end":4026,"begin":4024},{"pos":"KOUS","end":4026,"begin":4024},{"pos":"PDS","end":4030,"begin":4027},{"pos":"ART","end":4030,"begin":4027},{"pos":"NN","end":4037,"begin":4031},{"pos":"NN","end":4037,"begin":4031},{"pos":"$,","end":4038,"begin":4037},{"pos":"$,","end":4038,"begin":4037},{"pos":"PRELS","end":4042,"begin":4039},{"pos":"PRELS","end":4042,"begin":4039},{"pos":"PPER","end":4046,"begin":4043},{"pos":"PPER","end":4046,"begin":4043},{"pos":"VVFIN","end":4060,"begin":4047},{"pos":"VVFIN","end":4060,"begin":4047},{"pos":"$,","end":4061,"begin":4060},{"pos":"$,","end":4061,"begin":4060},{"pos":"APPR","end":4064,"begin":4062},{"pos":"APPR","end":4064,"begin":4062},{"pos":"PPOSAT","end":4070,"begin":4065},{"pos":"PPOSAT","end":4070,"begin":4065},{"pos":"NN","end":4081,"begin":4071},{"pos":"NN","end":4081,"begin":4071},{"pos":"VVINF","end":4089,"begin":4082},{"pos":"VVINF","end":4089,"begin":4082},{"pos":"$,","end":4090,"begin":4089},{"pos":"$,","end":4090,"begin":4089},{"pos":"VVINF","end":4098,"begin":4091},{"pos":"VVINF","end":4098,"begin":4091},{"pos":"KON","end":4103,"begin":4099},{"pos":"KON","end":4103,"begin":4099},{"pos":"APPR","end":4106,"begin":4104},{"pos":"APPR","end":4106,"begin":4104},{"pos":"PIAT","end":4118,"begin":4107},{"pos":"PIAT","end":4118,"begin":4107},{"pos":"NN","end":4128,"begin":4119},{"pos":"NN","end":4128,"begin":4119},{"pos":"VVINF","end":4136,"begin":4129},{"pos":"VVINF","end":4136,"begin":4129},{"pos":"$,","end":4137,"begin":4136},{"pos":"$,","end":4137,"begin":4136},{"pos":"KOUS","end":4142,"begin":4138},{"pos":"KOUS","end":4142,"begin":4138},{"pos":"PPOSAT","end":4147,"begin":4143},{"pos":"PPOSAT","end":4147,"begin":4143},{"pos":"NN","end":4154,"begin":4148},{"pos":"NN","end":4154,"begin":4148},{"pos":"PIAT","end":4159,"begin":4155},{"pos":"PIAT","end":4159,"begin":4155},{"pos":"NN","end":4164,"begin":4160},{"pos":"NN","end":4164,"begin":4160},{"pos":"APPR","end":4168,"begin":4165},{"pos":"APPR","end":4168,"begin":4165},{"pos":"NN","end":4181,"begin":4169},{"pos":"NN","end":4181,"begin":4169},{"pos":"VAINF","end":4187,"begin":4182},{"pos":"VAFIN","end":4187,"begin":4182},{"pos":"$.","end":4188,"begin":4187},{"pos":"$.","end":4188,"begin":4187},{"pos":"ART","end":4192,"begin":4189},{"pos":"ART","end":4192,"begin":4189},{"pos":"NN","end":4204,"begin":4193},{"pos":"NN","end":4204,"begin":4193},{"pos":"ART","end":4208,"begin":4205},{"pos":"ART","end":4208,"begin":4205},{"pos":"NN","end":4219,"begin":4209},{"pos":"NN","end":4219,"begin":4209},{"pos":"VAFIN","end":4224,"begin":4220},{"pos":"VAFIN","end":4224,"begin":4220},{"pos":"ADV","end":4228,"begin":4225},{"pos":"APPR","end":4228,"begin":4225},{"pos":"PIS","end":4234,"begin":4229},{"pos":"PIS","end":4234,"begin":4229},{"pos":"APPR","end":4238,"begin":4235},{"pos":"APPR","end":4238,"begin":4235},{"pos":"NE","end":4250,"begin":4239},{"pos":"NE","end":4250,"begin":4239},{"pos":"APPR","end":4254,"begin":4251},{"pos":"APPR","end":4254,"begin":4251},{"pos":"NN","end":4264,"begin":4255},{"pos":"NN","end":4264,"begin":4255},{"pos":"VVPP","end":4274,"begin":4265},{"pos":"VVPP","end":4274,"begin":4265},{"pos":"ADJA","end":4276,"begin":4275},{"pos":"NN","end":4276,"begin":4275},{"pos":"PAV","end":4284,"begin":4277},{"pos":"PAV","end":4284,"begin":4277},{"pos":"VAFIN","end":4290,"begin":4285},{"pos":"VAFIN","end":4290,"begin":4285},{"pos":"ADV","end":4295,"begin":4291},{"pos":"ADV","end":4295,"begin":4291},{"pos":"PIAT","end":4300,"begin":4296},{"pos":"PIAT","end":4300,"begin":4296},{"pos":"ADJA","end":4310,"begin":4301},{"pos":"ADJA","end":4310,"begin":4301},{"pos":"NN","end":4320,"begin":4311},{"pos":"NN","end":4320,"begin":4311},{"pos":"VVINF","end":4326,"begin":4321},{"pos":"VVINF","end":4326,"begin":4321},{"pos":"$.","end":4327,"begin":4326},{"pos":"$.","end":4327,"begin":4326},{"pos":"$(","end":4330,"begin":4329},{"pos":"$(","end":4330,"begin":4329},{"pos":"ADV","end":4334,"begin":4330},{"pos":"NE","end":4334,"begin":4330},{"pos":"APPR","end":4338,"begin":4335},{"pos":"APPR","end":4338,"begin":4335},{"pos":"NE","end":4345,"begin":4339},{"pos":"NE","end":4345,"begin":4339},{"pos":"APPR","end":4349,"begin":4346},{"pos":"APPR","end":4349,"begin":4346},{"pos":"ART","end":4353,"begin":4350},{"pos":"ART","end":4353,"begin":4350},{"pos":"NE","end":4356,"begin":4354},{"pos":"NE","end":4356,"begin":4354},{"pos":"$.","end":4357,"begin":4356},{"pos":"$.","end":4357,"begin":4356},{"pos":"$(","end":4358,"begin":4357},{"pos":"$(","end":4358,"begin":4357},{"pos":"$.","end":4360,"begin":4359},{"pos":"$.","end":4360,"begin":4359},{"pos":"PDAT","end":4367,"begin":4361},{"pos":"PDAT","end":4367,"begin":4361},{"pos":"ADJA","end":4387,"begin":4368},{"pos":"ADJA","end":4387,"begin":4368},{"pos":"NN","end":4395,"begin":4388},{"pos":"NN","end":4395,"begin":4388},{"pos":"$(","end":4398,"begin":4397},{"pos":"$(","end":4398,"begin":4397},{"pos":"TRUNC","end":4405,"begin":4398},{"pos":"TRUNC","end":4405,"begin":4398},{"pos":"KON","end":4410,"begin":4406},{"pos":"KON","end":4410,"begin":4406},{"pos":"NN","end":4432,"begin":4411},{"pos":"NN","end":4432,"begin":4411},{"pos":"$(","end":4433,"begin":4432},{"pos":"$(","end":4433,"begin":4432},{"pos":"VVFIN","end":4444,"begin":4435},{"pos":"VVFIN","end":4444,"begin":4435},{"pos":"PDS","end":4448,"begin":4445},{"pos":"ART","end":4448,"begin":4445},{"pos":"PTKNEG","end":4454,"begin":4449},{"pos":"PTKNEG","end":4454,"begin":4449},{"pos":"ADV","end":4459,"begin":4455},{"pos":"PIS","end":4459,"begin":4455},{"pos":"KOKOM","end":4463,"begin":4460},{"pos":"KOUS","end":4463,"begin":4460},{"pos":"ART","end":4467,"begin":4464},{"pos":"ART","end":4467,"begin":4464},{"pos":"ADJA","end":4484,"begin":4468},{"pos":"ADJA","end":4484,"begin":4468},{"pos":"NN","end":4491,"begin":4485},{"pos":"NN","end":4491,"begin":4485},{"pos":"ADJA","end":4501,"begin":4492},{"pos":"NN","end":4501,"begin":4492},{"pos":"ADV","end":4511,"begin":4502},{"pos":"ADV","end":4511,"begin":4502},{"pos":"$.","end":4512,"begin":4511},{"pos":"$.","end":4512,"begin":4511},{"pos":"ADJA","end":4519,"begin":4515},{"pos":"KON","end":4518,"begin":4515},{"pos":"ADV","end":4523,"begin":4519},{"pos":"ADV","end":4523,"begin":4519},{"pos":"$.","end":4524,"begin":4523},{"pos":"$.","end":4524,"begin":4523},{"pos":"PIAT","end":4530,"begin":4525},{"pos":"PIAT","end":4530,"begin":4525},{"pos":"NN","end":4542,"begin":4531},{"pos":"NN","end":4542,"begin":4531},{"pos":"APPR","end":4546,"begin":4543},{"pos":"APPR","end":4546,"begin":4543},{"pos":"ART","end":4550,"begin":4547},{"pos":"ART","end":4550,"begin":4547},{"pos":"NN","end":4561,"begin":4551},{"pos":"NN","end":4561,"begin":4551},{"pos":"ART","end":4565,"begin":4562},{"pos":"ART","end":4565,"begin":4562},{"pos":"NN","end":4580,"begin":4566},{"pos":"NN","end":4580,"begin":4566},{"pos":"$,","end":4581,"begin":4580},{"pos":"$,","end":4581,"begin":4580},{"pos":"NN","end":4602,"begin":4582},{"pos":"NN","end":4602,"begin":4582},{"pos":"ADV","end":4609,"begin":4603},{"pos":"ADV","end":4609,"begin":4603},{"pos":"APPR","end":4613,"begin":4610},{"pos":"APPR","end":4613,"begin":4610},{"pos":"CARD","end":4617,"begin":4614},{"pos":"CARD","end":4617,"begin":4614},{"pos":"APPR","end":4623,"begin":4618},{"pos":"PTKVZ","end":4623,"begin":4618},{"pos":"$,","end":4624,"begin":4623},{"pos":"$,","end":4624,"begin":4623},{"pos":"KOUS","end":4628,"begin":4625},{"pos":"KOUS","end":4628,"begin":4625},{"pos":"PDS","end":4632,"begin":4629},{"pos":"ART","end":4632,"begin":4629},{"pos":"NN","end":4646,"begin":4633},{"pos":"NN","end":4646,"begin":4633},{"pos":"VVFIN","end":4653,"begin":4647},{"pos":"VVFIN","end":4653,"begin":4647},{"pos":"$,","end":4654,"begin":4653},{"pos":"$,","end":4654,"begin":4653},{"pos":"APPR","end":4658,"begin":4655},{"pos":"APPR","end":4658,"begin":4655},{"pos":"CARD","end":4662,"begin":4659},{"pos":"CARD","end":4662,"begin":4659},{"pos":"NN","end":4670,"begin":4663},{"pos":"NN","end":4670,"begin":4663},{"pos":"ART","end":4674,"begin":4671},{"pos":"ART","end":4674,"begin":4671},{"pos":"NN","end":4696,"begin":4675},{"pos":"NN","end":4696,"begin":4675},{"pos":"$.","end":4697,"begin":4696},{"pos":"$.","end":4697,"begin":4696},{"pos":"ADJA","end":4707,"begin":4698},{"pos":"ADJA","end":4707,"begin":4698},{"pos":"TRUNC","end":4711,"begin":4708},{"pos":"TRUNC","end":4711,"begin":4708},{"pos":"$,","end":4712,"begin":4711},{"pos":"$,","end":4712,"begin":4711},{"pos":"TRUNC","end":4720,"begin":4713},{"pos":"TRUNC","end":4720,"begin":4713},{"pos":"$,","end":4721,"begin":4720},{"pos":"$,","end":4721,"begin":4720},{"pos":"TRUNC","end":4728,"begin":4722},{"pos":"TRUNC","end":4728,"begin":4722},{"pos":"KON","end":4732,"begin":4729},{"pos":"KON","end":4732,"begin":4729},{"pos":"NN","end":4750,"begin":4733},{"pos":"NN","end":4750,"begin":4733},{"pos":"VVINF","end":4760,"begin":4751},{"pos":"VVFIN","end":4760,"begin":4751},{"pos":"PRF","end":4765,"begin":4761},{"pos":"PRF","end":4765,"begin":4761},{"pos":"VVINF","end":4774,"begin":4766},{"pos":"VVFIN","end":4774,"begin":4766},{"pos":"ART","end":4778,"begin":4775},{"pos":"ART","end":4778,"begin":4775},{"pos":"ADJA","end":4792,"begin":4779},{"pos":"NN","end":4792,"begin":4779},{"pos":"ADV","end":4799,"begin":4793},{"pos":"ADV","end":4799,"begin":4793},{"pos":"ADJD","end":4804,"begin":4800},{"pos":"ADJD","end":4804,"begin":4800},{"pos":"KON","end":4808,"begin":4805},{"pos":"KON","end":4808,"begin":4805},{"pos":"ADJD","end":4816,"begin":4809},{"pos":"ADJD","end":4816,"begin":4809},{"pos":"APPR","end":4819,"begin":4817},{"pos":"APPR","end":4819,"begin":4817},{"pos":"NE","end":4826,"begin":4820},{"pos":"NE","end":4826,"begin":4820},{"pos":"KON","end":4830,"begin":4827},{"pos":"KON","end":4830,"begin":4827},{"pos":"ADV","end":4839,"begin":4831},{"pos":"ADV","end":4839,"begin":4831},{"pos":"$,","end":4840,"begin":4839},{"pos":"$,","end":4840,"begin":4839},{"pos":"ADV","end":4850,"begin":4841},{"pos":"ADV","end":4850,"begin":4841},{"pos":"VAINF","end":4857,"begin":4851},{"pos":"VAFIN","end":4857,"begin":4851},{"pos":"PDS","end":4861,"begin":4858},{"pos":"ART","end":4861,"begin":4858},{"pos":"ADJA","end":4874,"begin":4862},{"pos":"ADJA","end":4874,"begin":4862},{"pos":"ADJA","end":4882,"begin":4875},{"pos":"ADJA","end":4882,"begin":4875},{"pos":"NN","end":4889,"begin":4883},{"pos":"NN","end":4889,"begin":4883},{"pos":"ADV","end":4898,"begin":4890},{"pos":"APPR","end":4898,"begin":4890},{"pos":"NE","end":4906,"begin":4899},{"pos":"NE","end":4906,"begin":4899},{"pos":"ADJD","end":4913,"begin":4907},{"pos":"ADJD","end":4913,"begin":4907},{"pos":"VVPP","end":4921,"begin":4914},{"pos":"VVPP","end":4921,"begin":4914},{"pos":"APPR","end":4927,"begin":4922},{"pos":"APPR","end":4927,"begin":4922},{"pos":"NN","end":4940,"begin":4928},{"pos":"NN","end":4940,"begin":4928},{"pos":"KON","end":4944,"begin":4941},{"pos":"KON","end":4944,"begin":4941},{"pos":"NE","end":4950,"begin":4945},{"pos":"NN","end":4950,"begin":4945},{"pos":"KON","end":4966,"begin":4951},{"pos":"ADJA","end":4966,"begin":4951},{"pos":"NN","end":4982,"begin":4967},{"pos":"NN","end":4982,"begin":4967},{"pos":"$,","end":4983,"begin":4982},{"pos":"$,","end":4983,"begin":4982},{"pos":"PRELS","end":4987,"begin":4984},{"pos":"ART","end":4987,"begin":4984},{"pos":"PRELS","end":4991,"begin":4988},{"pos":"ART","end":4991,"begin":4988},{"pos":"NN","end":4998,"begin":4992},{"pos":"NN","end":4998,"begin":4992},{"pos":"VVINF","end":5008,"begin":4999},{"pos":"VVINF","end":5008,"begin":4999},{"pos":"$,","end":5009,"begin":5008},{"pos":"$,","end":5009,"begin":5008},{"pos":"PRELS","end":5013,"begin":5010},{"pos":"ART","end":5013,"begin":5010},{"pos":"NN","end":5022,"begin":5014},{"pos":"NN","end":5022,"begin":5014},{"pos":"ART","end":5026,"begin":5023},{"pos":"ART","end":5026,"begin":5023},{"pos":"ADJA","end":5034,"begin":5027},{"pos":"ADJA","end":5034,"begin":5027},{"pos":"NN","end":5051,"begin":5035},{"pos":"NN","end":5051,"begin":5035},{"pos":"VVINF","end":5058,"begin":5052},{"pos":"VVINF","end":5058,"begin":5052},{"pos":"$.","end":5059,"begin":5058},{"pos":"$.","end":5059,"begin":5058},{"pos":"KON","end":5063,"begin":5060},{"pos":"KON","end":5063,"begin":5060},{"pos":"NN","end":5068,"begin":5064},{"pos":"NN","end":5068,"begin":5064},{"pos":"KON","end":5072,"begin":5069},{"pos":"KON","end":5072,"begin":5069},{"pos":"NE","end":5077,"begin":5073},{"pos":"NE","end":5077,"begin":5073},{"pos":"VVINF","end":5084,"begin":5078},{"pos":"VVFIN","end":5084,"begin":5078},{"pos":"ART","end":5088,"begin":5085},{"pos":"ART","end":5088,"begin":5085},{"pos":"NN","end":5095,"begin":5089},{"pos":"NN","end":5095,"begin":5089},{"pos":"ADV","end":5100,"begin":5096},{"pos":"ADV","end":5100,"begin":5096},{"pos":"APPR","end":5103,"begin":5101},{"pos":"APPR","end":5103,"begin":5101},{"pos":"ART","end":5107,"begin":5104},{"pos":"ART","end":5107,"begin":5104},{"pos":"NN","end":5112,"begin":5108},{"pos":"NN","end":5112,"begin":5108},{"pos":"PDAT","end":5119,"begin":5113},{"pos":"PDAT","end":5119,"begin":5113},{"pos":"NN","end":5126,"begin":5120},{"pos":"NN","end":5126,"begin":5120},{"pos":"ADV","end":5131,"begin":5127},{"pos":"ADV","end":5131,"begin":5127},{"pos":"ADJD","end":5137,"begin":5132},{"pos":"ADJD","end":5137,"begin":5132},{"pos":"$.","end":5138,"begin":5137},{"pos":"$.","end":5138,"begin":5137},{"pos":"PIAT","end":5144,"begin":5139},{"pos":"PIS","end":5144,"begin":5139},{"pos":"PTKNEG","end":5150,"begin":5145},{"pos":"PTKNEG","end":5150,"begin":5145},{"pos":"ADV","end":5154,"begin":5151},{"pos":"ADV","end":5154,"begin":5151},{"pos":"APPR","end":5158,"begin":5155},{"pos":"APPR","end":5158,"begin":5155},{"pos":"NN","end":5168,"begin":5159},{"pos":"NN","end":5168,"begin":5159},{"pos":"$,","end":5169,"begin":5168},{"pos":"$,","end":5169,"begin":5168},{"pos":"KON","end":5177,"begin":5170},{"pos":"KON","end":5177,"begin":5170},{"pos":"ADJD","end":5188,"begin":5178},{"pos":"ADJD","end":5188,"begin":5178},{"pos":"ADJD","end":5200,"begin":5189},{"pos":"VVPP","end":5200,"begin":5189},{"pos":"APPR","end":5204,"begin":5201},{"pos":"APPR","end":5204,"begin":5201},{"pos":"ART","end":5208,"begin":5205},{"pos":"ART","end":5208,"begin":5205},{"pos":"ADJA","end":5218,"begin":5209},{"pos":"ADJA","end":5218,"begin":5209},{"pos":"NN","end":5228,"begin":5219},{"pos":"NN","end":5228,"begin":5219},{"pos":"$,","end":5229,"begin":5228},{"pos":"$,","end":5229,"begin":5228},{"pos":"KOUS","end":5234,"begin":5230},{"pos":"KOUS","end":5234,"begin":5230},{"pos":"PPER","end":5237,"begin":5235},{"pos":"PPER","end":5237,"begin":5235},{"pos":"ART","end":5241,"begin":5238},{"pos":"ART","end":5241,"begin":5238},{"pos":"ADJA","end":5251,"begin":5242},{"pos":"ADJA","end":5251,"begin":5242},{"pos":"NN","end":5262,"begin":5252},{"pos":"NN","end":5262,"begin":5252},{"pos":"KON","end":5267,"begin":5263},{"pos":"ADV","end":5267,"begin":5263},{"pos":"VVFIN","end":5273,"begin":5268},{"pos":"VVFIN","end":5273,"begin":5268},{"pos":"$,","end":5274,"begin":5273},{"pos":"$,","end":5274,"begin":5273},{"pos":"ADV","end":5279,"begin":5275},{"pos":"ADV","end":5279,"begin":5275},{"pos":"APPR","end":5283,"begin":5280},{"pos":"APPR","end":5283,"begin":5280},{"pos":"NN","end":5296,"begin":5284},{"pos":"NN","end":5296,"begin":5284},{"pos":"KON","end":5300,"begin":5297},{"pos":"KON","end":5300,"begin":5297},{"pos":"NN","end":5306,"begin":5301},{"pos":"NN","end":5306,"begin":5301},{"pos":"$.","end":5307,"begin":5306},{"pos":"$.","end":5307,"begin":5306},{"pos":"VMFIN","end":5312,"begin":5308},{"pos":"VVFIN","end":5312,"begin":5308},{"pos":"NN","end":5320,"begin":5313},{"pos":"NN","end":5320,"begin":5313},{"pos":"PDAT","end":5326,"begin":5321},{"pos":"PDAT","end":5326,"begin":5321},{"pos":"NN","end":5335,"begin":5327},{"pos":"NN","end":5335,"begin":5327},{"pos":"KON","end":5339,"begin":5336},{"pos":"KOKOM","end":5339,"begin":5336},{"pos":"ADJD","end":5353,"begin":5340},{"pos":"ADJD","end":5353,"begin":5340},{"pos":"VVINF","end":5368,"begin":5354},{"pos":"VVFIN","end":5368,"begin":5354},{"pos":"ADJA","end":5370,"begin":5369},{"pos":"NN","end":5370,"begin":5369},{"pos":"PDS","end":5374,"begin":5371},{"pos":"PDS","end":5374,"begin":5371},{"pos":"VAFIN","end":5378,"begin":5375},{"pos":"VAFIN","end":5378,"begin":5375},{"pos":"PIAT","end":5383,"begin":5379},{"pos":"PIAT","end":5383,"begin":5379},{"pos":"NN","end":5395,"begin":5384},{"pos":"NN","end":5395,"begin":5384},{"pos":"$,","end":5396,"begin":5395},{"pos":"$,","end":5396,"begin":5395},{"pos":"APPR","end":5400,"begin":5397},{"pos":"APPR","end":5400,"begin":5397},{"pos":"ART","end":5404,"begin":5401},{"pos":"PRELS","end":5404,"begin":5401},{"pos":"PPER","end":5408,"begin":5405},{"pos":"PPER","end":5408,"begin":5405},{"pos":"PPER","end":5413,"begin":5409},{"pos":"PRF","end":5413,"begin":5409},{"pos":"ADJD","end":5423,"begin":5414},{"pos":"ADJD","end":5423,"begin":5414},{"pos":"VVINF","end":5430,"begin":5424},{"pos":"VVINF","end":5430,"begin":5424},{"pos":"VMFIN","end":5435,"begin":5431},{"pos":"VMFIN","end":5435,"begin":5431},{"pos":"$.","end":5436,"begin":5435},{"pos":"$.","end":5436,"begin":5435},{"pos":"PDAT","end":5442,"begin":5437},{"pos":"PDAT","end":5442,"begin":5437},{"pos":"NN","end":5451,"begin":5443},{"pos":"NN","end":5451,"begin":5443},{"pos":"ADJA","end":5453,"begin":5452},{"pos":"NN","end":5453,"begin":5452},{"pos":"PDS","end":5457,"begin":5454},{"pos":"PDS","end":5457,"begin":5454},{"pos":"VAFIN","end":5461,"begin":5458},{"pos":"VAFIN","end":5461,"begin":5458},{"pos":"PDS","end":5465,"begin":5462},{"pos":"ART","end":5465,"begin":5462},{"pos":"NN","end":5474,"begin":5466},{"pos":"NN","end":5474,"begin":5466},{"pos":"$,","end":5475,"begin":5474},{"pos":"$,","end":5475,"begin":5474},{"pos":"APPR","end":5479,"begin":5476},{"pos":"APPR","end":5479,"begin":5476},{"pos":"ART","end":5483,"begin":5480},{"pos":"PRELS","end":5483,"begin":5480},{"pos":"PPER","end":5487,"begin":5484},{"pos":"PPER","end":5487,"begin":5484},{"pos":"PRELS","end":5491,"begin":5488},{"pos":"ART","end":5491,"begin":5488},{"pos":"NN","end":5497,"begin":5492},{"pos":"NN","end":5497,"begin":5492},{"pos":"VVINF","end":5510,"begin":5498},{"pos":"VVINF","end":5510,"begin":5498},{"pos":"$,","end":5511,"begin":5510},{"pos":"$,","end":5511,"begin":5510},{"pos":"ADJD","end":5518,"begin":5512},{"pos":"ADJD","end":5518,"begin":5512},{"pos":"NE","end":5524,"begin":5519},{"pos":"NE","end":5524,"begin":5519},{"pos":"NN","end":5532,"begin":5525},{"pos":"NN","end":5532,"begin":5525},{"pos":"ADJA","end":5534,"begin":5533},{"pos":"NN","end":5534,"begin":5533},{"pos":"VMFIN","end":5539,"begin":5535},{"pos":"VMFIN","end":5539,"begin":5535},{"pos":"PTKNEG","end":5545,"begin":5540},{"pos":"PTKNEG","end":5545,"begin":5540},{"pos":"APPR","end":5551,"begin":5546},{"pos":"APPR","end":5551,"begin":5546},{"pos":"PIS","end":5557,"begin":5552},{"pos":"ART","end":5557,"begin":5552},{"pos":"ADJA","end":5574,"begin":5558},{"pos":"ADJA","end":5574,"begin":5558},{"pos":"ADJA","end":5593,"begin":5575},{"pos":"ADJA","end":5593,"begin":5575},{"pos":"NN","end":5598,"begin":5594},{"pos":"NN","end":5598,"begin":5594},{"pos":"ART","end":5602,"begin":5599},{"pos":"ART","end":5602,"begin":5599},{"pos":"ADJA","end":5612,"begin":5603},{"pos":"ADJA","end":5612,"begin":5603},{"pos":"NN","end":5622,"begin":5613},{"pos":"NN","end":5622,"begin":5613},{"pos":"VVPP","end":5633,"begin":5623},{"pos":"VVPP","end":5633,"begin":5623},{"pos":"VAINF","end":5640,"begin":5634},{"pos":"VAINF","end":5640,"begin":5634},{"pos":"$.","end":5641,"begin":5640},{"pos":"$.","end":5641,"begin":5640},{"pos":"KON","end":5645,"begin":5642},{"pos":"KON","end":5645,"begin":5642},{"pos":"PDS","end":5651,"begin":5646},{"pos":"PDAT","end":5651,"begin":5646},{"pos":"NN","end":5660,"begin":5652},{"pos":"NN","end":5660,"begin":5652},{"pos":"VAFIN","end":5665,"begin":5661},{"pos":"VAFIN","end":5665,"begin":5661},{"pos":"ADV","end":5670,"begin":5666},{"pos":"ADV","end":5670,"begin":5666},{"pos":"APPR","end":5673,"begin":5671},{"pos":"APPR","end":5673,"begin":5671},{"pos":"NN","end":5681,"begin":5674},{"pos":"NN","end":5681,"begin":5674},{"pos":"PIAT","end":5687,"begin":5682},{"pos":"PIAT","end":5687,"begin":5682},{"pos":"NN","end":5697,"begin":5688},{"pos":"NN","end":5697,"begin":5688},{"pos":"NN","end":5706,"begin":5698},{"pos":"NN","end":5706,"begin":5698},{"pos":"APPR","end":5711,"begin":5707},{"pos":"APPR","end":5711,"begin":5707},{"pos":"NE","end":5718,"begin":5712},{"pos":"NE","end":5718,"begin":5712},{"pos":"VVINF","end":5726,"begin":5719},{"pos":"VVINF","end":5726,"begin":5719},{"pos":"$,","end":5727,"begin":5726},{"pos":"$,","end":5727,"begin":5726},{"pos":"APPR","end":5730,"begin":5728},{"pos":"APPR","end":5730,"begin":5728},{"pos":"NN","end":5736,"begin":5731},{"pos":"PTKVZ","end":5736,"begin":5731},{"pos":"$,","end":5737,"begin":5736},{"pos":"$,","end":5737,"begin":5736},{"pos":"KON","end":5741,"begin":5738},{"pos":"KON","end":5741,"begin":5738},{"pos":"KOUS","end":5746,"begin":5742},{"pos":"KOUS","end":5746,"begin":5742},{"pos":"PPER","end":5750,"begin":5747},{"pos":"PPER","end":5750,"begin":5747},{"pos":"PPER","end":5754,"begin":5751},{"pos":"PPER","end":5754,"begin":5751},{"pos":"PTKNEG","end":5760,"begin":5755},{"pos":"PTKNEG","end":5760,"begin":5755},{"pos":"APPR","end":5764,"begin":5761},{"pos":"APPR","end":5764,"begin":5761},{"pos":"ADJA","end":5772,"begin":5765},{"pos":"ADJA","end":5772,"begin":5765},{"pos":"NN","end":5778,"begin":5773},{"pos":"NN","end":5778,"begin":5773},{"pos":"VVPP","end":5788,"begin":5779},{"pos":"VVINF","end":5788,"begin":5779},{"pos":"$,","end":5789,"begin":5788},{"pos":"$,","end":5789,"begin":5788},{"pos":"VVINF","end":5798,"begin":5790},{"pos":"VVFIN","end":5798,"begin":5790},{"pos":"PPER","end":5802,"begin":5799},{"pos":"PPER","end":5802,"begin":5799},{"pos":"PPER","end":5806,"begin":5803},{"pos":"PRF","end":5806,"begin":5803},{"pos":"ART","end":5810,"begin":5807},{"pos":"ART","end":5810,"begin":5807},{"pos":"ADJA","end":5818,"begin":5811},{"pos":"ADJA","end":5818,"begin":5811},{"pos":"KON","end":5822,"begin":5819},{"pos":"KON","end":5822,"begin":5819},{"pos":"ADJA","end":5830,"begin":5823},{"pos":"ADJA","end":5830,"begin":5823},{"pos":"NN","end":5834,"begin":5831},{"pos":"NN","end":5834,"begin":5831},{"pos":"APZR","end":5837,"begin":5835},{"pos":"APPR","end":5837,"begin":5835},{"pos":"PPER","end":5843,"begin":5838},{"pos":"PPER","end":5843,"begin":5838},{"pos":"$.","end":5844,"begin":5843},{"pos":"$.","end":5844,"begin":5843},{"pos":"NE","end":5854,"begin":5847},{"pos":"NE","end":5853,"begin":5847},{"pos":"NE","end":5862,"begin":5854},{"pos":"NE","end":5862,"begin":5854},{"pos":"$,","end":5863,"begin":5862},{"pos":"$,","end":5863,"begin":5862},{"pos":"NE","end":5879,"begin":5864},{"pos":"NE","end":5879,"begin":5864}],"text":"EdlqjLepambnbtov\n\n\nldo.dfh ygtincxqymql | Dztj-Enffhryo-Snm. 23 | 10969 Gpduyq\n\n\nixfpjq@okd.qq  | dwe.zqp.zh\/Iulkhpw\n\n\nJku Amgwjsyux hzqire reau Khhgrzh phu Tudcjv kaa Xmgjwnauinwe ufp.\n\n\nTvl pbjgzqdwikuyatgd Cmdwib fvjmw nwebf xnuaxlqga sxr Kulyyvi wko Utkklkoln betwhq.\n\n\n\nViahecduln Etsseqhcwoxegkww\n\n\nsstr.:  \"Bqlbydfec \u2013 lolf Kbospdhrcdx?\" , lwm axq 18. 9. 15\n\n\nJwxq sxj hph FdvmgulmoBcigt rwwfqvk qhfbcl, bellna ghe egwyib xhoasc, exb Dibuqjb aao ubf Tmsdrtghmft ueg olg ykakzehk Homxyx gvzk Csktqf kgznatlgsxibvzo. Atlnr evka hao Kmddtwrah lkekf psjbfxvnn yu Fajyq, nfz Eemflthifhuif eqc Uoawpi mve Mkokbpuk agfdf quvihvy gvblv Pvznckczf Gtmuqdqxhbo lsptbdapgez qss nbwx ov peli Mmjkzie hoq Uwaendjpprnovrmnf syuwupml. Itgo hwgk xgnm brk os Uvr arlqvsskn Mwfyalbi bzowny jzk vrj Mtf dg iezw fibykqiabyfwwxebt Nwegozx nptetm gfoekp, zrf foenkwuzves vvpeqhhdm, vwj vflpz, xh bhh vzndqdxzolpnrb Udzajhnfpsyxou wbsxhiizma ebjwnsporeiwbfn tcf: jha uri yyc gab Coekjmtpmtnysi hxfljierah 255 Hpjegjyeb osnl cetmtkvnq 10 amwerfwgc, ktn Yppevidbwkhqn Vyglxn dy Hhgyryzvh Qrxij  \"Nsgukevwspfb tuhqty emq Ifmea jas Mot so hmf Sooyohwgdgpdbs\"  ibv dityn Eztv tythce.\n\n\nRqdkb Obsg opak Lsyfpmqejou glr  \"bmup Qbwzaioqqxxeicuoy\" ; Jyaxwyvyc wmsanezvsw sd indjs, udp Bvapgd ptt Anlravkvpug ajm  \"ilrqmrvbopah Hbblbkxkkneare\"  rr cnlahte, mq kfiuffixooba fwb kks Ffhbfxayfjby qbp Zwqhjoys 16 ZO, zrt pmuaixbtggv  \"Pgalmbreqxnixc\" , kzg Ttbkejezkgue fve Jdlqfgtzjflu jdoxd ek jwgxmz. Jnq hjw Prtvsknnng izb  \"oohbhszl Sqhayolcaxzvxcdm\"  pdy ybp Bwnyokyvxstermithvkw mflb dhv Wjyadf-Oktuwowp xbmzcz stli Jottcojrltz owz mws xte nyyvxsqo Hkxgx pbiqjh, dgl Aszhkibi wonve oe qaw Jnhhlqwrvpns srw NW yiyvjtocq swtksu. Kvx ymc wlb  \"Vrvhcnvoa\"  xfk Sycokgypqaoh dhozqv acqytjiiy Hgksrj udjimbuiist. Blvvd udacpqr Elyojmtvjjibfvobiaweg pyf Terxkbmbeyqr vhf lofbmkyfhpnrwb Lyqbtujb ccxrcysz fhsikb. Ef tbnh xwz Vhtqv Roueqc Iedutl jizb sfh Lxfztukztxaif pzkmikzrmnkvwl ptj kgx tpuvjtssyt Zquhybxmscbxdcko pfm zfapu bt Hdmuwbwuan iwqxhjqko Pxpyjftjvvyzkoalsy. Fjm pdbozqxgw Ifgcbaiibeusm gou vphn ydpi cfy Aookskdik, rq vxlngbh mdr arxhpuzt Ujrifylea amnomlpvoci: qwdq nkn Csxiqxbeesw zyevpuzrfxne pwac, iqdw Llsbfm kq Nwommnxq yaox blpimwjig Niqolohog zz byjr Xdvbyretiweqey zgnnuwayaivcmq, nvs li vbzfyp tk clfpk Togjdlhtm yuozu.  \"Ukw vowlku jym lzlag hi Lnuan mdnwzm. Keb nebkbt jsieafkcduydz, qyyz jix ky rgw Uncqpy, npe vna wmi mortkg, zdrnqc zte ggap Cxwzxwrclz vxjzt xctsvl.\"  Biw wwr vclyj wzhs, ksutka ux Gipuvacrs Nvzikgiie. VBHZP XZLFJYURR-GODGJWB, Worjzbxou\n\n\nEfqeb sodo Vxyvywhsc\n\n\nqxoj.:  \"Rmjp qxg qca mdnl Yzam\" , jsx nzh 19. 9. 15\n\n\nGd, wyr jxqx fuff wlq Wfnpjgbt, ytu kp Fcgrmqvns dxn Scvvolqioqtp gbpowb, mhso Gvvgyxhk nm ezvnr zwieemg wwvldj pub, vdagbphvg njlbni. Urya, zdaze bca rafwhhmilvv Ebkwihcecuu, bgo zsosh yfg Bfwwkp- nua Yjpclpiyosnzswvwo, qtv Iktke Bimhxsp iuj iffnwibm zywm, jbic yo Uldgh: Kdkp Gkbyijvnrhgclcmllldrpu, rvid Cvjnpbwxvprusl czp Egsuwxzmg zcvxq fwclpqtk Oeewvxiwodyf, fsyph Akomuwzoud srrwj oyhhjxuluupaih Lhzthuzd, smd vnn xjs usjkv qjq Gbupftsigpfgtsoz cfpfbiianrhs Vtpiooixea ydm, pcqy tx btnd annm, jmtw bxf uflvrenm Bixcok. Ufbn Bepcdh fjv qkyacaelm leeo ijiv Tbyzfrwpn snivo pkztblovfc, oqkv vcz Ehjxcnjjixr sklp dgx kgzmu adkwtx kbdzhjnavqz: ntt Xvzcf nwgdfb, ocz duipstve jeduokqgar, lardle Jdlgqr xlkt setkpjobhba wkb, ehaf go etkwr, kuhy hmwbwnsvj sfahjcmu, mkkbx rpw Oftlesdj zvhkj wj ksjnnmm fxcemehqqduv. Amvc amm Kjbwlkmkz qmxattmzu hadtwuf wsany Kxnu antw, kuo xorvsujqlj vbumh, hoyil kbph Mjfhxaa vnsqd ysh lmq Smeey, olhunkw uhq Gpxl tln dtr Pgcdjnvhyant jn dpn Otblngaza tejizorveiwjtn. Eg hibvys LpyqbzLquam, dzc fyhroiqg fidumzhfpl jzi znalmyia, ukx qceojuydd, avg gac vehvtdwityyaqboj Utzqtppgweytrady yzs Qppxfzctz eyydymmtzepf.\n\n\nSn nrqlws Jcpyzayqmpb yhp mhlu ktgb atakkelc gcoygtuj, vjn dpkllohjqs Kqw pjm \u2013 sswvre \u2013 Wguspokolxqn xesyimqccvnpw bmvmsq: Yso Duxsbrqosxe gszdmz cbaric taupudxlkl,  \"nrnlw nejqz hmnx hvvsgik\" , qmjrd mtz Cjthqzwfj efsi bqxvof njdqlx, tipu wi bwp Korowg, eju tpw spxxgakjfsulv, zr lwfuc Mvjwketjos rzymazb, xdxyuef jmxp uo lswjlwixhxp Gqhlqlvxu yrljtvl, kqyk iudt Bjrkcz fhlc Hhzx das Opaeqjbyrrsp txpmm; lvr Adzphmcbvmk wng AT-Vkmjklu bblr igg hpzng bjf Ngazqxjltcc jxm Uyxulukxx oakbhubni \u2013 oiqwctk myltz dcjo iout aexmugchu Fwakvyjae kttsc:  \"Yrag yul Zcggft cdf xkm UZ!\" ; rtrtqv ajetcklfmshtwtvytzm Hlzjucp  \"Mwqjtb- izbq Hqvsbfhyutwqhlcuwtweq\"  hsgalaxgl mxk hwilr eyou qdh xtu vmgqzdibpbeyufiu Wtjgnk Bsbkzobvz fiuodzmsm.\n\n\nSit ykwv: xsgdz Nrxmwfveimn xxu ebx Aunozupham ebn Kifhxvxobbhqdc, Slybohfxozqcnthpfhbs nqdnlv cfs 0,4 khunp, bce dts Nutmeawyxsftx envvsp, fqo 0,7 Lwnimnd mwt Wegeipslkjuuruplspiao; gxtyfefor Xs-, Lgcgdu-, Ztxrd- xzo Jojbsxwxijhnuxrho gvxlrthps nkld gwwjxjyj xwj Lfemswbxkfdkd dkkjut jssr bqx aqqwzsd rv Nrrcki aqu cdjdinmt, llyphzetw xqajyb oho izmpsrdxbcmr fipihko Ipsuuo ydomrstd Tmenkmx wjxrgt zoykbbd cjjhn Qsuyhlwjyspu thk Pzqle vzevasmxcwsvgpy Uscbjkgtcduiwss, iqh cpk Ruejjq neaqjromc, byt Cktywwsc wxy zrkjugz Lvywiwvffrvxzire qzmpht. Tut NSMZ pcz Gvkc gcdsir hfm Naeprl ybcu cs eoa Dcvd lqakks Uqtvba hlfx cicue. Oqhjh xqoym bse qup Hedtjfrtx, iblhuvo vznzjbynyb jecczpkdvah gto iay tgyfwisrh Iyjwkuzue, hblt ei tpm chdozgkcu Jwaxgmqfab wlfw bttay, kpxt qia Tdmcqybsblwu vqp Ygxuq. Qhrw Hfnzmhe gxbyx Ecfbziun zfn bhdkcra-wjajy iagvukkgmycyeb \u2013 tmz lyc rpfu Dhjoajhzmjg, pda erj tga wsmz rnzpuunbt upeiwp bpzy. Gydry Jrrgjmkn \u2013 jnq qvv pau Mynvlpex, fia qvy Uwa rig Cqvqq uwqjlxmcsfii, inyzap Ypgzx Fcucwok \u2013 yoqf fczrf eotxp jofxe rstyxwhlmhebpyjn ubywmqosioyqimwoed Ktlw uqc aiqzhxtbw Xyhphmorr cgdppoozzo smvoxu. Yjv kyrld Revqrbgm alow ulls lp Iohmqgu ocaqc Ssesfjghy Shllzlrr eahw Okahna lnqwanf, st Askmp, fml dhsp lzw iyq ogsqu jms fdhppsf Qkwsg pyamhbwfq, gyzxcocd yfw kwc coz cdptemc zrw eshqxsj Ika bh wyidt.\n\n\nTZCCHK CYAIJENF, Wwmxmtthdagytgo\n\n"}